Workbook

Sheet Raw Comps
B1: RAW RENT COMPS — COMPARABLE LISTINGS
B2: API-ingested comp data. Do not edit manually — refreshed automatically on import.
B3: # | C3: Purchase Price | D3: Improvements | E3: rank | F3: distance_m | G3: distance_km | H3: filter_beds | I3: filter_baths | J3: type | K3: formattedAddress | L3: price | M3: bedrooms | N3: bathrooms | O3: squareFootage | P3: propertyType | Q3: listing_status | R3: daysOnMarket | S3: latitude | T3: longitude | U3: url | V3: id
B4: 1 | E4: 1 | F4: 5400 | G4: 5.4 | H4: 2 | I4: 2 | K4: 40 Harrison St, Unit 32HI, New York, NY 10013 | L4: 8095 | M4: 2 | N4: 2 | P4: Apartment | Q4: Active | R4: 1 | S4: 40.718975 | T4: -74.010757 | V4: 40-Harrison-St,-Unit-32HI,-New-York,-NY-10013
B5: 2 | E5: 2 | F5: 5432 | G5: 5.432 | H5: 2 | I5: 2 | K5: 80 N Moore St, Unit 36LM, New York, NY 10013 | L5: 8295 | M5: 2 | N5: 2 | P5: Apartment | Q5: Active | R5: 1 | S5: 40.719585 | T5: -74.010941 | V5: 80-N-Moore-St,-Unit-36LM,-New-York,-NY-10013
B6: 3 | E6: 3 | F6: 5502 | G6: 5.502 | H6: 2 | I6: 2 | K6: 201-205 W 11th St, Unit F, New York, NY 10014 | L6: 6600 | M6: 2 | N6: 2 | O6: 630 | P6: Apartment | Q6: Active | R6: 1 | S6: 40.73661 | T6: -74.001289 | V6: 201-205-W-11th-St,-Unit-F,-New-York,-NY-10014
B7: 4 | E7: 4 | F7: 7146 | G7: 7.146 | H7: 2 | I7: 2 | K7: 435 E 79th St, Unit 11, New York, NY 10075 | L7: 7100 | M7: 2 | N7: 2 | O7: 1145 | P7: Apartment | Q7: Active | R7: 1 | S7: 40.77174 | T7: -73.950729 | V7: 435-E-79th-St,-Unit-11,-New-York,-NY-10075
B8: 5 | E8: 5 | F8: 9049 | G8: 9.049 | H8: 2 | I8: 2 | K8: 120 W 86th St, Unit B, New York, NY 10024 | L8: 7600 | M8: 2 | N8: 2 | P8: Apartment | Q8: Active | R8: 1 | S8: 40.786713 | T8: -73.973106 | V8: 120-W-86th-St,-Unit-B,-New-York,-NY-10024

Sheet Rent Assumptions
B1: RENT ASSUMPTIONS — COMP-BASED UNIT MIX
B2: Search ID | C2: SRCH-20260225-002 | D2: Subject Lat | E2: 27.994007 | F2: Radius (mi) | G2: 5
B3: Email | C3: nikomoutop10@gmail.com | D3: Subject Long | E3: -82.467783 | F3: Max Comps | G3: 20
B4: Status | C4: Active | D4: Filter Combos | E4: 1 | F4: Selected Filter | G4: 1x1
B5: RENT ASSUMPTIONS — COMP-BASED UNIT MIX
B6: Auto-populated from Raw Comps tab. Aggregated by bed/bath type for use in Assumptions.
B7: Unit Type | C7: Beds | D7: Baths | E7: Count | F7: Model Inputs | G7: Avg SF | H7: Avg Rent / Mo ($)
B8: =IF(OR(E8=0,E8=""),"",C8&"BR/"&D8&"BA") | C8: {=_xlfn._xlws.SORT(_xlfn.UNIQUE(_xlfn._xlws.FILTER('Raw Comps'!$J$4:$K$998,'Raw Comps'!$J$4:$J$998<>"")),1,1)} -> #VALUE! | E8: =IF(D8=0,"",COUNTIFS('Raw Comps'!$J$3:$J$998,C8,'Raw Comps'!$K$3:$K$998,D8)) | G8: =IFERROR(AVERAGEIFS('Raw Comps'!$L$3:$L$998,'Raw Comps'!$J$3:$J$998,C8,'Raw Comps'!$K$3:$K$998,D8),"") | H8: =IFERROR(AVERAGEIFS('Raw Comps'!$I$3:$I$998,'Raw Comps'!$J$3:$J$998,C8,'Raw Comps'!$K$3:$K$998,D8),"")
B9: =IF(OR(E9=0,E9=""),"",C9&"BR/"&D9&"BA") | E9: =IF(D9=0,"",COUNTIFS('Raw Comps'!$J$3:$J$998,C9,'Raw Comps'!$K$3:$K$998,D9)) | G9: =IFERROR(AVERAGEIFS('Raw Comps'!$L$3:$L$998,'Raw Comps'!$J$3:$J$998,C9,'Raw Comps'!$K$3:$K$998,D9),"") | H9: =IFERROR(AVERAGEIFS('Raw Comps'!$I$3:$I$998,'Raw Comps'!$J$3:$J$998,C9,'Raw Comps'!$K$3:$K$998,D9),"")
B10: =IF(OR(E10=0,E10=""),"",C10&"BR/"&D10&"BA") | E10: =IF(D10=0,"",COUNTIFS('Raw Comps'!$J$3:$J$998,C10,'Raw Comps'!$K$3:$K$998,D10)) | G10: =IFERROR(AVERAGEIFS('Raw Comps'!$L$3:$L$998,'Raw Comps'!$J$3:$J$998,C10,'Raw Comps'!$K$3:$K$998,D10),"") | H10: =IFERROR(AVERAGEIFS('Raw Comps'!$I$3:$I$998,'Raw Comps'!$J$3:$J$998,C10,'Raw Comps'!$K$3:$K$998,D10),"")
B11: =IF(OR(E11=0,E11=""),"",C11&"BR/"&D11&"BA") | E11: =IF(D11=0,"",COUNTIFS('Raw Comps'!$J$3:$J$998,C11,'Raw Comps'!$K$3:$K$998,D11)) | G11: =IFERROR(AVERAGEIFS('Raw Comps'!$L$3:$L$998,'Raw Comps'!$J$3:$J$998,C11,'Raw Comps'!$K$3:$K$998,D11),"") | H11: =IFERROR(AVERAGEIFS('Raw Comps'!$I$3:$I$998,'Raw Comps'!$J$3:$J$998,C11,'Raw Comps'!$K$3:$K$998,D11),"")
B12: =IF(OR(E12=0,E12=""),"",C12&"BR/"&D12&"BA") | E12: =IF(D12=0,"",COUNTIFS('Raw Comps'!$J$3:$J$998,C12,'Raw Comps'!$K$3:$K$998,D12)) | G12: =IFERROR(AVERAGEIFS('Raw Comps'!$L$3:$L$998,'Raw Comps'!$J$3:$J$998,C12,'Raw Comps'!$K$3:$K$998,D12),"") | H12: =IFERROR(AVERAGEIFS('Raw Comps'!$I$3:$I$998,'Raw Comps'!$J$3:$J$998,C12,'Raw Comps'!$K$3:$K$998,D12),"")
B13: =IF(OR(E13=0,E13=""),"",C13&"BR/"&D13&"BA") | E13: =IF(D13=0,"",COUNTIFS('Raw Comps'!$J$3:$J$998,C13,'Raw Comps'!$K$3:$K$998,D13)) | G13: =IFERROR(AVERAGEIFS('Raw Comps'!$L$3:$L$998,'Raw Comps'!$J$3:$J$998,C13,'Raw Comps'!$K$3:$K$998,D13),"") | H13: =IFERROR(AVERAGEIFS('Raw Comps'!$I$3:$I$998,'Raw Comps'!$J$3:$J$998,C13,'Raw Comps'!$K$3:$K$998,D13),"")
B14: =IF(OR(E14=0,E14=""),"",C14&"BR/"&D14&"BA") | E14: =IF(D14=0,"",COUNTIFS('Raw Comps'!$J$3:$J$998,C14,'Raw Comps'!$K$3:$K$998,D14)) | G14: =IFERROR(AVERAGEIFS('Raw Comps'!$L$3:$L$998,'Raw Comps'!$J$3:$J$998,C14,'Raw Comps'!$K$3:$K$998,D14),"") | H14: =IFERROR(AVERAGEIFS('Raw Comps'!$I$3:$I$998,'Raw Comps'!$J$3:$J$998,C14,'Raw Comps'!$K$3:$K$998,D14),"")
B15: =IF(OR(E15=0,E15=""),"",C15&"BR/"&D15&"BA") | E15: =IF(D15=0,"",COUNTIFS('Raw Comps'!$J$3:$J$998,C15,'Raw Comps'!$K$3:$K$998,D15)) | G15: =IFERROR(AVERAGEIFS('Raw Comps'!$L$3:$L$998,'Raw Comps'!$J$3:$J$998,C15,'Raw Comps'!$K$3:$K$998,D15),"") | H15: =IFERROR(AVERAGEIFS('Raw Comps'!$I$3:$I$998,'Raw Comps'!$J$3:$J$998,C15,'Raw Comps'!$K$3:$K$998,D15),"")
B16: =IF(OR(E16=0,E16=""),"",C16&"BR/"&D16&"BA") | E16: =IF(D16=0,"",COUNTIFS('Raw Comps'!$J$3:$J$998,C16,'Raw Comps'!$K$3:$K$998,D16)) | G16: =IFERROR(AVERAGEIFS('Raw Comps'!$L$3:$L$998,'Raw Comps'!$J$3:$J$998,C16,'Raw Comps'!$K$3:$K$998,D16),"") | H16: =IFERROR(AVERAGEIFS('Raw Comps'!$I$3:$I$998,'Raw Comps'!$J$3:$J$998,C16,'Raw Comps'!$K$3:$K$998,D16),"")
B17: =IF(OR(E17=0,E17=""),"",C17&"BR/"&D17&"BA") | E17: =IF(D17=0,"",COUNTIFS('Raw Comps'!$J$3:$J$998,C17,'Raw Comps'!$K$3:$K$998,D17)) | G17: =IFERROR(AVERAGEIFS('Raw Comps'!$L$3:$L$998,'Raw Comps'!$J$3:$J$998,C17,'Raw Comps'!$K$3:$K$998,D17),"") | H17: =IFERROR(AVERAGEIFS('Raw Comps'!$I$3:$I$998,'Raw Comps'!$J$3:$J$998,C17,'Raw Comps'!$K$3:$K$998,D17),"")
B18: =IF(OR(E18=0,E18=""),"",C18&"BR/"&D18&"BA") | E18: =IF(D18=0,"",COUNTIFS('Raw Comps'!$J$3:$J$998,C18,'Raw Comps'!$K$3:$K$998,D18)) | G18: =IFERROR(AVERAGEIFS('Raw Comps'!$L$3:$L$998,'Raw Comps'!$J$3:$J$998,C18,'Raw Comps'!$K$3:$K$998,D18),"") | H18: =IFERROR(AVERAGEIFS('Raw Comps'!$I$3:$I$998,'Raw Comps'!$J$3:$J$998,C18,'Raw Comps'!$K$3:$K$998,D18),"")
B19: =IF(OR(E19=0,E19=""),"",C19&"BR/"&D19&"BA") | E19: =IF(D19=0,"",COUNTIFS('Raw Comps'!$J$3:$J$998,C19,'Raw Comps'!$K$3:$K$998,D19)) | G19: =IFERROR(AVERAGEIFS('Raw Comps'!$L$3:$L$998,'Raw Comps'!$J$3:$J$998,C19,'Raw Comps'!$K$3:$K$998,D19),"") | H19: =IFERROR(AVERAGEIFS('Raw Comps'!$I$3:$I$998,'Raw Comps'!$J$3:$J$998,C19,'Raw Comps'!$K$3:$K$998,D19),"")
B20: =IF(OR(E20=0,E20=""),"",C20&"BR/"&D20&"BA") | E20: =IF(D20=0,"",COUNTIFS('Raw Comps'!$J$3:$J$998,C20,'Raw Comps'!$K$3:$K$998,D20)) | G20: =IFERROR(AVERAGEIFS('Raw Comps'!$L$3:$L$998,'Raw Comps'!$J$3:$J$998,C20,'Raw Comps'!$K$3:$K$998,D20),"") | H20: =IFERROR(AVERAGEIFS('Raw Comps'!$I$3:$I$998,'Raw Comps'!$J$3:$J$998,C20,'Raw Comps'!$K$3:$K$998,D20),"")
... B30: =IF(OR(E30=0,E30=""),"",C30&"BR/"&D30&"BA") | E30: =IF(D30=0,"",COUNTIFS('Raw Comps'!$J$3:$J$998,C30,'Raw Comps'!$K$3:$K$998,D30)) | G30: =IFERROR(AVERAGEIFS('Raw Comps'!$L$3:$L$998,'Raw Comps'!$J$3:$J$998,C30,'Raw Comps'!$K$3:$K$998,D30),"") | H30: =IFERROR(AVERAGEIFS('Raw Comps'!$I$3:$I$998,'Raw Comps'!$J$3:$J$998,C30,'Raw Comps'!$K$3:$K$998,D30),"")

Sheet Assumptions
B2: MULTIFAMILY ACQUISITION — ASSUMPTIONS
B3: All inputs below drive the model. Blue = hardcoded input. Black = formula output.
B5: ACQUISITION & PROPERTY
B6: Property Name | C6: Sample Multifamily | D6: Total Units | E6: 20
B7: Acquisition Price ($) | C7: 12500000
B8: Closing Costs (%) | C8: 0.02
B9: Closing Costs ($) | C9: =C7*C8 -> 250000
B10: Total Acquisition Cost ($) | C10: =C7+C9 -> 12750000
B12: UNIT MIX & RENT SCHEDULE
B13: Unit Types | C13: Monthly Rent/Unit | D13: Count | E13: Avg SF | F13: Rent / SF | G13: Total SF | H13: Total Monthly Rent | I13: Total Annual Rent
B14: 1BR/2BA | C14: =IFERROR(AVERAGEIF('Rent Assumptions'!$B$8:$B$30,$B14,'Rent Assumptions'!$H$8:$H$30),"") | D14: =IF(B14<>"", E$6/COUNTA(B$14:B$20), "") -> 6.6666667 | E14: =IFERROR(AVERAGEIF('Rent Assumptions'!$B$8:$B$30,$B14,'Rent Assumptions'!$G$8:$G$30),"") | F14: =IFERROR(C14/E14,"") | G14: =IFERROR(E14*D14,"") | H14: =IFERROR(C14*D14,"") | I14: =IFERROR(H14*12,"")
B15: 1BR/2BA | C15: =IFERROR(AVERAGEIF('Rent Assumptions'!$B$8:$B$30,$B15,'Rent Assumptions'!$H$8:$H$30),"") | D15: =IF(B15<>"", E$6/COUNTA(B$14:B$20), "") -> 6.6666667 | E15: =IFERROR(AVERAGEIF('Rent Assumptions'!$B$8:$B$30,$B15,'Rent Assumptions'!$G$8:$G$30),"") | F15: =IFERROR(C15/E15,"") | G15: =IFERROR(E15*D15,"") | H15: =IFERROR(C15*D15,"") | I15: =IFERROR(H15*12,"")
B16: 1BR/1BA | C16: =IFERROR(AVERAGEIF('Rent Assumptions'!$B$8:$B$30,$B16,'Rent Assumptions'!$H$8:$H$30),"") | D16: =IF(B16<>"", E$6/COUNTA(B$14:B$20), "") -> 6.6666667 | E16: =IFERROR(AVERAGEIF('Rent Assumptions'!$B$8:$B$30,$B16,'Rent Assumptions'!$G$8:$G$30),"") | F16: =IFERROR(C16/E16,"") | G16: =IFERROR(E16*D16,"") | H16: =IFERROR(C16*D16,"") | I16: =IFERROR(H16*12,"")
C17: =IFERROR(AVERAGEIF('Rent Assumptions'!$B$8:$B$30,$B17,'Rent Assumptions'!$H$8:$H$30),"") | D17: =IF(B17<>"", E$6/COUNTA(B$14:B$20), "") | E17: =IFERROR(AVERAGEIF('Rent Assumptions'!$B$8:$B$30,$B17,'Rent Assumptions'!$G$8:$G$30),"") | F17: =IFERROR(C17/E17,"") | G17: =IFERROR(E17*D17,"") | H17: =IFERROR(C17*D17,"") | I17: =IFERROR(H17*12,"")
C18: =IFERROR(AVERAGEIF('Rent Assumptions'!$B$8:$B$30,$B18,'Rent Assumptions'!$H$8:$H$30),"") | D18: =IF(B18<>"", E$6/COUNTA(B$14:B$20), "") | E18: =IFERROR(AVERAGEIF('Rent Assumptions'!$B$8:$B$30,$B18,'Rent Assumptions'!$G$8:$G$30),"") | F18: =IFERROR(C18/E18,"") | G18: =IFERROR(E18*D18,"") | H18: =IFERROR(C18*D18,"") | I18: =IFERROR(H18*12,"")
C19: =IFERROR(AVERAGEIF('Rent Assumptions'!$B$8:$B$30,$B19,'Rent Assumptions'!$H$8:$H$30),"") | D19: =IF(B19<>"", E$6/COUNTA(B$14:B$20), "") | E19: =IFERROR(AVERAGEIF('Rent Assumptions'!$B$8:$B$30,$B19,'Rent Assumptions'!$G$8:$G$30),"") | F19: =IFERROR(C19/E19,"") | G19: =IFERROR(E19*D19,"") | H19: =IFERROR(C19*D19,"") | I19: =IFERROR(H19*12,"")
C20: =IFERROR(AVERAGEIF('Rent Assumptions'!$B$8:$B$30,$B20,'Rent Assumptions'!$H$8:$H$30),"") | D20: =IF(B20<>"", E$6/COUNTA(B$14:B$20), "") | E20: =IFERROR(AVERAGEIF('Rent Assumptions'!$B$8:$B$30,$B20,'Rent Assumptions'!$G$8:$G$30),"") | F20: =IFERROR(C20/E20,"") | G20: =IFERROR(E20*D20,"") | H20: =IFERROR(C20*D20,"") | I20: =IFERROR(H20*12,"")
D21: =SUM(D14:D20) -> 20 | E21: =IFERROR(SUMPRODUCT(E14:E20,D14:D20)/SUM(D14:D20),"") -> 0 | F21: =IFERROR(H21/(E21*D21),"") | G21: =SUM(G14:G20) -> 0 | H21: =SUM(H14:H20) -> 0 | I21: =SUM(I14:I20) -> 0
B23: Total Units (auto) | C23: =D21 -> 20
B24: Gross Potential Rent / Yr ($) | C24: =I21 -> 0
B26: CAPITAL COSTS
B27: Total Capital Cost Budget ($) | C27: 1000000 | D27: =IF(C27=0,"Enter total above",IF(E35=C27,"✓ Balanced","⚠ Unallocated: "&TEXT(C27-E35,"$#,##0"))) -> ⚠ Unallocated: $1,000,000
B29: Unit Type | C29: Total SF | D29: SF % of Total | E29: Allocated Cost ($) | F29: Cost / SF ($) | G29: Cost / Unit ($)
B30: =IF(B14<>""," "&B14,"") -> 1BR/2BA | C30: =IFERROR(G14,"") | D30: =IFERROR(C30/C$35,"") | E30: =IFERROR(C$27*D30,"") | F30: =IFERROR(E30/C30,"") | G30: =IFERROR(E30/D14,"")
B31: =IF(B15<>""," "&B15,"") -> 1BR/2BA | C31: =IFERROR(G15,"") | D31: =IFERROR(C31/C$35,"") | E31: =IFERROR(C$27*D31,"") | F31: =IFERROR(E31/C31,"") | G31: =IFERROR(E31/D15,"")
B32: =IF(B16<>""," "&B16,"") -> 1BR/1BA | C32: =IFERROR(G16,"") | D32: =IFERROR(C32/C$35,"") | E32: =IFERROR(C$27*D32,"") | F32: =IFERROR(E32/C32,"") | G32: =IFERROR(E32/D16,"")
B33: =IF(B17<>""," "&B17,"") | C33: =IFERROR(G17,"") | D33: =IFERROR(C33/C$35,"") | E33: =IFERROR(C$27*D33,"") | F33: =IFERROR(E33/C33,"") | G33: =IFERROR(E33/D17,"")
B34: =IF(B18<>""," "&B18,"") | C34: =IFERROR(G18,"") | D34: =IFERROR(C34/C$35,"") | E34: =IFERROR(C$27*D34,"") | F34: =IFERROR(E34/C34,"") | G34: =IFERROR(E34/D18,"")
B35: Total | C35: =SUM(C30:C34) -> 0 | D35: =SUM(D30:D32) -> 0 | E35: =SUM(E30:E32) -> 0 | F35: =IFERROR(C27/C35,"") | G35: =IFERROR(C27/C23,"") -> 50000
B38: REVENUE ASSUMPTIONS
B39: Vacancy & Credit Loss (%) | C39: 0.07
B40: Other Income / Unit / Month ($) | C40: 75
B42: OPERATING EXPENSES
B43: OpEx Ratio (% of EGI) | C43: 0.35
B44: OpEx Growth Rate (%) | C44: 0.03
B50: DEBT ASSUMPTIONS
B51: Loan Type | C51: Agency/Perm
B52: LTV (%) | C52: 0.7
B53: Loan Amount ($) | C53: =C7*C52 -> 8750000
B54: Interest Rate (%) | C54: 0.065
B55: IO Period (Months) | C55: 24
B56: Amortization (Years) | C56: 30
B57: Loan Term (Years) | C57: 10
B58: Origination Fee (%) | C58: 0.01
B59: Origination Fee ($) | C59: =C53*C58 -> 87500
B61: HOLD PERIOD & EXIT
B62: Hold Period (Years) | C62: 5
B63: Exit Cap Rate (%) | C63: 0.06
B64: Selling Costs (%) | C64: 0.02
B66: GP/LP STRUCTURE
B67: GP Co-Invest (%) | C67: 0.1
B68: LP Pref Return (%) | C68: 0.08
B69: GP Promote Above Pref (%) | C69: 0.2
B71: RENT GROWTH BY YEAR
B72: Year 1 | C72: 0.03
B73: Year 2 | C73: 0.03
B74: Year 3 | C74: 0.025
B75: Year 4 | C75: 0.025
B76: Year 5 | C76: 0.025
B77: Year 6 | C77: 0.02
B78: Year 7 | C78: 0.02
B79: Year 8 | C79: 0.02
B80: Year 9 | C80: 0.02
B81: Year 10 | C81: 0.02
B83: EQUITY SUMMARY
B84: Total Equity Required ($) | C84: =C10+C36-C53+C59 -> 4087500
B85: GP Equity ($) | C85: =C84*C67 -> 408750
B86: LP Equity ($) | C86: =C84-C85 -> 3678750

Sheet Pricing Scenarios
B1: PRICING SCENARIOS — CAP RATE-BASED ACQUISITION ANALYSIS
B2: Implied acquisition price = Year 1 NOI ÷ Entry Cap Rate. Returns linked live to model. Edit thresholds to flag scenarios.
B4: RETURN THRESHOLDS (edit these) | E4: Year 1 NOI (live): | F4: ='Cash Flow'!E21 -> 11207.43
B5: Min IRR Target (Levered) | C5: 0.1 | E5: Hold Period (live): | F5: =Assumptions!C62 -> 5
B6: Min Avg CoC Target | C6: 0.06 | E6: Exit Cap (live): | F6: =Assumptions!C63 -> 0.06
B8: SCENARIO TABLE — Entry Cap Rate × Implied Price × Returns
B9: Entry Cap Rate | C9: Implied Acq Price | D9: LTV (live) | E9: Loan Amount | F9: Total Equity | G9: GP Equity | H9: LP Equity | I9: Year 1 NOI | J9: Year 1 CoC | K9: Avg CoC (hold) | L9: Levered IRR | M9: Exit Multiple | N9: CF0 | O9: CF1 | P9: CF2 | Q9: CF3 | R9: CF4 | S9: CF5
A10: =IF(ABS(C10-Assumptions!$C$7)<C10*0.02,"★ BASE",IF(Assumptions!$C$7>C10,"▼ OVERPRICE","▲ UPSIDE")) -> ▼ OVERPRICE | B10: 0.05 | C10: ='Cash Flow'!$E$21/B10 -> 224148.6 | D10: =Assumptions!$C$52 -> 0.7 | E10: =C10*D10 -> 156904.02 | F10: =C10*(1+Assumptions!$C$8)+Assumptions!$C$36-E10 -> 71727.552 | G10: =F10*Assumptions!$C$67 -> 7172.7552 | H10: =F10-G10 -> 64554.797 | I10: ='Cash Flow'!$E$21 -> 11207.43 | J10: =('Cash Flow'!$E$21-E10*Assumptions!$C$54)/F10 -> 0.0140625 | K10: =IFERROR(AVERAGE('Cash Flow'!$E$21-E10*Assumptions!$C$54,'Cash Flow'!$F$21-E10*Assumptions!$C$54,'Cash Flow'!$G$21+PMT(Assumptions!$C$54/12,Assumptions!$C$56*12,E10)*12,'Cash Flow'!$H$21+PMT(Assumptions!$C$54/12,Assumptions!$C$56*12,E10)*12,'Cash Flow'!$I$21+PMT(Assumptions!$C$54/12,Assumptions!$C$56*12,E10)*12)/F10,"-") -> 0.007944169 | L10: =IFERROR(IRR(N10:S10),"n/a") -> -0.060314325 | M10: =IFERROR((SUM(O10:S10)+N10)/(-N10)+1,"n/a") -> 0.73894254 | N10: =-F10 -> -71727.552 | O10: ='Cash Flow'!$E$21-E10*Assumptions!$C$54 -> 1008.6687 | P10: ='Cash Flow'!$F$21-E10*Assumptions!$C$54 -> 1344.8916 | Q10: ='Cash Flow'!$G$21+PMT(Assumptions!$C$54/12,Assumptions!$C$56*12,E10)*12 -> -99.716499 | R10: ='Cash Flow'!$H$21+PMT(Assumptions!$C$54/12,Assumptions!$C$56*12,E10)*12 -> 163.30119 | S10: ='Cash Flow'!$I$21+PMT(Assumptions!$C$54/12,Assumptions!$C$56*12,E10)*12+('Cash Flow'!$I$21/Assumptions!$C$63)*(1-Assumptions!$C$64)-(E10+CUMPRINC(Assumptions!$C$54/12,Assumptions!$C$56*12,E10,1,MIN(Assumptions!$C$62*12-Assumptions!$C$55,Assumptions!$C$56*12),0)) -> 50585.394
A11: =IF(ABS(C11-Assumptions!$C$7)<C11*0.02,"★ BASE",IF(Assumptions!$C$7>C11,"▼ OVERPRICE","▲ UPSIDE")) -> ▼ OVERPRICE | B11: 0.06 | C11: ='Cash Flow'!$E$21/B11 -> 186790.5 | D11: =Assumptions!$C$52 -> 0.7 | E11: =C11*D11 -> 130753.35 | F11: =C11*(1+Assumptions!$C$8)+Assumptions!$C$36-E11 -> 59772.96 | G11: =F11*Assumptions!$C$67 -> 5977.296 | H11: =F11-G11 -> 53795.664 | I11: ='Cash Flow'!$E$21 -> 11207.43 | J11: =('Cash Flow'!$E$21-E11*Assumptions!$C$54)/F11 -> 0.0453125 | K11: =IFERROR(AVERAGE('Cash Flow'!$E$21-E11*Assumptions!$C$54,'Cash Flow'!$F$21-E11*Assumptions!$C$54,'Cash Flow'!$G$21+PMT(Assumptions!$C$54/12,Assumptions!$C$56*12,E11)*12,'Cash Flow'!$H$21+PMT(Assumptions!$C$54/12,Assumptions!$C$56*12,E11)*12,'Cash Flow'!$I$21+PMT(Assumptions!$C$54/12,Assumptions!$C$56*12,E11)*12)/F11,"-") -> 0.040818146 | L11: =IFERROR(IRR(N11:S11),"n/a") -> 0.085245031 | M11: =IFERROR((SUM(O11:S11)+N11)/(-N11)+1,"n/a") -> 1.4649822 | N11: =-F11 -> -59772.96 | O11: ='Cash Flow'!$E$21-E11*Assumptions!$C$54 -> 2708.4623 | P11: ='Cash Flow'!$F$21-E11*Assumptions!$C$54 -> 3044.6852 | Q11: ='Cash Flow'!$G$21+PMT(Assumptions!$C$54/12,Assumptions!$C$56*12,E11)*12 -> 1883.7638 | R11: ='Cash Flow'!$H$21+PMT(Assumptions!$C$54/12,Assumptions!$C$56*12,E11)*12 -> 2146.7815 | S11: ='Cash Flow'!$I$21+PMT(Assumptions!$C$54/12,Assumptions!$C$56*12,E11)*12+('Cash Flow'!$I$21/Assumptions!$C$63)*(1-Assumptions!$C$64)-(E11+CUMPRINC(Assumptions!$C$54/12,Assumptions!$C$56*12,E11,1,MIN(Assumptions!$C$62*12-Assumptions!$C$55,Assumptions!$C$56*12),0)) -> 77782.629
A12: =IF(ABS(C12-Assumptions!$C$7)<C12*0.02,"★ BASE",IF(Assumptions!$C$7>C12,"▼ OVERPRICE","▲ UPSIDE")) -> ▼ OVERPRICE | B12: 0.07 | C12: ='Cash Flow'!$E$21/B12 -> 160106.14 | D12: =Assumptions!$C$52 -> 0.7 | E12: =C12*D12 -> 112074.3 | F12: =C12*(1+Assumptions!$C$8)+Assumptions!$C$36-E12 -> 51233.966 | G12: =F12*Assumptions!$C$67 -> 5123.3966 | H12: =F12-G12 -> 46110.569 | I12: ='Cash Flow'!$E$21 -> 11207.43 | J12: =('Cash Flow'!$E$21-E12*Assumptions!$C$54)/F12 -> 0.0765625 | K12: =IFERROR(AVERAGE('Cash Flow'!$E$21-E12*Assumptions!$C$54,'Cash Flow'!$F$21-E12*Assumptions!$C$54,'Cash Flow'!$G$21+PMT(Assumptions!$C$54/12,Assumptions!$C$56*12,E12)*12,'Cash Flow'!$H$21+PMT(Assumptions!$C$54/12,Assumptions!$C$56*12,E12)*12,'Cash Flow'!$I$21+PMT(Assumptions!$C$54/12,Assumptions!$C$56*12,E12)*12)/F12,"-") -> 0.073692122 | L12: =IFERROR(IRR(N12:S12),"n/a") -> 0.18759618 | M12: =IFERROR((SUM(O12:S12)+N12)/(-N12)+1,"n/a") -> 2.1910218 | N12: =-F12 -> -51233.966 | O12: ='Cash Flow'!$E$21-E12*Assumptions!$C$54 -> 3922.6005 | P12: ='Cash Flow'!$F$21-E12*Assumptions!$C$54 -> 4258.8234 | Q12: ='Cash Flow'!$G$21+PMT(Assumptions!$C$54/12,Assumptions!$C$56*12,E12)*12 -> 3300.5354 | R12: ='Cash Flow'!$H$21+PMT(Assumptions!$C$54/12,Assumptions!$C$56*12,E12)*12 -> 3563.5531 | S12: ='Cash Flow'!$I$21+PMT(Assumptions!$C$54/12,Assumptions!$C$56*12,E12)*12+('Cash Flow'!$I$21/Assumptions!$C$63)*(1-Assumptions!$C$64)-(E12+CUMPRINC(Assumptions!$C$54/12,Assumptions!$C$56*12,E12,1,MIN(Assumptions!$C$62*12-Assumptions!$C$55,Assumptions!$C$56*12),0)) -> 97209.226
A13: =IF(ABS(C13-Assumptions!$C$7)<C13*0.02,"★ BASE",IF(Assumptions!$C$7>C13,"▼ OVERPRICE","▲ UPSIDE")) -> ▼ OVERPRICE | B13: 0.08 | C13: ='Cash Flow'!$E$21/B13 -> 140092.88 | D13: =Assumptions!$C$52 -> 0.7 | E13: =C13*D13 -> 98065.012 | F13: =C13*(1+Assumptions!$C$8)+Assumptions!$C$36-E13 -> 44829.72 | G13: =F13*Assumptions!$C$67 -> 4482.972 | H13: =F13-G13 -> 40346.748 | I13: ='Cash Flow'!$E$21 -> 11207.43 | J13: =('Cash Flow'!$E$21-E13*Assumptions!$C$54)/F13 -> 0.1078125 | K13: =IFERROR(AVERAGE('Cash Flow'!$E$21-E13*Assumptions!$C$54,'Cash Flow'!$F$21-E13*Assumptions!$C$54,'Cash Flow'!$G$21+PMT(Assumptions!$C$54/12,Assumptions!$C$56*12,E13)*12,'Cash Flow'!$H$21+PMT(Assumptions!$C$54/12,Assumptions!$C$56*12,E13)*12,'Cash Flow'!$I$21+PMT(Assumptions!$C$54/12,Assumptions!$C$56*12,E13)*12)/F13,"-") -> 0.1065661 | L13: =IFERROR(IRR(N13:S13),"n/a") -> 0.26949006 | M13: =IFERROR((SUM(O13:S13)+N13)/(-N13)+1,"n/a") -> 2.9170615 | N13: =-F13 -> -44829.72 | O13: ='Cash Flow'!$E$21-E13*Assumptions!$C$54 -> 4833.2042 | P13: ='Cash Flow'!$F$21-E13*Assumptions!$C$54 -> 5169.4271 | Q13: ='Cash Flow'!$G$21+PMT(Assumptions!$C$54/12,Assumptions!$C$56*12,E13)*12 -> 4363.1141 | R13: ='Cash Flow'!$H$21+PMT(Assumptions!$C$54/12,Assumptions!$C$56*12,E13)*12 -> 4626.1318 | S13: ='Cash Flow'!$I$21+PMT(Assumptions!$C$54/12,Assumptions!$C$56*12,E13)*12+('Cash Flow'!$I$21/Assumptions!$C$63)*(1-Assumptions!$C$64)-(E13+CUMPRINC(Assumptions!$C$54/12,Assumptions!$C$56*12,E13,1,MIN(Assumptions!$C$62*12-Assumptions!$C$55,Assumptions!$C$56*12),0)) -> 111779.17
A14: =IF(ABS(C14-Assumptions!$C$7)<C14*0.02,"★ BASE",IF(Assumptions!$C$7>C14,"▼ OVERPRICE","▲ UPSIDE")) -> ▼ OVERPRICE | B14: 0.09 | C14: ='Cash Flow'!$E$21/B14 -> 124527 | D14: =Assumptions!$C$52 -> 0.7 | E14: =C14*D14 -> 87168.9 | F14: =C14*(1+Assumptions!$C$8)+Assumptions!$C$36-E14 -> 39848.64 | G14: =F14*Assumptions!$C$67 -> 3984.864 | H14: =F14-G14 -> 35863.776 | I14: ='Cash Flow'!$E$21 -> 11207.43 | J14: =('Cash Flow'!$E$21-E14*Assumptions!$C$54)/F14 -> 0.1390625 | K14: =IFERROR(AVERAGE('Cash Flow'!$E$21-E14*Assumptions!$C$54,'Cash Flow'!$F$21-E14*Assumptions!$C$54,'Cash Flow'!$G$21+PMT(Assumptions!$C$54/12,Assumptions!$C$56*12,E14)*12,'Cash Flow'!$H$21+PMT(Assumptions!$C$54/12,Assumptions!$C$56*12,E14)*12,'Cash Flow'!$I$21+PMT(Assumptions!$C$54/12,Assumptions!$C$56*12,E14)*12)/F14,"-") -> 0.13944008 | L14: =IFERROR(IRR(N14:S14),"n/a") -> 0.33922408 | M14: =IFERROR((SUM(O14:S14)+N14)/(-N14)+1,"n/a") -> 3.6431012 | N14: =-F14 -> -39848.64 | O14: ='Cash Flow'!$E$21-E14*Assumptions!$C$54 -> 5541.4515 | P14: ='Cash Flow'!$F$21-E14*Assumptions!$C$54 -> 5877.6744 | Q14: ='Cash Flow'!$G$21+PMT(Assumptions!$C$54/12,Assumptions!$C$56*12,E14)*12 -> 5189.5642 | R14: ='Cash Flow'!$H$21+PMT(Assumptions!$C$54/12,Assumptions!$C$56*12,E14)*12 -> 5452.5819 | S14: ='Cash Flow'!$I$21+PMT(Assumptions!$C$54/12,Assumptions!$C$56*12,E14)*12+('Cash Flow'!$I$21/Assumptions!$C$63)*(1-Assumptions!$C$64)-(E14+CUMPRINC(Assumptions!$C$54/12,Assumptions!$C$56*12,E14,1,MIN(Assumptions!$C$62*12-Assumptions!$C$55,Assumptions!$C$56*12),0)) -> 123111.35
A15: =IF(ABS(C15-Assumptions!$C$7)<C15*0.02,"★ BASE",IF(Assumptions!$C$7>C15,"▼ OVERPRICE","▲ UPSIDE")) -> ▼ OVERPRICE | B15: 0.1 | C15: ='Cash Flow'!$E$21/B15 -> 112074.3 | D15: =Assumptions!$C$52 -> 0.7 | E15: =C15*D15 -> 78452.01 | F15: =C15*(1+Assumptions!$C$8)+Assumptions!$C$36-E15 -> 35863.776 | G15: =F15*Assumptions!$C$67 -> 3586.3776 | H15: =F15-G15 -> 32277.398 | I15: ='Cash Flow'!$E$21 -> 11207.43 | J15: =('Cash Flow'!$E$21-E15*Assumptions!$C$54)/F15 -> 0.1703125 | K15: =IFERROR(AVERAGE('Cash Flow'!$E$21-E15*Assumptions!$C$54,'Cash Flow'!$F$21-E15*Assumptions!$C$54,'Cash Flow'!$G$21+PMT(Assumptions!$C$54/12,Assumptions!$C$56*12,E15)*12,'Cash Flow'!$H$21+PMT(Assumptions!$C$54/12,Assumptions!$C$56*12,E15)*12,'Cash Flow'!$I$21+PMT(Assumptions!$C$54/12,Assumptions!$C$56*12,E15)*12)/F15,"-") -> 0.17231405 | L15: =IFERROR(IRR(N15:S15),"n/a") -> 0.40083165 | M15: =IFERROR((SUM(O15:S15)+N15)/(-N15)+1,"n/a") -> 4.3691408 | N15: =-F15 -> -35863.776 | O15: ='Cash Flow'!$E$21-E15*Assumptions!$C$54 -> 6108.0494 | P15: ='Cash Flow'!$F$21-E15*Assumptions!$C$54 -> 6444.2723 | Q15: ='Cash Flow'!$G$21+PMT(Assumptions!$C$54/12,Assumptions!$C$56*12,E15)*12 -> 5850.7243 | R15: ='Cash Flow'!$H$21+PMT(Assumptions!$C$54/12,Assumptions!$C$56*12,E15)*12 -> 6113.742 | S15: ='Cash Flow'!$I$21+PMT(Assumptions!$C$54/12,Assumptions!$C$56*12,E15)*12+('Cash Flow'!$I$21/Assumptions!$C$63)*(1-Assumptions!$C$64)-(E15+CUMPRINC(Assumptions!$C$54/12,Assumptions!$C$56*12,E15,1,MIN(Assumptions!$C$62*12-Assumptions!$C$55,Assumptions!$C$56*12),0)) -> 132177.1
A16: =IF(ABS(C16-Assumptions!$C$7)<C16*0.02,"★ BASE",IF(Assumptions!$C$7>C16,"▼ OVERPRICE","▲ UPSIDE")) -> ▼ OVERPRICE | B16: 0.11 | C16: ='Cash Flow'!$E$21/B16 -> 101885.73 | D16: =Assumptions!$C$52 -> 0.7 | E16: =C16*D16 -> 71320.009 | F16: =C16*(1+Assumptions!$C$8)+Assumptions!$C$36-E16 -> 32603.433 | G16: =F16*Assumptions!$C$67 -> 3260.3433 | H16: =F16-G16 -> 29343.089 | I16: ='Cash Flow'!$E$21 -> 11207.43 | J16: =('Cash Flow'!$E$21-E16*Assumptions!$C$54)/F16 -> 0.2015625 | K16: =IFERROR(AVERAGE('Cash Flow'!$E$21-E16*Assumptions!$C$54,'Cash Flow'!$F$21-E16*Assumptions!$C$54,'Cash Flow'!$G$21+PMT(Assumptions!$C$54/12,Assumptions!$C$56*12,E16)*12,'Cash Flow'!$H$21+PMT(Assumptions!$C$54/12,Assumptions!$C$56*12,E16)*12,'Cash Flow'!$I$21+PMT(Assumptions!$C$54/12,Assumptions!$C$56*12,E16)*12)/F16,"-") -> 0.20518803 | L16: =IFERROR(IRR(N16:S16),"n/a") -> 0.45660127 | M16: =IFERROR((SUM(O16:S16)+N16)/(-N16)+1,"n/a") -> 5.0951805 | N16: =-F16 -> -32603.433 | O16: ='Cash Flow'!$E$21-E16*Assumptions!$C$54 -> 6571.6294 | P16: ='Cash Flow'!$F$21-E16*Assumptions!$C$54 -> 6907.8523 | Q16: ='Cash Flow'!$G$21+PMT(Assumptions!$C$54/12,Assumptions!$C$56*12,E16)*12 -> 6391.6735 | R16: ='Cash Flow'!$H$21+PMT(Assumptions!$C$54/12,Assumptions!$C$56*12,E16)*12 -> 6654.6912 | S16: ='Cash Flow'!$I$21+PMT(Assumptions!$C$54/12,Assumptions!$C$56*12,E16)*12+('Cash Flow'!$I$21/Assumptions!$C$63)*(1-Assumptions!$C$64)-(E16+CUMPRINC(Assumptions!$C$54/12,Assumptions!$C$56*12,E16,1,MIN(Assumptions!$C$62*12-Assumptions!$C$55,Assumptions!$C$56*12),0)) -> 139594.53
A17: =IF(ABS(C17-Assumptions!$C$7)<C17*0.02,"★ BASE",IF(Assumptions!$C$7>C17,"▼ OVERPRICE","▲ UPSIDE")) -> ▼ OVERPRICE | B17: 0.12 | C17: ='Cash Flow'!$E$21/B17 -> 93395.25 | D17: =Assumptions!$C$52 -> 0.7 | E17: =C17*D17 -> 65376.675 | F17: =C17*(1+Assumptions!$C$8)+Assumptions!$C$36-E17 -> 29886.48 | G17: =F17*Assumptions!$C$67 -> 2988.648 | H17: =F17-G17 -> 26897.832 | I17: ='Cash Flow'!$E$21 -> 11207.43 | J17: =('Cash Flow'!$E$21-E17*Assumptions!$C$54)/F17 -> 0.2328125 | K17: =IFERROR(AVERAGE('Cash Flow'!$E$21-E17*Assumptions!$C$54,'Cash Flow'!$F$21-E17*Assumptions!$C$54,'Cash Flow'!$G$21+PMT(Assumptions!$C$54/12,Assumptions!$C$56*12,E17)*12,'Cash Flow'!$H$21+PMT(Assumptions!$C$54/12,Assumptions!$C$56*12,E17)*12,'Cash Flow'!$I$21+PMT(Assumptions!$C$54/12,Assumptions!$C$56*12,E17)*12)/F17,"-") -> 0.238062 | L17: =IFERROR(IRR(N17:S17),"n/a") -> 0.50796585 | M17: =IFERROR((SUM(O17:S17)+N17)/(-N17)+1,"n/a") -> 5.8212201 | N17: =-F17 -> -29886.48 | O17: ='Cash Flow'!$E$21-E17*Assumptions!$C$54 -> 6957.9461 | P17: ='Cash Flow'!$F$21-E17*Assumptions!$C$54 -> 7294.169 | Q17: ='Cash Flow'!$G$21+PMT(Assumptions!$C$54/12,Assumptions!$C$56*12,E17)*12 -> 6842.4645 | R17: ='Cash Flow'!$H$21+PMT(Assumptions!$C$54/12,Assumptions!$C$56*12,E17)*12 -> 7105.4822 | S17: ='Cash Flow'!$I$21+PMT(Assumptions!$C$54/12,Assumptions!$C$56*12,E17)*12+('Cash Flow'!$I$21/Assumptions!$C$63)*(1-Assumptions!$C$64)-(E17+CUMPRINC(Assumptions!$C$54/12,Assumptions!$C$56*12,E17,1,MIN(Assumptions!$C$62*12-Assumptions!$C$55,Assumptions!$C$56*12),0)) -> 145775.72
A18: =IF(ABS(C18-Assumptions!$C$7)<C18*0.02,"★ BASE",IF(Assumptions!$C$7>C18,"▼ OVERPRICE","▲ UPSIDE")) -> ▼ OVERPRICE | B18: 0.13 | C18: ='Cash Flow'!$E$21/B18 -> 86211 | D18: =Assumptions!$C$52 -> 0.7 | E18: =C18*D18 -> 60347.7 | F18: =C18*(1+Assumptions!$C$8)+Assumptions!$C$36-E18 -> 27587.52 | G18: =F18*Assumptions!$C$67 -> 2758.752 | H18: =F18-G18 -> 24828.768 | I18: ='Cash Flow'!$E$21 -> 11207.43 | J18: =('Cash Flow'!$E$21-E18*Assumptions!$C$54)/F18 -> 0.2640625 | K18: =IFERROR(AVERAGE('Cash Flow'!$E$21-E18*Assumptions!$C$54,'Cash Flow'!$F$21-E18*Assumptions!$C$54,'Cash Flow'!$G$21+PMT(Assumptions!$C$54/12,Assumptions!$C$56*12,E18)*12,'Cash Flow'!$H$21+PMT(Assumptions!$C$54/12,Assumptions!$C$56*12,E18)*12,'Cash Flow'!$I$21+PMT(Assumptions!$C$54/12,Assumptions!$C$56*12,E18)*12)/F18,"-") -> 0.27093598 | L18: =IFERROR(IRR(N18:S18),"n/a") -> 0.55588641 | M18: =IFERROR((SUM(O18:S18)+N18)/(-N18)+1,"n/a") -> 6.5472598 | N18: =-F18 -> -27587.52 | O18: ='Cash Flow'!$E$21-E18*Assumptions!$C$54 -> 7284.8295 | P18: ='Cash Flow'!$F$21-E18*Assumptions!$C$54 -> 7621.0524 | Q18: ='Cash Flow'!$G$21+PMT(Assumptions!$C$54/12,Assumptions!$C$56*12,E18)*12 -> 7223.903 | R18: ='Cash Flow'!$H$21+PMT(Assumptions!$C$54/12,Assumptions!$C$56*12,E18)*12 -> 7486.9207 | S18: ='Cash Flow'!$I$21+PMT(Assumptions!$C$54/12,Assumptions!$C$56*12,E18)*12+('Cash Flow'!$I$21/Assumptions!$C$63)*(1-Assumptions!$C$64)-(E18+CUMPRINC(Assumptions!$C$54/12,Assumptions!$C$56*12,E18,1,MIN(Assumptions!$C$62*12-Assumptions!$C$55,Assumptions!$C$56*12),0)) -> 151005.95
A19: =IF(ABS(C19-Assumptions!$C$7)<C19*0.02,"★ BASE",IF(Assumptions!$C$7>C19,"▼ OVERPRICE","▲ UPSIDE")) -> ▼ OVERPRICE | B19: 0.14 | C19: ='Cash Flow'!$E$21/B19 -> 80053.071 | D19: =Assumptions!$C$52 -> 0.7 | E19: =C19*D19 -> 56037.15 | F19: =C19*(1+Assumptions!$C$8)+Assumptions!$C$36-E19 -> 25616.983 | G19: =F19*Assumptions!$C$67 -> 2561.6983 | H19: =F19-G19 -> 23055.285 | I19: ='Cash Flow'!$E$21 -> 11207.43 | J19: =('Cash Flow'!$E$21-E19*Assumptions!$C$54)/F19 -> 0.2953125 | K19: =IFERROR(AVERAGE('Cash Flow'!$E$21-E19*Assumptions!$C$54,'Cash Flow'!$F$21-E19*Assumptions!$C$54,'Cash Flow'!$G$21+PMT(Assumptions!$C$54/12,Assumptions!$C$56*12,E19)*12,'Cash Flow'!$H$21+PMT(Assumptions!$C$54/12,Assumptions!$C$56*12,E19)*12,'Cash Flow'!$I$21+PMT(Assumptions!$C$54/12,Assumptions!$C$56*12,E19)*12)/F19,"-") -> 0.30380996 | L19: =IFERROR(IRR(N19:S19),"n/a") -> 0.60104114 | M19: =IFERROR((SUM(O19:S19)+N19)/(-N19)+1,"n/a") -> 7.2732994 | N19: =-F19 -> -25616.983 | O19: ='Cash Flow'!$E$21-E19*Assumptions!$C$54 -> 7565.0153 | P19: ='Cash Flow'!$F$21-E19*Assumptions!$C$54 -> 7901.2382 | Q19: ='Cash Flow'!$G$21+PMT(Assumptions!$C$54/12,Assumptions!$C$56*12,E19)*12 -> 7550.8503 | R19: ='Cash Flow'!$H$21+PMT(Assumptions!$C$54/12,Assumptions!$C$56*12,E19)*12 -> 7813.868 | S19: ='Cash Flow'!$I$21+PMT(Assumptions!$C$54/12,Assumptions!$C$56*12,E19)*12+('Cash Flow'!$I$21/Assumptions!$C$63)*(1-Assumptions!$C$64)-(E19+CUMPRINC(Assumptions!$C$54/12,Assumptions!$C$56*12,E19,1,MIN(Assumptions!$C$62*12-Assumptions!$C$55,Assumptions!$C$56*12),0)) -> 155489.02
A20: =IF(ABS(C20-Assumptions!$C$7)<C20*0.02,"★ BASE",IF(Assumptions!$C$7>C20,"▼ OVERPRICE","▲ UPSIDE")) -> ▼ OVERPRICE | B20: 0.15 | C20: ='Cash Flow'!$E$21/B20 -> 74716.2 | D20: =Assumptions!$C$52 -> 0.7 | E20: =C20*D20 -> 52301.34 | F20: =C20*(1+Assumptions!$C$8)+Assumptions!$C$36-E20 -> 23909.184 | G20: =F20*Assumptions!$C$67 -> 2390.9184 | H20: =F20-G20 -> 21518.266 | I20: ='Cash Flow'!$E$21 -> 11207.43 | J20: =('Cash Flow'!$E$21-E20*Assumptions!$C$54)/F20 -> 0.3265625 | K20: =IFERROR(AVERAGE('Cash Flow'!$E$21-E20*Assumptions!$C$54,'Cash Flow'!$F$21-E20*Assumptions!$C$54,'Cash Flow'!$G$21+PMT(Assumptions!$C$54/12,Assumptions!$C$56*12,E20)*12,'Cash Flow'!$H$21+PMT(Assumptions!$C$54/12,Assumptions!$C$56*12,E20)*12,'Cash Flow'!$I$21+PMT(Assumptions!$C$54/12,Assumptions!$C$56*12,E20)*12)/F20,"-") -> 0.33668393 | L20: =IFERROR(IRR(N20:S20),"n/a") -> 0.64392781 | M20: =IFERROR((SUM(O20:S20)+N20)/(-N20)+1,"n/a") -> 7.9993391 | N20: =-F20 -> -23909.184 | O20: ='Cash Flow'!$E$21-E20*Assumptions!$C$54 -> 7807.8429 | P20: ='Cash Flow'!$F$21-E20*Assumptions!$C$54 -> 8144.0658 | Q20: ='Cash Flow'!$G$21+PMT(Assumptions!$C$54/12,Assumptions!$C$56*12,E20)*12 -> 7834.2046 | R20: ='Cash Flow'!$H$21+PMT(Assumptions!$C$54/12,Assumptions!$C$56*12,E20)*12 -> 8097.2223 | S20: ='Cash Flow'!$I$21+PMT(Assumptions!$C$54/12,Assumptions!$C$56*12,E20)*12+('Cash Flow'!$I$21/Assumptions!$C$63)*(1-Assumptions!$C$64)-(E20+CUMPRINC(Assumptions!$C$54/12,Assumptions!$C$56*12,E20,1,MIN(Assumptions!$C$62*12-Assumptions!$C$55,Assumptions!$C$56*12),0)) -> 159374.33
B23: SENSITIVITY: LEVERED IRR — Entry Cap Rate (rows) × Exit Cap Rate (columns)
B24: 🟢 ≥ IRR target 🟡 within 3% below 🔴 below | Yellow column = live exit cap from Assumptions
B25: Entry Cap \ Exit Cap | C25: 0.04 | D25: 0.045 | E25: 0.05 | F25: 0.055 | G25: 0.06 | H25: 0.065 | I25: 0.07 | J25: 0.075 | K25: 0.08
B26: 0.05 | C26: =IFERROR(IRR(N300:S300),"n/a") -> 0.16717343 | D26: =IFERROR(IRR(N301:S301),"n/a") -> 0.11055108 | E26: =IFERROR(IRR(N302:S302),"n/a") -> 0.055040532 | F26: =IFERROR(IRR(N303:S303),"n/a") -> -0.001179772 | G26: =IFERROR(IRR(N304:S304),"n/a") -> -0.060314325 | H26: =IFERROR(IRR(N305:S305),"n/a") -> -0.12568884 | I26: =IFERROR(IRR(N306:S306),"n/a") -> -0.2037351 | J26: =IFERROR(IRR(N307:S307),"n/a") -> -0.31238232 | K26: =IFERROR(IRR(N308:S308),"n/a") -> -0.65738393 | V26: ='Cash Flow'!$I$21+PMT(Assumptions!$C$54/12,Assumptions!$C$56*12,E10)*12+('Cash Flow'!$I$21/0.04)*(1-Assumptions!$C$64)-(E10+CUMPRINC(Assumptions!$C$54/12,Assumptions!$C$56*12,E10,1,MIN(Assumptions!$C$62*12-Assumptions!$C$55,Assumptions!$C$56*12),0)) -> 151303.39 | W26: ='Cash Flow'!$I$21+PMT(Assumptions!$C$54/12,Assumptions!$C$56*12,E10)*12+('Cash Flow'!$I$21/0.045)*(1-Assumptions!$C$64)-(E10+CUMPRINC(Assumptions!$C$54/12,Assumptions!$C$56*12,E10,1,MIN(Assumptions!$C$62*12-Assumptions!$C$55,Assumptions!$C$56*12),0)) -> 117730.72 | X26: ='Cash Flow'!$I$21+PMT(Assumptions!$C$54/12,Assumptions!$C$56*12,E10)*12+('Cash Flow'!$I$21/0.05)*(1-Assumptions!$C$64)-(E10+CUMPRINC(Assumptions!$C$54/12,Assumptions!$C$56*12,E10,1,MIN(Assumptions!$C$62*12-Assumptions!$C$55,Assumptions!$C$56*12),0)) -> 90872.592 | Y26: ='Cash Flow'!$I$21+PMT(Assumptions!$C$54/12,Assumptions!$C$56*12,E10)*12+('Cash Flow'!$I$21/0.055)*(1-Assumptions!$C$64)-(E10+CUMPRINC(Assumptions!$C$54/12,Assumptions!$C$56*12,E10,1,MIN(Assumptions!$C$62*12-Assumptions!$C$55,Assumptions!$C$56*12),0)) -> 68897.757 | Z26: ='Cash Flow'!$I$21+PMT(Assumptions!$C$54/12,Assumptions!$C$56*12,E10)*12+('Cash Flow'!$I$21/0.06)*(1-Assumptions!$C$64)-(E10+CUMPRINC(Assumptions!$C$54/12,Assumptions!$C$56*12,E10,1,MIN(Assumptions!$C$62*12-Assumptions!$C$55,Assumptions!$C$56*12),0)) -> 50585.394 | AA26: ='Cash Flow'!$I$21+PMT(Assumptions!$C$54/12,Assumptions!$C$56*12,E10)*12+('Cash Flow'!$I$21/0.065)*(1-Assumptions!$C$64)-(E10+CUMPRINC(Assumptions!$C$54/12,Assumptions!$C$56*12,E10,1,MIN(Assumptions!$C$62*12-Assumptions!$C$55,Assumptions!$C$56*12),0)) -> 35090.318 | AB26: ='Cash Flow'!$I$21+PMT(Assumptions!$C$54/12,Assumptions!$C$56*12,E10)*12+('Cash Flow'!$I$21/0.07)*(1-Assumptions!$C$64)-(E10+CUMPRINC(Assumptions!$C$54/12,Assumptions!$C$56*12,E10,1,MIN(Assumptions!$C$62*12-Assumptions!$C$55,Assumptions!$C$56*12),0)) -> 21808.824 | AC26: ='Cash Flow'!$I$21+PMT(Assumptions!$C$54/12,Assumptions!$C$56*12,E10)*12+('Cash Flow'!$I$21/0.075)*(1-Assumptions!$C$64)-(E10+CUMPRINC(Assumptions!$C$54/12,Assumptions!$C$56*12,E10,1,MIN(Assumptions!$C$62*12-Assumptions!$C$55,Assumptions!$C$56*12),0)) -> 10298.196 | AD26: ='Cash Flow'!$I$21+PMT(Assumptions!$C$54/12,Assumptions!$C$56*12,E10)*12+('Cash Flow'!$I$21/0.08)*(1-Assumptions!$C$64)-(E10+CUMPRINC(Assumptions!$C$54/12,Assumptions!$C$56*12,E10,1,MIN(Assumptions!$C$62*12-Assumptions!$C$55,Assumptions!$C$56*12),0)) -> 226.39704
B27: 0.06 | C27: =IFERROR(IRR(N309:S309),"n/a") -> 0.27009247 | D27: =IFERROR(IRR(N310:S310),"n/a") -> 0.22053128 | E27: =IFERROR(IRR(N311:S311),"n/a") -> 0.17391255 | F27: =IFERROR(IRR(N312:S312),"n/a") -> 0.12913369 | G27: =IFERROR(IRR(N313:S313),"n/a") -> 0.085245031 | H27: =IFERROR(IRR(N314:S314),"n/a") -> 0.041328086 | I27: =IFERROR(IRR(N315:S315),"n/a") -> -0.0036291451 | J27: =IFERROR(IRR(N316:S316),"n/a") -> -0.050908901 | K27: =IFERROR(IRR(N317:S317),"n/a") -> -0.10239377 | V27: ='Cash Flow'!$I$21+PMT(Assumptions!$C$54/12,Assumptions!$C$56*12,E11)*12+('Cash Flow'!$I$21/0.04)*(1-Assumptions!$C$64)-(E11+CUMPRINC(Assumptions!$C$54/12,Assumptions!$C$56*12,E11,1,MIN(Assumptions!$C$62*12-Assumptions!$C$55,Assumptions!$C$56*12),0)) -> 178500.62 | W27: ='Cash Flow'!$I$21+PMT(Assumptions!$C$54/12,Assumptions!$C$56*12,E11)*12+('Cash Flow'!$I$21/0.045)*(1-Assumptions!$C$64)-(E11+CUMPRINC(Assumptions!$C$54/12,Assumptions!$C$56*12,E11,1,MIN(Assumptions!$C$62*12-Assumptions!$C$55,Assumptions!$C$56*12),0)) -> 144927.96 | X27: ='Cash Flow'!$I$21+PMT(Assumptions!$C$54/12,Assumptions!$C$56*12,E11)*12+('Cash Flow'!$I$21/0.05)*(1-Assumptions!$C$64)-(E11+CUMPRINC(Assumptions!$C$54/12,Assumptions!$C$56*12,E11,1,MIN(Assumptions!$C$62*12-Assumptions!$C$55,Assumptions!$C$56*12),0)) -> 118069.83 | Y27: ='Cash Flow'!$I$21+PMT(Assumptions!$C$54/12,Assumptions!$C$56*12,E11)*12+('Cash Flow'!$I$21/0.055)*(1-Assumptions!$C$64)-(E11+CUMPRINC(Assumptions!$C$54/12,Assumptions!$C$56*12,E11,1,MIN(Assumptions!$C$62*12-Assumptions!$C$55,Assumptions!$C$56*12),0)) -> 96094.992 | Z27: ='Cash Flow'!$I$21+PMT(Assumptions!$C$54/12,Assumptions!$C$56*12,E11)*12+('Cash Flow'!$I$21/0.06)*(1-Assumptions!$C$64)-(E11+CUMPRINC(Assumptions!$C$54/12,Assumptions!$C$56*12,E11,1,MIN(Assumptions!$C$62*12-Assumptions!$C$55,Assumptions!$C$56*12),0)) -> 77782.629 | AA27: ='Cash Flow'!$I$21+PMT(Assumptions!$C$54/12,Assumptions!$C$56*12,E11)*12+('Cash Flow'!$I$21/0.065)*(1-Assumptions!$C$64)-(E11+CUMPRINC(Assumptions!$C$54/12,Assumptions!$C$56*12,E11,1,MIN(Assumptions!$C$62*12-Assumptions!$C$55,Assumptions!$C$56*12),0)) -> 62287.553 | AB27: ='Cash Flow'!$I$21+PMT(Assumptions!$C$54/12,Assumptions!$C$56*12,E11)*12+('Cash Flow'!$I$21/0.07)*(1-Assumptions!$C$64)-(E11+CUMPRINC(Assumptions!$C$54/12,Assumptions!$C$56*12,E11,1,MIN(Assumptions!$C$62*12-Assumptions!$C$55,Assumptions!$C$56*12),0)) -> 49006.059 | AC27: ='Cash Flow'!$I$21+PMT(Assumptions!$C$54/12,Assumptions!$C$56*12,E11)*12+('Cash Flow'!$I$21/0.075)*(1-Assumptions!$C$64)-(E11+CUMPRINC(Assumptions!$C$54/12,Assumptions!$C$56*12,E11,1,MIN(Assumptions!$C$62*12-Assumptions!$C$55,Assumptions!$C$56*12),0)) -> 37495.432 | AD27: ='Cash Flow'!$I$21+PMT(Assumptions!$C$54/12,Assumptions!$C$56*12,E11)*12+('Cash Flow'!$I$21/0.08)*(1-Assumptions!$C$64)-(E11+CUMPRINC(Assumptions!$C$54/12,Assumptions!$C$56*12,E11,1,MIN(Assumptions!$C$62*12-Assumptions!$C$55,Assumptions!$C$56*12),0)) -> 27423.632
B28: 0.07 | C28: =IFERROR(IRR(N318:S318),"n/a") -> 0.35323643 | D28: =IFERROR(IRR(N319:S319),"n/a") -> 0.30729514 | E28: =IFERROR(IRR(N320:S320),"n/a") -> 0.26498129 | F28: =IFERROR(IRR(N321:S321),"n/a") -> 0.22532956 | G28: =IFERROR(IRR(N322:S322),"n/a") -> 0.18759618 | H28: =IFERROR(IRR(N323:S323),"n/a") -> 0.15117178 | I28: =IFERROR(IRR(N324:S324),"n/a") -> 0.11552186 | J28: =IFERROR(IRR(N325:S325),"n/a") -> 0.080139992 | K28: =IFERROR(IRR(N326:S326),"n/a") -> 0.044503098 | V28: ='Cash Flow'!$I$21+PMT(Assumptions!$C$54/12,Assumptions!$C$56*12,E12)*12+('Cash Flow'!$I$21/0.04)*(1-Assumptions!$C$64)-(E12+CUMPRINC(Assumptions!$C$54/12,Assumptions!$C$56*12,E12,1,MIN(Assumptions!$C$62*12-Assumptions!$C$55,Assumptions!$C$56*12),0)) -> 197927.22 | W28: ='Cash Flow'!$I$21+PMT(Assumptions!$C$54/12,Assumptions!$C$56*12,E12)*12+('Cash Flow'!$I$21/0.045)*(1-Assumptions!$C$64)-(E12+CUMPRINC(Assumptions!$C$54/12,Assumptions!$C$56*12,E12,1,MIN(Assumptions!$C$62*12-Assumptions!$C$55,Assumptions!$C$56*12),0)) -> 164354.56 | X28: ='Cash Flow'!$I$21+PMT(Assumptions!$C$54/12,Assumptions!$C$56*12,E12)*12+('Cash Flow'!$I$21/0.05)*(1-Assumptions!$C$64)-(E12+CUMPRINC(Assumptions!$C$54/12,Assumptions!$C$56*12,E12,1,MIN(Assumptions!$C$62*12-Assumptions!$C$55,Assumptions!$C$56*12),0)) -> 137496.42 | Y28: ='Cash Flow'!$I$21+PMT(Assumptions!$C$54/12,Assumptions!$C$56*12,E12)*12+('Cash Flow'!$I$21/0.055)*(1-Assumptions!$C$64)-(E12+CUMPRINC(Assumptions!$C$54/12,Assumptions!$C$56*12,E12,1,MIN(Assumptions!$C$62*12-Assumptions!$C$55,Assumptions!$C$56*12),0)) -> 115521.59 | Z28: ='Cash Flow'!$I$21+PMT(Assumptions!$C$54/12,Assumptions!$C$56*12,E12)*12+('Cash Flow'!$I$21/0.06)*(1-Assumptions!$C$64)-(E12+CUMPRINC(Assumptions!$C$54/12,Assumptions!$C$56*12,E12,1,MIN(Assumptions!$C$62*12-Assumptions!$C$55,Assumptions!$C$56*12),0)) -> 97209.226 | AA28: ='Cash Flow'!$I$21+PMT(Assumptions!$C$54/12,Assumptions!$C$56*12,E12)*12+('Cash Flow'!$I$21/0.065)*(1-Assumptions!$C$64)-(E12+CUMPRINC(Assumptions!$C$54/12,Assumptions!$C$56*12,E12,1,MIN(Assumptions!$C$62*12-Assumptions!$C$55,Assumptions!$C$56*12),0)) -> 81714.15 | AB28: ='Cash Flow'!$I$21+PMT(Assumptions!$C$54/12,Assumptions!$C$56*12,E12)*12+('Cash Flow'!$I$21/0.07)*(1-Assumptions!$C$64)-(E12+CUMPRINC(Assumptions!$C$54/12,Assumptions!$C$56*12,E12,1,MIN(Assumptions!$C$62*12-Assumptions!$C$55,Assumptions!$C$56*12),0)) -> 68432.656 | AC28: ='Cash Flow'!$I$21+PMT(Assumptions!$C$54/12,Assumptions!$C$56*12,E12)*12+('Cash Flow'!$I$21/0.075)*(1-Assumptions!$C$64)-(E12+CUMPRINC(Assumptions!$C$54/12,Assumptions!$C$56*12,E12,1,MIN(Assumptions!$C$62*12-Assumptions!$C$55,Assumptions!$C$56*12),0)) -> 56922.028 | AD28: ='Cash Flow'!$I$21+PMT(Assumptions!$C$54/12,Assumptions!$C$56*12,E12)*12+('Cash Flow'!$I$21/0.08)*(1-Assumptions!$C$64)-(E12+CUMPRINC(Assumptions!$C$54/12,Assumptions!$C$56*12,E12,1,MIN(Assumptions!$C$62*12-Assumptions!$C$55,Assumptions!$C$56*12),0)) -> 46850.229
B29: 0.08 | C29: =IFERROR(IRR(N327:S327),"n/a") -> 0.42429447 | D29: =IFERROR(IRR(N328:S328),"n/a") -> 0.38050776 | E29: =IFERROR(IRR(N329:S329),"n/a") -> 0.34069345 | F29: =IFERROR(IRR(N330:S330),"n/a") -> 0.30391849 | G29: =IFERROR(IRR(N331:S331),"n/a") -> 0.26949006 | H29: =IFERROR(IRR(N332:S332),"n/a") -> 0.23687185 | I29: =IFERROR(IRR(N333:S333),"n/a") -> 0.20563115 | J29: =IFERROR(IRR(N334:S334),"n/a") -> 0.17540352 | K29: =IFERROR(IRR(N335:S335),"n/a") -> 0.14586718 | V29: ='Cash Flow'!$I$21+PMT(Assumptions!$C$54/12,Assumptions!$C$56*12,E13)*12+('Cash Flow'!$I$21/0.04)*(1-Assumptions!$C$64)-(E13+CUMPRINC(Assumptions!$C$54/12,Assumptions!$C$56*12,E13,1,MIN(Assumptions!$C$62*12-Assumptions!$C$55,Assumptions!$C$56*12),0)) -> 212497.17 | W29: ='Cash Flow'!$I$21+PMT(Assumptions!$C$54/12,Assumptions!$C$56*12,E13)*12+('Cash Flow'!$I$21/0.045)*(1-Assumptions!$C$64)-(E13+CUMPRINC(Assumptions!$C$54/12,Assumptions!$C$56*12,E13,1,MIN(Assumptions!$C$62*12-Assumptions!$C$55,Assumptions!$C$56*12),0)) -> 178924.5 | X29: ='Cash Flow'!$I$21+PMT(Assumptions!$C$54/12,Assumptions!$C$56*12,E13)*12+('Cash Flow'!$I$21/0.05)*(1-Assumptions!$C$64)-(E13+CUMPRINC(Assumptions!$C$54/12,Assumptions!$C$56*12,E13,1,MIN(Assumptions!$C$62*12-Assumptions!$C$55,Assumptions!$C$56*12),0)) -> 152066.37 | Y29: ='Cash Flow'!$I$21+PMT(Assumptions!$C$54/12,Assumptions!$C$56*12,E13)*12+('Cash Flow'!$I$21/0.055)*(1-Assumptions!$C$64)-(E13+CUMPRINC(Assumptions!$C$54/12,Assumptions!$C$56*12,E13,1,MIN(Assumptions!$C$62*12-Assumptions!$C$55,Assumptions!$C$56*12),0)) -> 130091.54 | Z29: ='Cash Flow'!$I$21+PMT(Assumptions!$C$54/12,Assumptions!$C$56*12,E13)*12+('Cash Flow'!$I$21/0.06)*(1-Assumptions!$C$64)-(E13+CUMPRINC(Assumptions!$C$54/12,Assumptions!$C$56*12,E13,1,MIN(Assumptions!$C$62*12-Assumptions!$C$55,Assumptions!$C$56*12),0)) -> 111779.17 | AA29: ='Cash Flow'!$I$21+PMT(Assumptions!$C$54/12,Assumptions!$C$56*12,E13)*12+('Cash Flow'!$I$21/0.065)*(1-Assumptions!$C$64)-(E13+CUMPRINC(Assumptions!$C$54/12,Assumptions!$C$56*12,E13,1,MIN(Assumptions!$C$62*12-Assumptions!$C$55,Assumptions!$C$56*12),0)) -> 96284.097 | AB29: ='Cash Flow'!$I$21+PMT(Assumptions!$C$54/12,Assumptions!$C$56*12,E13)*12+('Cash Flow'!$I$21/0.07)*(1-Assumptions!$C$64)-(E13+CUMPRINC(Assumptions!$C$54/12,Assumptions!$C$56*12,E13,1,MIN(Assumptions!$C$62*12-Assumptions!$C$55,Assumptions!$C$56*12),0)) -> 83002.603 | AC29: ='Cash Flow'!$I$21+PMT(Assumptions!$C$54/12,Assumptions!$C$56*12,E13)*12+('Cash Flow'!$I$21/0.075)*(1-Assumptions!$C$64)-(E13+CUMPRINC(Assumptions!$C$54/12,Assumptions!$C$56*12,E13,1,MIN(Assumptions!$C$62*12-Assumptions!$C$55,Assumptions!$C$56*12),0)) -> 71491.975 | AD29: ='Cash Flow'!$I$21+PMT(Assumptions!$C$54/12,Assumptions!$C$56*12,E13)*12+('Cash Flow'!$I$21/0.08)*(1-Assumptions!$C$64)-(E13+CUMPRINC(Assumptions!$C$54/12,Assumptions!$C$56*12,E13,1,MIN(Assumptions!$C$62*12-Assumptions!$C$55,Assumptions!$C$56*12),0)) -> 61420.176
B30: 0.09 | C30: =IFERROR(IRR(N336:S336),"n/a") -> 0.48714091 | D30: =IFERROR(IRR(N337:S337),"n/a") -> 0.44475804 | E30: =IFERROR(IRR(N338:S338),"n/a") -> 0.40655558 | F30: =IFERROR(IRR(N339:S339),"n/a") -> 0.37160437 | G30: =IFERROR(IRR(N340:S340),"n/a") -> 0.33922408 | H30: =IFERROR(IRR(N341:S341),"n/a") -> 0.30889894 | I30: =IFERROR(IRR(N342:S342),"n/a") -> 0.28022541 | J30: =IFERROR(IRR(N343:S343),"n/a") -> 0.25287827 | K30: =IFERROR(IRR(N344:S344),"n/a") -> 0.22658749 | V30: ='Cash Flow'!$I$21+PMT(Assumptions!$C$54/12,Assumptions!$C$56*12,E14)*12+('Cash Flow'!$I$21/0.04)*(1-Assumptions!$C$64)-(E14+CUMPRINC(Assumptions!$C$54/12,Assumptions!$C$56*12,E14,1,MIN(Assumptions!$C$62*12-Assumptions!$C$55,Assumptions!$C$56*12),0)) -> 223829.35 | W30: ='Cash Flow'!$I$21+PMT(Assumptions!$C$54/12,Assumptions!$C$56*12,E14)*12+('Cash Flow'!$I$21/0.045)*(1-Assumptions!$C$64)-(E14+CUMPRINC(Assumptions!$C$54/12,Assumptions!$C$56*12,E14,1,MIN(Assumptions!$C$62*12-Assumptions!$C$55,Assumptions!$C$56*12),0)) -> 190256.68 | X30: ='Cash Flow'!$I$21+PMT(Assumptions!$C$54/12,Assumptions!$C$56*12,E14)*12+('Cash Flow'!$I$21/0.05)*(1-Assumptions!$C$64)-(E14+CUMPRINC(Assumptions!$C$54/12,Assumptions!$C$56*12,E14,1,MIN(Assumptions!$C$62*12-Assumptions!$C$55,Assumptions!$C$56*12),0)) -> 163398.55 | Y30: ='Cash Flow'!$I$21+PMT(Assumptions!$C$54/12,Assumptions!$C$56*12,E14)*12+('Cash Flow'!$I$21/0.055)*(1-Assumptions!$C$64)-(E14+CUMPRINC(Assumptions!$C$54/12,Assumptions!$C$56*12,E14,1,MIN(Assumptions!$C$62*12-Assumptions!$C$55,Assumptions!$C$56*12),0)) -> 141423.72 | Z30: ='Cash Flow'!$I$21+PMT(Assumptions!$C$54/12,Assumptions!$C$56*12,E14)*12+('Cash Flow'!$I$21/0.06)*(1-Assumptions!$C$64)-(E14+CUMPRINC(Assumptions!$C$54/12,Assumptions!$C$56*12,E14,1,MIN(Assumptions!$C$62*12-Assumptions!$C$55,Assumptions!$C$56*12),0)) -> 123111.35 | AA30: ='Cash Flow'!$I$21+PMT(Assumptions!$C$54/12,Assumptions!$C$56*12,E14)*12+('Cash Flow'!$I$21/0.065)*(1-Assumptions!$C$64)-(E14+CUMPRINC(Assumptions!$C$54/12,Assumptions!$C$56*12,E14,1,MIN(Assumptions!$C$62*12-Assumptions!$C$55,Assumptions!$C$56*12),0)) -> 107616.28 | AB30: ='Cash Flow'!$I$21+PMT(Assumptions!$C$54/12,Assumptions!$C$56*12,E14)*12+('Cash Flow'!$I$21/0.07)*(1-Assumptions!$C$64)-(E14+CUMPRINC(Assumptions!$C$54/12,Assumptions!$C$56*12,E14,1,MIN(Assumptions!$C$62*12-Assumptions!$C$55,Assumptions!$C$56*12),0)) -> 94334.784 | AC30: ='Cash Flow'!$I$21+PMT(Assumptions!$C$54/12,Assumptions!$C$56*12,E14)*12+('Cash Flow'!$I$21/0.075)*(1-Assumptions!$C$64)-(E14+CUMPRINC(Assumptions!$C$54/12,Assumptions!$C$56*12,E14,1,MIN(Assumptions!$C$62*12-Assumptions!$C$55,Assumptions!$C$56*12),0)) -> 82824.157 | AD30: ='Cash Flow'!$I$21+PMT(Assumptions!$C$54/12,Assumptions!$C$56*12,E14)*12+('Cash Flow'!$I$21/0.08)*(1-Assumptions!$C$64)-(E14+CUMPRINC(Assumptions!$C$54/12,Assumptions!$C$56*12,E14,1,MIN(Assumptions!$C$62*12-Assumptions!$C$55,Assumptions!$C$56*12),0)) -> 72752.357
B31: 0.1 | C31: =IFERROR(IRR(N345:S345),"n/a") -> 0.54402162 | D31: =IFERROR(IRR(N346:S346),"n/a") -> 0.50261227 | E31: =IFERROR(IRR(N347:S347),"n/a") -> 0.46552481 | F31: =IFERROR(IRR(N348:S348),"n/a") -> 0.43182465 | G31: =IFERROR(IRR(N349:S349),"n/a") -> 0.40083165 | H31: =IFERROR(IRR(N350:S350),"n/a") -> 0.37203462 | I31: =IFERROR(IRR(N351:S351),"n/a") -> 0.34503857 | J31: =IFERROR(IRR(N352:S352),"n/a") -> 0.31953064 | K31: =IFERROR(IRR(N353:S353),"n/a") -> 0.29525732 | V31: ='Cash Flow'!$I$21+PMT(Assumptions!$C$54/12,Assumptions!$C$56*12,E15)*12+('Cash Flow'!$I$21/0.04)*(1-Assumptions!$C$64)-(E15+CUMPRINC(Assumptions!$C$54/12,Assumptions!$C$56*12,E15,1,MIN(Assumptions!$C$62*12-Assumptions!$C$55,Assumptions!$C$56*12),0)) -> 232895.09 | W31: ='Cash Flow'!$I$21+PMT(Assumptions!$C$54/12,Assumptions!$C$56*12,E15)*12+('Cash Flow'!$I$21/0.045)*(1-Assumptions!$C$64)-(E15+CUMPRINC(Assumptions!$C$54/12,Assumptions!$C$56*12,E15,1,MIN(Assumptions!$C$62*12-Assumptions!$C$55,Assumptions!$C$56*12),0)) -> 199322.43 | X31: ='Cash Flow'!$I$21+PMT(Assumptions!$C$54/12,Assumptions!$C$56*12,E15)*12+('Cash Flow'!$I$21/0.05)*(1-Assumptions!$C$64)-(E15+CUMPRINC(Assumptions!$C$54/12,Assumptions!$C$56*12,E15,1,MIN(Assumptions!$C$62*12-Assumptions!$C$55,Assumptions!$C$56*12),0)) -> 172464.3 | Y31: ='Cash Flow'!$I$21+PMT(Assumptions!$C$54/12,Assumptions!$C$56*12,E15)*12+('Cash Flow'!$I$21/0.055)*(1-Assumptions!$C$64)-(E15+CUMPRINC(Assumptions!$C$54/12,Assumptions!$C$56*12,E15,1,MIN(Assumptions!$C$62*12-Assumptions!$C$55,Assumptions!$C$56*12),0)) -> 150489.46 | Z31: ='Cash Flow'!$I$21+PMT(Assumptions!$C$54/12,Assumptions!$C$56*12,E15)*12+('Cash Flow'!$I$21/0.06)*(1-Assumptions!$C$64)-(E15+CUMPRINC(Assumptions!$C$54/12,Assumptions!$C$56*12,E15,1,MIN(Assumptions!$C$62*12-Assumptions!$C$55,Assumptions!$C$56*12),0)) -> 132177.1 | AA31: ='Cash Flow'!$I$21+PMT(Assumptions!$C$54/12,Assumptions!$C$56*12,E15)*12+('Cash Flow'!$I$21/0.065)*(1-Assumptions!$C$64)-(E15+CUMPRINC(Assumptions!$C$54/12,Assumptions!$C$56*12,E15,1,MIN(Assumptions!$C$62*12-Assumptions!$C$55,Assumptions!$C$56*12),0)) -> 116682.02 | AB31: ='Cash Flow'!$I$21+PMT(Assumptions!$C$54/12,Assumptions!$C$56*12,E15)*12+('Cash Flow'!$I$21/0.07)*(1-Assumptions!$C$64)-(E15+CUMPRINC(Assumptions!$C$54/12,Assumptions!$C$56*12,E15,1,MIN(Assumptions!$C$62*12-Assumptions!$C$55,Assumptions!$C$56*12),0)) -> 103400.53 | AC31: ='Cash Flow'!$I$21+PMT(Assumptions!$C$54/12,Assumptions!$C$56*12,E15)*12+('Cash Flow'!$I$21/0.075)*(1-Assumptions!$C$64)-(E15+CUMPRINC(Assumptions!$C$54/12,Assumptions!$C$56*12,E15,1,MIN(Assumptions!$C$62*12-Assumptions!$C$55,Assumptions!$C$56*12),0)) -> 91889.902 | AD31: ='Cash Flow'!$I$21+PMT(Assumptions!$C$54/12,Assumptions!$C$56*12,E15)*12+('Cash Flow'!$I$21/0.08)*(1-Assumptions!$C$64)-(E15+CUMPRINC(Assumptions!$C$54/12,Assumptions!$C$56*12,E15,1,MIN(Assumptions!$C$62*12-Assumptions!$C$55,Assumptions!$C$56*12),0)) -> 81818.102
B32: 0.11 | C32: =IFERROR(IRR(N354:S354),"n/a") -> 0.59636302 | D32: =IFERROR(IRR(N355:S355),"n/a") -> 0.55566142 | E32: =IFERROR(IRR(N356:S356),"n/a") -> 0.51938628 | F32: =IFERROR(IRR(N357:S357),"n/a") -> 0.48659438 | G32: =IFERROR(IRR(N358:S358),"n/a") -> 0.45660127 | H32: =IFERROR(IRR(N359:S359),"n/a") -> 0.42889467 | I32: =IFERROR(IRR(N360:S360),"n/a") -> 0.4030809 | J32: =IFERROR(IRR(N361:S361),"n/a") -> 0.37885053 | K32: =IFERROR(IRR(N362:S362),"n/a") -> 0.35595538 | V32: ='Cash Flow'!$I$21+PMT(Assumptions!$C$54/12,Assumptions!$C$56*12,E16)*12+('Cash Flow'!$I$21/0.04)*(1-Assumptions!$C$64)-(E16+CUMPRINC(Assumptions!$C$54/12,Assumptions!$C$56*12,E16,1,MIN(Assumptions!$C$62*12-Assumptions!$C$55,Assumptions!$C$56*12),0)) -> 240312.52 | W32: ='Cash Flow'!$I$21+PMT(Assumptions!$C$54/12,Assumptions!$C$56*12,E16)*12+('Cash Flow'!$I$21/0.045)*(1-Assumptions!$C$64)-(E16+CUMPRINC(Assumptions!$C$54/12,Assumptions!$C$56*12,E16,1,MIN(Assumptions!$C$62*12-Assumptions!$C$55,Assumptions!$C$56*12),0)) -> 206739.86 | X32: ='Cash Flow'!$I$21+PMT(Assumptions!$C$54/12,Assumptions!$C$56*12,E16)*12+('Cash Flow'!$I$21/0.05)*(1-Assumptions!$C$64)-(E16+CUMPRINC(Assumptions!$C$54/12,Assumptions!$C$56*12,E16,1,MIN(Assumptions!$C$62*12-Assumptions!$C$55,Assumptions!$C$56*12),0)) -> 179881.72 | Y32: ='Cash Flow'!$I$21+PMT(Assumptions!$C$54/12,Assumptions!$C$56*12,E16)*12+('Cash Flow'!$I$21/0.055)*(1-Assumptions!$C$64)-(E16+CUMPRINC(Assumptions!$C$54/12,Assumptions!$C$56*12,E16,1,MIN(Assumptions!$C$62*12-Assumptions!$C$55,Assumptions!$C$56*12),0)) -> 157906.89 | Z32: ='Cash Flow'!$I$21+PMT(Assumptions!$C$54/12,Assumptions!$C$56*12,E16)*12+('Cash Flow'!$I$21/0.06)*(1-Assumptions!$C$64)-(E16+CUMPRINC(Assumptions!$C$54/12,Assumptions!$C$56*12,E16,1,MIN(Assumptions!$C$62*12-Assumptions!$C$55,Assumptions!$C$56*12),0)) -> 139594.53 | AA32: ='Cash Flow'!$I$21+PMT(Assumptions!$C$54/12,Assumptions!$C$56*12,E16)*12+('Cash Flow'!$I$21/0.065)*(1-Assumptions!$C$64)-(E16+CUMPRINC(Assumptions!$C$54/12,Assumptions!$C$56*12,E16,1,MIN(Assumptions!$C$62*12-Assumptions!$C$55,Assumptions!$C$56*12),0)) -> 124099.45 | AB32: ='Cash Flow'!$I$21+PMT(Assumptions!$C$54/12,Assumptions!$C$56*12,E16)*12+('Cash Flow'!$I$21/0.07)*(1-Assumptions!$C$64)-(E16+CUMPRINC(Assumptions!$C$54/12,Assumptions!$C$56*12,E16,1,MIN(Assumptions!$C$62*12-Assumptions!$C$55,Assumptions!$C$56*12),0)) -> 110817.96 | AC32: ='Cash Flow'!$I$21+PMT(Assumptions!$C$54/12,Assumptions!$C$56*12,E16)*12+('Cash Flow'!$I$21/0.075)*(1-Assumptions!$C$64)-(E16+CUMPRINC(Assumptions!$C$54/12,Assumptions!$C$56*12,E16,1,MIN(Assumptions!$C$62*12-Assumptions!$C$55,Assumptions!$C$56*12),0)) -> 99307.329 | AD32: ='Cash Flow'!$I$21+PMT(Assumptions!$C$54/12,Assumptions!$C$56*12,E16)*12+('Cash Flow'!$I$21/0.08)*(1-Assumptions!$C$64)-(E16+CUMPRINC(Assumptions!$C$54/12,Assumptions!$C$56*12,E16,1,MIN(Assumptions!$C$62*12-Assumptions!$C$55,Assumptions!$C$56*12),0)) -> 89235.53
B33: 0.12 | C33: =IFERROR(IRR(N363:S363),"n/a") -> 0.64513161 | D33: =IFERROR(IRR(N364:S364),"n/a") -> 0.60496474 | E33: =IFERROR(IRR(N365:S365),"n/a") -> 0.56930633 | F33: =IFERROR(IRR(N366:S366),"n/a") -> 0.53720349 | G33: =IFERROR(IRR(N367:S367),"n/a") -> 0.50796585 | H33: =IFERROR(IRR(N368:S368),"n/a") -> 0.4810778 | I33: =IFERROR(IRR(N369:S369),"n/a") -> 0.45614418 | J33: =IFERROR(IRR(N370:S370),"n/a") -> 0.43285555 | K33: =IFERROR(IRR(N371:S371),"n/a") -> 0.41096489 | V33: ='Cash Flow'!$I$21+PMT(Assumptions!$C$54/12,Assumptions!$C$56*12,E17)*12+('Cash Flow'!$I$21/0.04)*(1-Assumptions!$C$64)-(E17+CUMPRINC(Assumptions!$C$54/12,Assumptions!$C$56*12,E17,1,MIN(Assumptions!$C$62*12-Assumptions!$C$55,Assumptions!$C$56*12),0)) -> 246493.71 | W33: ='Cash Flow'!$I$21+PMT(Assumptions!$C$54/12,Assumptions!$C$56*12,E17)*12+('Cash Flow'!$I$21/0.045)*(1-Assumptions!$C$64)-(E17+CUMPRINC(Assumptions!$C$54/12,Assumptions!$C$56*12,E17,1,MIN(Assumptions!$C$62*12-Assumptions!$C$55,Assumptions!$C$56*12),0)) -> 212921.05 | X33: ='Cash Flow'!$I$21+PMT(Assumptions!$C$54/12,Assumptions!$C$56*12,E17)*12+('Cash Flow'!$I$21/0.05)*(1-Assumptions!$C$64)-(E17+CUMPRINC(Assumptions!$C$54/12,Assumptions!$C$56*12,E17,1,MIN(Assumptions!$C$62*12-Assumptions!$C$55,Assumptions!$C$56*12),0)) -> 186062.91 | Y33: ='Cash Flow'!$I$21+PMT(Assumptions!$C$54/12,Assumptions!$C$56*12,E17)*12+('Cash Flow'!$I$21/0.055)*(1-Assumptions!$C$64)-(E17+CUMPRINC(Assumptions!$C$54/12,Assumptions!$C$56*12,E17,1,MIN(Assumptions!$C$62*12-Assumptions!$C$55,Assumptions!$C$56*12),0)) -> 164088.08 | Z33: ='Cash Flow'!$I$21+PMT(Assumptions!$C$54/12,Assumptions!$C$56*12,E17)*12+('Cash Flow'!$I$21/0.06)*(1-Assumptions!$C$64)-(E17+CUMPRINC(Assumptions!$C$54/12,Assumptions!$C$56*12,E17,1,MIN(Assumptions!$C$62*12-Assumptions!$C$55,Assumptions!$C$56*12),0)) -> 145775.72 | AA33: ='Cash Flow'!$I$21+PMT(Assumptions!$C$54/12,Assumptions!$C$56*12,E17)*12+('Cash Flow'!$I$21/0.065)*(1-Assumptions!$C$64)-(E17+CUMPRINC(Assumptions!$C$54/12,Assumptions!$C$56*12,E17,1,MIN(Assumptions!$C$62*12-Assumptions!$C$55,Assumptions!$C$56*12),0)) -> 130280.64 | AB33: ='Cash Flow'!$I$21+PMT(Assumptions!$C$54/12,Assumptions!$C$56*12,E17)*12+('Cash Flow'!$I$21/0.07)*(1-Assumptions!$C$64)-(E17+CUMPRINC(Assumptions!$C$54/12,Assumptions!$C$56*12,E17,1,MIN(Assumptions!$C$62*12-Assumptions!$C$55,Assumptions!$C$56*12),0)) -> 116999.15 | AC33: ='Cash Flow'!$I$21+PMT(Assumptions!$C$54/12,Assumptions!$C$56*12,E17)*12+('Cash Flow'!$I$21/0.075)*(1-Assumptions!$C$64)-(E17+CUMPRINC(Assumptions!$C$54/12,Assumptions!$C$56*12,E17,1,MIN(Assumptions!$C$62*12-Assumptions!$C$55,Assumptions!$C$56*12),0)) -> 105488.52 | AD33: ='Cash Flow'!$I$21+PMT(Assumptions!$C$54/12,Assumptions!$C$56*12,E17)*12+('Cash Flow'!$I$21/0.08)*(1-Assumptions!$C$64)-(E17+CUMPRINC(Assumptions!$C$54/12,Assumptions!$C$56*12,E17,1,MIN(Assumptions!$C$62*12-Assumptions!$C$55,Assumptions!$C$56*12),0)) -> 95416.72
B34: 0.13 | C34: =IFERROR(IRR(N372:S372),"n/a") -> 0.69101472 | D34: =IFERROR(IRR(N373:S373),"n/a") -> 0.65126558 | E34: =IFERROR(IRR(N374:S374),"n/a") -> 0.61609197 | F34: =IFERROR(IRR(N375:S375),"n/a") -> 0.58453117 | G34: =IFERROR(IRR(N376:S376),"n/a") -> 0.55588641 | H34: =IFERROR(IRR(N377:S377),"n/a") -> 0.52963789 | I34: =IFERROR(IRR(N378:S378),"n/a") -> 0.50538787 | J34: =IFERROR(IRR(N379:S379),"n/a") -> 0.48282546 | K34: =IFERROR(IRR(N380:S380),"n/a") -> 0.46170312 | V34: ='Cash Flow'!$I$21+PMT(Assumptions!$C$54/12,Assumptions!$C$56*12,E18)*12+('Cash Flow'!$I$21/0.04)*(1-Assumptions!$C$64)-(E18+CUMPRINC(Assumptions!$C$54/12,Assumptions!$C$56*12,E18,1,MIN(Assumptions!$C$62*12-Assumptions!$C$55,Assumptions!$C$56*12),0)) -> 251723.95 | W34: ='Cash Flow'!$I$21+PMT(Assumptions!$C$54/12,Assumptions!$C$56*12,E18)*12+('Cash Flow'!$I$21/0.045)*(1-Assumptions!$C$64)-(E18+CUMPRINC(Assumptions!$C$54/12,Assumptions!$C$56*12,E18,1,MIN(Assumptions!$C$62*12-Assumptions!$C$55,Assumptions!$C$56*12),0)) -> 218151.28 | X34: ='Cash Flow'!$I$21+PMT(Assumptions!$C$54/12,Assumptions!$C$56*12,E18)*12+('Cash Flow'!$I$21/0.05)*(1-Assumptions!$C$64)-(E18+CUMPRINC(Assumptions!$C$54/12,Assumptions!$C$56*12,E18,1,MIN(Assumptions!$C$62*12-Assumptions!$C$55,Assumptions!$C$56*12),0)) -> 191293.15 | Y34: ='Cash Flow'!$I$21+PMT(Assumptions!$C$54/12,Assumptions!$C$56*12,E18)*12+('Cash Flow'!$I$21/0.055)*(1-Assumptions!$C$64)-(E18+CUMPRINC(Assumptions!$C$54/12,Assumptions!$C$56*12,E18,1,MIN(Assumptions!$C$62*12-Assumptions!$C$55,Assumptions!$C$56*12),0)) -> 169318.32 | Z34: ='Cash Flow'!$I$21+PMT(Assumptions!$C$54/12,Assumptions!$C$56*12,E18)*12+('Cash Flow'!$I$21/0.06)*(1-Assumptions!$C$64)-(E18+CUMPRINC(Assumptions!$C$54/12,Assumptions!$C$56*12,E18,1,MIN(Assumptions!$C$62*12-Assumptions!$C$55,Assumptions!$C$56*12),0)) -> 151005.95 | AA34: ='Cash Flow'!$I$21+PMT(Assumptions!$C$54/12,Assumptions!$C$56*12,E18)*12+('Cash Flow'!$I$21/0.065)*(1-Assumptions!$C$64)-(E18+CUMPRINC(Assumptions!$C$54/12,Assumptions!$C$56*12,E18,1,MIN(Assumptions!$C$62*12-Assumptions!$C$55,Assumptions!$C$56*12),0)) -> 135510.88 | AB34: ='Cash Flow'!$I$21+PMT(Assumptions!$C$54/12,Assumptions!$C$56*12,E18)*12+('Cash Flow'!$I$21/0.07)*(1-Assumptions!$C$64)-(E18+CUMPRINC(Assumptions!$C$54/12,Assumptions!$C$56*12,E18,1,MIN(Assumptions!$C$62*12-Assumptions!$C$55,Assumptions!$C$56*12),0)) -> 122229.38 | AC34: ='Cash Flow'!$I$21+PMT(Assumptions!$C$54/12,Assumptions!$C$56*12,E18)*12+('Cash Flow'!$I$21/0.075)*(1-Assumptions!$C$64)-(E18+CUMPRINC(Assumptions!$C$54/12,Assumptions!$C$56*12,E18,1,MIN(Assumptions!$C$62*12-Assumptions!$C$55,Assumptions!$C$56*12),0)) -> 110718.76 | AD34: ='Cash Flow'!$I$21+PMT(Assumptions!$C$54/12,Assumptions!$C$56*12,E18)*12+('Cash Flow'!$I$21/0.08)*(1-Assumptions!$C$64)-(E18+CUMPRINC(Assumptions!$C$54/12,Assumptions!$C$56*12,E18,1,MIN(Assumptions!$C$62*12-Assumptions!$C$55,Assumptions!$C$56*12),0)) -> 100646.96
B35: 0.14 | C35: =IFERROR(IRR(N381:S381),"n/a") -> 0.73451981 | D35: =IFERROR(IRR(N382:S382),"n/a") -> 0.69510711 | E35: =IFERROR(IRR(N383:S383),"n/a") -> 0.66032643 | F35: =IFERROR(IRR(N384:S384),"n/a") -> 0.62920551 | G35: =IFERROR(IRR(N385:S385),"n/a") -> 0.60104114 | H35: =IFERROR(IRR(N386:S386),"n/a") -> 0.5753091 | I35: =IFERROR(IRR(N387:S387),"n/a") -> 0.55160864 | J35: =IFERROR(IRR(N388:S388),"n/a") -> 0.52962685 | K35: =IFERROR(IRR(N389:S389),"n/a") -> 0.50911493 | V35: ='Cash Flow'!$I$21+PMT(Assumptions!$C$54/12,Assumptions!$C$56*12,E19)*12+('Cash Flow'!$I$21/0.04)*(1-Assumptions!$C$64)-(E19+CUMPRINC(Assumptions!$C$54/12,Assumptions!$C$56*12,E19,1,MIN(Assumptions!$C$62*12-Assumptions!$C$55,Assumptions!$C$56*12),0)) -> 256207.01 | W35: ='Cash Flow'!$I$21+PMT(Assumptions!$C$54/12,Assumptions!$C$56*12,E19)*12+('Cash Flow'!$I$21/0.045)*(1-Assumptions!$C$64)-(E19+CUMPRINC(Assumptions!$C$54/12,Assumptions!$C$56*12,E19,1,MIN(Assumptions!$C$62*12-Assumptions!$C$55,Assumptions!$C$56*12),0)) -> 222634.34 | X35: ='Cash Flow'!$I$21+PMT(Assumptions!$C$54/12,Assumptions!$C$56*12,E19)*12+('Cash Flow'!$I$21/0.05)*(1-Assumptions!$C$64)-(E19+CUMPRINC(Assumptions!$C$54/12,Assumptions!$C$56*12,E19,1,MIN(Assumptions!$C$62*12-Assumptions!$C$55,Assumptions!$C$56*12),0)) -> 195776.21 | Y35: ='Cash Flow'!$I$21+PMT(Assumptions!$C$54/12,Assumptions!$C$56*12,E19)*12+('Cash Flow'!$I$21/0.055)*(1-Assumptions!$C$64)-(E19+CUMPRINC(Assumptions!$C$54/12,Assumptions!$C$56*12,E19,1,MIN(Assumptions!$C$62*12-Assumptions!$C$55,Assumptions!$C$56*12),0)) -> 173801.38 | Z35: ='Cash Flow'!$I$21+PMT(Assumptions!$C$54/12,Assumptions!$C$56*12,E19)*12+('Cash Flow'!$I$21/0.06)*(1-Assumptions!$C$64)-(E19+CUMPRINC(Assumptions!$C$54/12,Assumptions!$C$56*12,E19,1,MIN(Assumptions!$C$62*12-Assumptions!$C$55,Assumptions!$C$56*12),0)) -> 155489.02 | AA35: ='Cash Flow'!$I$21+PMT(Assumptions!$C$54/12,Assumptions!$C$56*12,E19)*12+('Cash Flow'!$I$21/0.065)*(1-Assumptions!$C$64)-(E19+CUMPRINC(Assumptions!$C$54/12,Assumptions!$C$56*12,E19,1,MIN(Assumptions!$C$62*12-Assumptions!$C$55,Assumptions!$C$56*12),0)) -> 139993.94 | AB35: ='Cash Flow'!$I$21+PMT(Assumptions!$C$54/12,Assumptions!$C$56*12,E19)*12+('Cash Flow'!$I$21/0.07)*(1-Assumptions!$C$64)-(E19+CUMPRINC(Assumptions!$C$54/12,Assumptions!$C$56*12,E19,1,MIN(Assumptions!$C$62*12-Assumptions!$C$55,Assumptions!$C$56*12),0)) -> 126712.45 | AC35: ='Cash Flow'!$I$21+PMT(Assumptions!$C$54/12,Assumptions!$C$56*12,E19)*12+('Cash Flow'!$I$21/0.075)*(1-Assumptions!$C$64)-(E19+CUMPRINC(Assumptions!$C$54/12,Assumptions!$C$56*12,E19,1,MIN(Assumptions!$C$62*12-Assumptions!$C$55,Assumptions!$C$56*12),0)) -> 115201.82 | AD35: ='Cash Flow'!$I$21+PMT(Assumptions!$C$54/12,Assumptions!$C$56*12,E19)*12+('Cash Flow'!$I$21/0.08)*(1-Assumptions!$C$64)-(E19+CUMPRINC(Assumptions!$C$54/12,Assumptions!$C$56*12,E19,1,MIN(Assumptions!$C$62*12-Assumptions!$C$55,Assumptions!$C$56*12),0)) -> 105130.02
B36: 0.15 | C36: =IFERROR(IRR(N390:S390),"n/a") -> 0.77603301 | D36: =IFERROR(IRR(N391:S391),"n/a") -> 0.73689914 | E36: =IFERROR(IRR(N392:S392),"n/a") -> 0.70244591 | F36: =IFERROR(IRR(N393:S393),"n/a") -> 0.67169196 | G36: =IFERROR(IRR(N394:S394),"n/a") -> 0.64392781 | H36: =IFERROR(IRR(N395:S395),"n/a") -> 0.61862485 | I36: =IFERROR(IRR(N396:S396),"n/a") -> 0.59537922 | J36: =IFERROR(IRR(N397:S397),"n/a") -> 0.5738758 | K36: =IFERROR(IRR(N398:S398),"n/a") -> 0.55386421 | V36: ='Cash Flow'!$I$21+PMT(Assumptions!$C$54/12,Assumptions!$C$56*12,E20)*12+('Cash Flow'!$I$21/0.04)*(1-Assumptions!$C$64)-(E20+CUMPRINC(Assumptions!$C$54/12,Assumptions!$C$56*12,E20,1,MIN(Assumptions!$C$62*12-Assumptions!$C$55,Assumptions!$C$56*12),0)) -> 260092.33 | W36: ='Cash Flow'!$I$21+PMT(Assumptions!$C$54/12,Assumptions!$C$56*12,E20)*12+('Cash Flow'!$I$21/0.045)*(1-Assumptions!$C$64)-(E20+CUMPRINC(Assumptions!$C$54/12,Assumptions!$C$56*12,E20,1,MIN(Assumptions!$C$62*12-Assumptions!$C$55,Assumptions!$C$56*12),0)) -> 226519.66 | X36: ='Cash Flow'!$I$21+PMT(Assumptions!$C$54/12,Assumptions!$C$56*12,E20)*12+('Cash Flow'!$I$21/0.05)*(1-Assumptions!$C$64)-(E20+CUMPRINC(Assumptions!$C$54/12,Assumptions!$C$56*12,E20,1,MIN(Assumptions!$C$62*12-Assumptions!$C$55,Assumptions!$C$56*12),0)) -> 199661.53 | Y36: ='Cash Flow'!$I$21+PMT(Assumptions!$C$54/12,Assumptions!$C$56*12,E20)*12+('Cash Flow'!$I$21/0.055)*(1-Assumptions!$C$64)-(E20+CUMPRINC(Assumptions!$C$54/12,Assumptions!$C$56*12,E20,1,MIN(Assumptions!$C$62*12-Assumptions!$C$55,Assumptions!$C$56*12),0)) -> 177686.7 | Z36: ='Cash Flow'!$I$21+PMT(Assumptions!$C$54/12,Assumptions!$C$56*12,E20)*12+('Cash Flow'!$I$21/0.06)*(1-Assumptions!$C$64)-(E20+CUMPRINC(Assumptions!$C$54/12,Assumptions!$C$56*12,E20,1,MIN(Assumptions!$C$62*12-Assumptions!$C$55,Assumptions!$C$56*12),0)) -> 159374.33 | AA36: ='Cash Flow'!$I$21+PMT(Assumptions!$C$54/12,Assumptions!$C$56*12,E20)*12+('Cash Flow'!$I$21/0.065)*(1-Assumptions!$C$64)-(E20+CUMPRINC(Assumptions!$C$54/12,Assumptions!$C$56*12,E20,1,MIN(Assumptions!$C$62*12-Assumptions!$C$55,Assumptions!$C$56*12),0)) -> 143879.26 | AB36: ='Cash Flow'!$I$21+PMT(Assumptions!$C$54/12,Assumptions!$C$56*12,E20)*12+('Cash Flow'!$I$21/0.07)*(1-Assumptions!$C$64)-(E20+CUMPRINC(Assumptions!$C$54/12,Assumptions!$C$56*12,E20,1,MIN(Assumptions!$C$62*12-Assumptions!$C$55,Assumptions!$C$56*12),0)) -> 130597.76 | AC36: ='Cash Flow'!$I$21+PMT(Assumptions!$C$54/12,Assumptions!$C$56*12,E20)*12+('Cash Flow'!$I$21/0.075)*(1-Assumptions!$C$64)-(E20+CUMPRINC(Assumptions!$C$54/12,Assumptions!$C$56*12,E20,1,MIN(Assumptions!$C$62*12-Assumptions!$C$55,Assumptions!$C$56*12),0)) -> 119087.14 | AD36: ='Cash Flow'!$I$21+PMT(Assumptions!$C$54/12,Assumptions!$C$56*12,E20)*12+('Cash Flow'!$I$21/0.08)*(1-Assumptions!$C$64)-(E20+CUMPRINC(Assumptions!$C$54/12,Assumptions!$C$56*12,E20,1,MIN(Assumptions!$C$62*12-Assumptions!$C$55,Assumptions!$C$56*12),0)) -> 109015.34
B38: SENSITIVITY: AVG CASH-ON-CASH — Entry Cap Rate (rows) × Exit Cap Rate (columns)
B39: Avg CoC over hold period. Exit cap doesn't affect CoC — columns instead show rent level adjustment (−15% to +15% vs comps). Base = 0%.
B40: Entry Cap \ Rent Adj% | C40: -0.15 | D40: -0.1 | E40: -0.05 | F40: 0 | G40: 0.05 | H40: 0.1 | I40: 0.15
B41: 0.05 | C41: =IFERROR(AVERAGE('Cash Flow'!$E$21*0.85-E10*Assumptions!$C$54,'Cash Flow'!$F$21*0.85-E10*Assumptions!$C$54,'Cash Flow'!$G$21*0.85+PMT(Assumptions!$C$54/12,Assumptions!$C$56*12,E10)*12,'Cash Flow'!$H$21*0.85+PMT(Assumptions!$C$54/12,Assumptions!$C$56*12,E10)*12,'Cash Flow'!$I$21*0.85+PMT(Assumptions!$C$54/12,Assumptions!$C$56*12,E10)*12)/F10,"-") -> -0.016711313 | D41: =IFERROR(AVERAGE('Cash Flow'!$E$21*0.9-E10*Assumptions!$C$54,'Cash Flow'!$F$21*0.9-E10*Assumptions!$C$54,'Cash Flow'!$G$21*0.9+PMT(Assumptions!$C$54/12,Assumptions!$C$56*12,E10)*12,'Cash Flow'!$H$21*0.9+PMT(Assumptions!$C$54/12,Assumptions!$C$56*12,E10)*12,'Cash Flow'!$I$21*0.9+PMT(Assumptions!$C$54/12,Assumptions!$C$56*12,E10)*12)/F10,"-") -> -0.0084928193 | E41: =IFERROR(AVERAGE('Cash Flow'!$E$21*0.95-E10*Assumptions!$C$54,'Cash Flow'!$F$21*0.95-E10*Assumptions!$C$54,'Cash Flow'!$G$21*0.95+PMT(Assumptions!$C$54/12,Assumptions!$C$56*12,E10)*12,'Cash Flow'!$H$21*0.95+PMT(Assumptions!$C$54/12,Assumptions!$C$56*12,E10)*12,'Cash Flow'!$I$21*0.95+PMT(Assumptions!$C$54/12,Assumptions!$C$56*12,E10)*12)/F10,"-") -> -0.00027432513 | F41: =IFERROR(AVERAGE('Cash Flow'!$E$21*1-E10*Assumptions!$C$54,'Cash Flow'!$F$21*1-E10*Assumptions!$C$54,'Cash Flow'!$G$21*1+PMT(Assumptions!$C$54/12,Assumptions!$C$56*12,E10)*12,'Cash Flow'!$H$21*1+PMT(Assumptions!$C$54/12,Assumptions!$C$56*12,E10)*12,'Cash Flow'!$I$21*1+PMT(Assumptions!$C$54/12,Assumptions!$C$56*12,E10)*12)/F10,"-") -> 0.007944169 | G41: =IFERROR(AVERAGE('Cash Flow'!$E$21*1.05-E10*Assumptions!$C$54,'Cash Flow'!$F$21*1.05-E10*Assumptions!$C$54,'Cash Flow'!$G$21*1.05+PMT(Assumptions!$C$54/12,Assumptions!$C$56*12,E10)*12,'Cash Flow'!$H$21*1.05+PMT(Assumptions!$C$54/12,Assumptions!$C$56*12,E10)*12,'Cash Flow'!$I$21*1.05+PMT(Assumptions!$C$54/12,Assumptions!$C$56*12,E10)*12)/F10,"-") -> 0.016162663 | H41: =IFERROR(AVERAGE('Cash Flow'!$E$21*1.1-E10*Assumptions!$C$54,'Cash Flow'!$F$21*1.1-E10*Assumptions!$C$54,'Cash Flow'!$G$21*1.1+PMT(Assumptions!$C$54/12,Assumptions!$C$56*12,E10)*12,'Cash Flow'!$H$21*1.1+PMT(Assumptions!$C$54/12,Assumptions!$C$56*12,E10)*12,'Cash Flow'!$I$21*1.1+PMT(Assumptions!$C$54/12,Assumptions!$C$56*12,E10)*12)/F10,"-") -> 0.024381157 | I41: =IFERROR(AVERAGE('Cash Flow'!$E$21*1.15-E10*Assumptions!$C$54,'Cash Flow'!$F$21*1.15-E10*Assumptions!$C$54,'Cash Flow'!$G$21*1.15+PMT(Assumptions!$C$54/12,Assumptions!$C$56*12,E10)*12,'Cash Flow'!$H$21*1.15+PMT(Assumptions!$C$54/12,Assumptions!$C$56*12,E10)*12,'Cash Flow'!$I$21*1.15+PMT(Assumptions!$C$54/12,Assumptions!$C$56*12,E10)*12)/F10,"-") -> 0.032599651
B42: 0.06 | C42: =IFERROR(AVERAGE('Cash Flow'!$E$21*0.85-E11*Assumptions!$C$54,'Cash Flow'!$F$21*0.85-E11*Assumptions!$C$54,'Cash Flow'!$G$21*0.85+PMT(Assumptions!$C$54/12,Assumptions!$C$56*12,E11)*12,'Cash Flow'!$H$21*0.85+PMT(Assumptions!$C$54/12,Assumptions!$C$56*12,E11)*12,'Cash Flow'!$I$21*0.85+PMT(Assumptions!$C$54/12,Assumptions!$C$56*12,E11)*12)/F11,"-") -> 0.011231567 | D42: =IFERROR(AVERAGE('Cash Flow'!$E$21*0.9-E11*Assumptions!$C$54,'Cash Flow'!$F$21*0.9-E11*Assumptions!$C$54,'Cash Flow'!$G$21*0.9+PMT(Assumptions!$C$54/12,Assumptions!$C$56*12,E11)*12,'Cash Flow'!$H$21*0.9+PMT(Assumptions!$C$54/12,Assumptions!$C$56*12,E11)*12,'Cash Flow'!$I$21*0.9+PMT(Assumptions!$C$54/12,Assumptions!$C$56*12,E11)*12)/F11,"-") -> 0.02109376 | E42: =IFERROR(AVERAGE('Cash Flow'!$E$21*0.95-E11*Assumptions!$C$54,'Cash Flow'!$F$21*0.95-E11*Assumptions!$C$54,'Cash Flow'!$G$21*0.95+PMT(Assumptions!$C$54/12,Assumptions!$C$56*12,E11)*12,'Cash Flow'!$H$21*0.95+PMT(Assumptions!$C$54/12,Assumptions!$C$56*12,E11)*12,'Cash Flow'!$I$21*0.95+PMT(Assumptions!$C$54/12,Assumptions!$C$56*12,E11)*12)/F11,"-") -> 0.030955953 | F42: =IFERROR(AVERAGE('Cash Flow'!$E$21*1-E11*Assumptions!$C$54,'Cash Flow'!$F$21*1-E11*Assumptions!$C$54,'Cash Flow'!$G$21*1+PMT(Assumptions!$C$54/12,Assumptions!$C$56*12,E11)*12,'Cash Flow'!$H$21*1+PMT(Assumptions!$C$54/12,Assumptions!$C$56*12,E11)*12,'Cash Flow'!$I$21*1+PMT(Assumptions!$C$54/12,Assumptions!$C$56*12,E11)*12)/F11,"-") -> 0.040818146 | G42: =IFERROR(AVERAGE('Cash Flow'!$E$21*1.05-E11*Assumptions!$C$54,'Cash Flow'!$F$21*1.05-E11*Assumptions!$C$54,'Cash Flow'!$G$21*1.05+PMT(Assumptions!$C$54/12,Assumptions!$C$56*12,E11)*12,'Cash Flow'!$H$21*1.05+PMT(Assumptions!$C$54/12,Assumptions!$C$56*12,E11)*12,'Cash Flow'!$I$21*1.05+PMT(Assumptions!$C$54/12,Assumptions!$C$56*12,E11)*12)/F11,"-") -> 0.050680339 | H42: =IFERROR(AVERAGE('Cash Flow'!$E$21*1.1-E11*Assumptions!$C$54,'Cash Flow'!$F$21*1.1-E11*Assumptions!$C$54,'Cash Flow'!$G$21*1.1+PMT(Assumptions!$C$54/12,Assumptions!$C$56*12,E11)*12,'Cash Flow'!$H$21*1.1+PMT(Assumptions!$C$54/12,Assumptions!$C$56*12,E11)*12,'Cash Flow'!$I$21*1.1+PMT(Assumptions!$C$54/12,Assumptions!$C$56*12,E11)*12)/F11,"-") -> 0.060542531 | I42: =IFERROR(AVERAGE('Cash Flow'!$E$21*1.15-E11*Assumptions!$C$54,'Cash Flow'!$F$21*1.15-E11*Assumptions!$C$54,'Cash Flow'!$G$21*1.15+PMT(Assumptions!$C$54/12,Assumptions!$C$56*12,E11)*12,'Cash Flow'!$H$21*1.15+PMT(Assumptions!$C$54/12,Assumptions!$C$56*12,E11)*12,'Cash Flow'!$I$21*1.15+PMT(Assumptions!$C$54/12,Assumptions!$C$56*12,E11)*12)/F11,"-") -> 0.070404724
B43: 0.07 | C43: =IFERROR(AVERAGE('Cash Flow'!$E$21*0.85-E12*Assumptions!$C$54,'Cash Flow'!$F$21*0.85-E12*Assumptions!$C$54,'Cash Flow'!$G$21*0.85+PMT(Assumptions!$C$54/12,Assumptions!$C$56*12,E12)*12,'Cash Flow'!$H$21*0.85+PMT(Assumptions!$C$54/12,Assumptions!$C$56*12,E12)*12,'Cash Flow'!$I$21*0.85+PMT(Assumptions!$C$54/12,Assumptions!$C$56*12,E12)*12)/F12,"-") -> 0.039174447 | D43: =IFERROR(AVERAGE('Cash Flow'!$E$21*0.9-E12*Assumptions!$C$54,'Cash Flow'!$F$21*0.9-E12*Assumptions!$C$54,'Cash Flow'!$G$21*0.9+PMT(Assumptions!$C$54/12,Assumptions!$C$56*12,E12)*12,'Cash Flow'!$H$21*0.9+PMT(Assumptions!$C$54/12,Assumptions!$C$56*12,E12)*12,'Cash Flow'!$I$21*0.9+PMT(Assumptions!$C$54/12,Assumptions!$C$56*12,E12)*12)/F12,"-") -> 0.050680339 | E43: =IFERROR(AVERAGE('Cash Flow'!$E$21*0.95-E12*Assumptions!$C$54,'Cash Flow'!$F$21*0.95-E12*Assumptions!$C$54,'Cash Flow'!$G$21*0.95+PMT(Assumptions!$C$54/12,Assumptions!$C$56*12,E12)*12,'Cash Flow'!$H$21*0.95+PMT(Assumptions!$C$54/12,Assumptions!$C$56*12,E12)*12,'Cash Flow'!$I$21*0.95+PMT(Assumptions!$C$54/12,Assumptions!$C$56*12,E12)*12)/F12,"-") -> 0.06218623 | F43: =IFERROR(AVERAGE('Cash Flow'!$E$21*1-E12*Assumptions!$C$54,'Cash Flow'!$F$21*1-E12*Assumptions!$C$54,'Cash Flow'!$G$21*1+PMT(Assumptions!$C$54/12,Assumptions!$C$56*12,E12)*12,'Cash Flow'!$H$21*1+PMT(Assumptions!$C$54/12,Assumptions!$C$56*12,E12)*12,'Cash Flow'!$I$21*1+PMT(Assumptions!$C$54/12,Assumptions!$C$56*12,E12)*12)/F12,"-") -> 0.073692122 | G43: =IFERROR(AVERAGE('Cash Flow'!$E$21*1.05-E12*Assumptions!$C$54,'Cash Flow'!$F$21*1.05-E12*Assumptions!$C$54,'Cash Flow'!$G$21*1.05+PMT(Assumptions!$C$54/12,Assumptions!$C$56*12,E12)*12,'Cash Flow'!$H$21*1.05+PMT(Assumptions!$C$54/12,Assumptions!$C$56*12,E12)*12,'Cash Flow'!$I$21*1.05+PMT(Assumptions!$C$54/12,Assumptions!$C$56*12,E12)*12)/F12,"-") -> 0.085198014 | H43: =IFERROR(AVERAGE('Cash Flow'!$E$21*1.1-E12*Assumptions!$C$54,'Cash Flow'!$F$21*1.1-E12*Assumptions!$C$54,'Cash Flow'!$G$21*1.1+PMT(Assumptions!$C$54/12,Assumptions!$C$56*12,E12)*12,'Cash Flow'!$H$21*1.1+PMT(Assumptions!$C$54/12,Assumptions!$C$56*12,E12)*12,'Cash Flow'!$I$21*1.1+PMT(Assumptions!$C$54/12,Assumptions!$C$56*12,E12)*12)/F12,"-") -> 0.096703906 | I43: =IFERROR(AVERAGE('Cash Flow'!$E$21*1.15-E12*Assumptions!$C$54,'Cash Flow'!$F$21*1.15-E12*Assumptions!$C$54,'Cash Flow'!$G$21*1.15+PMT(Assumptions!$C$54/12,Assumptions!$C$56*12,E12)*12,'Cash Flow'!$H$21*1.15+PMT(Assumptions!$C$54/12,Assumptions!$C$56*12,E12)*12,'Cash Flow'!$I$21*1.15+PMT(Assumptions!$C$54/12,Assumptions!$C$56*12,E12)*12)/F12,"-") -> 0.1082098
B44: 0.08 | C44: =IFERROR(AVERAGE('Cash Flow'!$E$21*0.85-E13*Assumptions!$C$54,'Cash Flow'!$F$21*0.85-E13*Assumptions!$C$54,'Cash Flow'!$G$21*0.85+PMT(Assumptions!$C$54/12,Assumptions!$C$56*12,E13)*12,'Cash Flow'!$H$21*0.85+PMT(Assumptions!$C$54/12,Assumptions!$C$56*12,E13)*12,'Cash Flow'!$I$21*0.85+PMT(Assumptions!$C$54/12,Assumptions!$C$56*12,E13)*12)/F13,"-") -> 0.067117327 | D44: =IFERROR(AVERAGE('Cash Flow'!$E$21*0.9-E13*Assumptions!$C$54,'Cash Flow'!$F$21*0.9-E13*Assumptions!$C$54,'Cash Flow'!$G$21*0.9+PMT(Assumptions!$C$54/12,Assumptions!$C$56*12,E13)*12,'Cash Flow'!$H$21*0.9+PMT(Assumptions!$C$54/12,Assumptions!$C$56*12,E13)*12,'Cash Flow'!$I$21*0.9+PMT(Assumptions!$C$54/12,Assumptions!$C$56*12,E13)*12)/F13,"-") -> 0.080266917 | E44: =IFERROR(AVERAGE('Cash Flow'!$E$21*0.95-E13*Assumptions!$C$54,'Cash Flow'!$F$21*0.95-E13*Assumptions!$C$54,'Cash Flow'!$G$21*0.95+PMT(Assumptions!$C$54/12,Assumptions!$C$56*12,E13)*12,'Cash Flow'!$H$21*0.95+PMT(Assumptions!$C$54/12,Assumptions!$C$56*12,E13)*12,'Cash Flow'!$I$21*0.95+PMT(Assumptions!$C$54/12,Assumptions!$C$56*12,E13)*12)/F13,"-") -> 0.093416508 | F44: =IFERROR(AVERAGE('Cash Flow'!$E$21*1-E13*Assumptions!$C$54,'Cash Flow'!$F$21*1-E13*Assumptions!$C$54,'Cash Flow'!$G$21*1+PMT(Assumptions!$C$54/12,Assumptions!$C$56*12,E13)*12,'Cash Flow'!$H$21*1+PMT(Assumptions!$C$54/12,Assumptions!$C$56*12,E13)*12,'Cash Flow'!$I$21*1+PMT(Assumptions!$C$54/12,Assumptions!$C$56*12,E13)*12)/F13,"-") -> 0.1065661 | G44: =IFERROR(AVERAGE('Cash Flow'!$E$21*1.05-E13*Assumptions!$C$54,'Cash Flow'!$F$21*1.05-E13*Assumptions!$C$54,'Cash Flow'!$G$21*1.05+PMT(Assumptions!$C$54/12,Assumptions!$C$56*12,E13)*12,'Cash Flow'!$H$21*1.05+PMT(Assumptions!$C$54/12,Assumptions!$C$56*12,E13)*12,'Cash Flow'!$I$21*1.05+PMT(Assumptions!$C$54/12,Assumptions!$C$56*12,E13)*12)/F13,"-") -> 0.11971569 | H44: =IFERROR(AVERAGE('Cash Flow'!$E$21*1.1-E13*Assumptions!$C$54,'Cash Flow'!$F$21*1.1-E13*Assumptions!$C$54,'Cash Flow'!$G$21*1.1+PMT(Assumptions!$C$54/12,Assumptions!$C$56*12,E13)*12,'Cash Flow'!$H$21*1.1+PMT(Assumptions!$C$54/12,Assumptions!$C$56*12,E13)*12,'Cash Flow'!$I$21*1.1+PMT(Assumptions!$C$54/12,Assumptions!$C$56*12,E13)*12)/F13,"-") -> 0.13286528 | I44: =IFERROR(AVERAGE('Cash Flow'!$E$21*1.15-E13*Assumptions!$C$54,'Cash Flow'!$F$21*1.15-E13*Assumptions!$C$54,'Cash Flow'!$G$21*1.15+PMT(Assumptions!$C$54/12,Assumptions!$C$56*12,E13)*12,'Cash Flow'!$H$21*1.15+PMT(Assumptions!$C$54/12,Assumptions!$C$56*12,E13)*12,'Cash Flow'!$I$21*1.15+PMT(Assumptions!$C$54/12,Assumptions!$C$56*12,E13)*12)/F13,"-") -> 0.14601487
B45: 0.09 | C45: =IFERROR(AVERAGE('Cash Flow'!$E$21*0.85-E14*Assumptions!$C$54,'Cash Flow'!$F$21*0.85-E14*Assumptions!$C$54,'Cash Flow'!$G$21*0.85+PMT(Assumptions!$C$54/12,Assumptions!$C$56*12,E14)*12,'Cash Flow'!$H$21*0.85+PMT(Assumptions!$C$54/12,Assumptions!$C$56*12,E14)*12,'Cash Flow'!$I$21*0.85+PMT(Assumptions!$C$54/12,Assumptions!$C$56*12,E14)*12)/F14,"-") -> 0.095060207 | D45: =IFERROR(AVERAGE('Cash Flow'!$E$21*0.9-E14*Assumptions!$C$54,'Cash Flow'!$F$21*0.9-E14*Assumptions!$C$54,'Cash Flow'!$G$21*0.9+PMT(Assumptions!$C$54/12,Assumptions!$C$56*12,E14)*12,'Cash Flow'!$H$21*0.9+PMT(Assumptions!$C$54/12,Assumptions!$C$56*12,E14)*12,'Cash Flow'!$I$21*0.9+PMT(Assumptions!$C$54/12,Assumptions!$C$56*12,E14)*12)/F14,"-") -> 0.1098535 | E45: =IFERROR(AVERAGE('Cash Flow'!$E$21*0.95-E14*Assumptions!$C$54,'Cash Flow'!$F$21*0.95-E14*Assumptions!$C$54,'Cash Flow'!$G$21*0.95+PMT(Assumptions!$C$54/12,Assumptions!$C$56*12,E14)*12,'Cash Flow'!$H$21*0.95+PMT(Assumptions!$C$54/12,Assumptions!$C$56*12,E14)*12,'Cash Flow'!$I$21*0.95+PMT(Assumptions!$C$54/12,Assumptions!$C$56*12,E14)*12)/F14,"-") -> 0.12464679 | F45: =IFERROR(AVERAGE('Cash Flow'!$E$21*1-E14*Assumptions!$C$54,'Cash Flow'!$F$21*1-E14*Assumptions!$C$54,'Cash Flow'!$G$21*1+PMT(Assumptions!$C$54/12,Assumptions!$C$56*12,E14)*12,'Cash Flow'!$H$21*1+PMT(Assumptions!$C$54/12,Assumptions!$C$56*12,E14)*12,'Cash Flow'!$I$21*1+PMT(Assumptions!$C$54/12,Assumptions!$C$56*12,E14)*12)/F14,"-") -> 0.13944008 | G45: =IFERROR(AVERAGE('Cash Flow'!$E$21*1.05-E14*Assumptions!$C$54,'Cash Flow'!$F$21*1.05-E14*Assumptions!$C$54,'Cash Flow'!$G$21*1.05+PMT(Assumptions!$C$54/12,Assumptions!$C$56*12,E14)*12,'Cash Flow'!$H$21*1.05+PMT(Assumptions!$C$54/12,Assumptions!$C$56*12,E14)*12,'Cash Flow'!$I$21*1.05+PMT(Assumptions!$C$54/12,Assumptions!$C$56*12,E14)*12)/F14,"-") -> 0.15423336 | H45: =IFERROR(AVERAGE('Cash Flow'!$E$21*1.1-E14*Assumptions!$C$54,'Cash Flow'!$F$21*1.1-E14*Assumptions!$C$54,'Cash Flow'!$G$21*1.1+PMT(Assumptions!$C$54/12,Assumptions!$C$56*12,E14)*12,'Cash Flow'!$H$21*1.1+PMT(Assumptions!$C$54/12,Assumptions!$C$56*12,E14)*12,'Cash Flow'!$I$21*1.1+PMT(Assumptions!$C$54/12,Assumptions!$C$56*12,E14)*12)/F14,"-") -> 0.16902665 | I45: =IFERROR(AVERAGE('Cash Flow'!$E$21*1.15-E14*Assumptions!$C$54,'Cash Flow'!$F$21*1.15-E14*Assumptions!$C$54,'Cash Flow'!$G$21*1.15+PMT(Assumptions!$C$54/12,Assumptions!$C$56*12,E14)*12,'Cash Flow'!$H$21*1.15+PMT(Assumptions!$C$54/12,Assumptions!$C$56*12,E14)*12,'Cash Flow'!$I$21*1.15+PMT(Assumptions!$C$54/12,Assumptions!$C$56*12,E14)*12)/F14,"-") -> 0.18381994
B46: 0.1 | C46: =IFERROR(AVERAGE('Cash Flow'!$E$21*0.85-E15*Assumptions!$C$54,'Cash Flow'!$F$21*0.85-E15*Assumptions!$C$54,'Cash Flow'!$G$21*0.85+PMT(Assumptions!$C$54/12,Assumptions!$C$56*12,E15)*12,'Cash Flow'!$H$21*0.85+PMT(Assumptions!$C$54/12,Assumptions!$C$56*12,E15)*12,'Cash Flow'!$I$21*0.85+PMT(Assumptions!$C$54/12,Assumptions!$C$56*12,E15)*12)/F15,"-") -> 0.12300309 | D46: =IFERROR(AVERAGE('Cash Flow'!$E$21*0.9-E15*Assumptions!$C$54,'Cash Flow'!$F$21*0.9-E15*Assumptions!$C$54,'Cash Flow'!$G$21*0.9+PMT(Assumptions!$C$54/12,Assumptions!$C$56*12,E15)*12,'Cash Flow'!$H$21*0.9+PMT(Assumptions!$C$54/12,Assumptions!$C$56*12,E15)*12,'Cash Flow'!$I$21*0.9+PMT(Assumptions!$C$54/12,Assumptions!$C$56*12,E15)*12)/F15,"-") -> 0.13944008 | E46: =IFERROR(AVERAGE('Cash Flow'!$E$21*0.95-E15*Assumptions!$C$54,'Cash Flow'!$F$21*0.95-E15*Assumptions!$C$54,'Cash Flow'!$G$21*0.95+PMT(Assumptions!$C$54/12,Assumptions!$C$56*12,E15)*12,'Cash Flow'!$H$21*0.95+PMT(Assumptions!$C$54/12,Assumptions!$C$56*12,E15)*12,'Cash Flow'!$I$21*0.95+PMT(Assumptions!$C$54/12,Assumptions!$C$56*12,E15)*12)/F15,"-") -> 0.15587706 | F46: =IFERROR(AVERAGE('Cash Flow'!$E$21*1-E15*Assumptions!$C$54,'Cash Flow'!$F$21*1-E15*Assumptions!$C$54,'Cash Flow'!$G$21*1+PMT(Assumptions!$C$54/12,Assumptions!$C$56*12,E15)*12,'Cash Flow'!$H$21*1+PMT(Assumptions!$C$54/12,Assumptions!$C$56*12,E15)*12,'Cash Flow'!$I$21*1+PMT(Assumptions!$C$54/12,Assumptions!$C$56*12,E15)*12)/F15,"-") -> 0.17231405 | G46: =IFERROR(AVERAGE('Cash Flow'!$E$21*1.05-E15*Assumptions!$C$54,'Cash Flow'!$F$21*1.05-E15*Assumptions!$C$54,'Cash Flow'!$G$21*1.05+PMT(Assumptions!$C$54/12,Assumptions!$C$56*12,E15)*12,'Cash Flow'!$H$21*1.05+PMT(Assumptions!$C$54/12,Assumptions!$C$56*12,E15)*12,'Cash Flow'!$I$21*1.05+PMT(Assumptions!$C$54/12,Assumptions!$C$56*12,E15)*12)/F15,"-") -> 0.18875104 | H46: =IFERROR(AVERAGE('Cash Flow'!$E$21*1.1-E15*Assumptions!$C$54,'Cash Flow'!$F$21*1.1-E15*Assumptions!$C$54,'Cash Flow'!$G$21*1.1+PMT(Assumptions!$C$54/12,Assumptions!$C$56*12,E15)*12,'Cash Flow'!$H$21*1.1+PMT(Assumptions!$C$54/12,Assumptions!$C$56*12,E15)*12,'Cash Flow'!$I$21*1.1+PMT(Assumptions!$C$54/12,Assumptions!$C$56*12,E15)*12)/F15,"-") -> 0.20518803 | I46: =IFERROR(AVERAGE('Cash Flow'!$E$21*1.15-E15*Assumptions!$C$54,'Cash Flow'!$F$21*1.15-E15*Assumptions!$C$54,'Cash Flow'!$G$21*1.15+PMT(Assumptions!$C$54/12,Assumptions!$C$56*12,E15)*12,'Cash Flow'!$H$21*1.15+PMT(Assumptions!$C$54/12,Assumptions!$C$56*12,E15)*12,'Cash Flow'!$I$21*1.15+PMT(Assumptions!$C$54/12,Assumptions!$C$56*12,E15)*12)/F15,"-") -> 0.22162502
B47: 0.11 | C47: =IFERROR(AVERAGE('Cash Flow'!$E$21*0.85-E16*Assumptions!$C$54,'Cash Flow'!$F$21*0.85-E16*Assumptions!$C$54,'Cash Flow'!$G$21*0.85+PMT(Assumptions!$C$54/12,Assumptions!$C$56*12,E16)*12,'Cash Flow'!$H$21*0.85+PMT(Assumptions!$C$54/12,Assumptions!$C$56*12,E16)*12,'Cash Flow'!$I$21*0.85+PMT(Assumptions!$C$54/12,Assumptions!$C$56*12,E16)*12)/F16,"-") -> 0.15094597 | D47: =IFERROR(AVERAGE('Cash Flow'!$E$21*0.9-E16*Assumptions!$C$54,'Cash Flow'!$F$21*0.9-E16*Assumptions!$C$54,'Cash Flow'!$G$21*0.9+PMT(Assumptions!$C$54/12,Assumptions!$C$56*12,E16)*12,'Cash Flow'!$H$21*0.9+PMT(Assumptions!$C$54/12,Assumptions!$C$56*12,E16)*12,'Cash Flow'!$I$21*0.9+PMT(Assumptions!$C$54/12,Assumptions!$C$56*12,E16)*12)/F16,"-") -> 0.16902665 | E47: =IFERROR(AVERAGE('Cash Flow'!$E$21*0.95-E16*Assumptions!$C$54,'Cash Flow'!$F$21*0.95-E16*Assumptions!$C$54,'Cash Flow'!$G$21*0.95+PMT(Assumptions!$C$54/12,Assumptions!$C$56*12,E16)*12,'Cash Flow'!$H$21*0.95+PMT(Assumptions!$C$54/12,Assumptions!$C$56*12,E16)*12,'Cash Flow'!$I$21*0.95+PMT(Assumptions!$C$54/12,Assumptions!$C$56*12,E16)*12)/F16,"-") -> 0.18710734 | F47: =IFERROR(AVERAGE('Cash Flow'!$E$21*1-E16*Assumptions!$C$54,'Cash Flow'!$F$21*1-E16*Assumptions!$C$54,'Cash Flow'!$G$21*1+PMT(Assumptions!$C$54/12,Assumptions!$C$56*12,E16)*12,'Cash Flow'!$H$21*1+PMT(Assumptions!$C$54/12,Assumptions!$C$56*12,E16)*12,'Cash Flow'!$I$21*1+PMT(Assumptions!$C$54/12,Assumptions!$C$56*12,E16)*12)/F16,"-") -> 0.20518803 | G47: =IFERROR(AVERAGE('Cash Flow'!$E$21*1.05-E16*Assumptions!$C$54,'Cash Flow'!$F$21*1.05-E16*Assumptions!$C$54,'Cash Flow'!$G$21*1.05+PMT(Assumptions!$C$54/12,Assumptions!$C$56*12,E16)*12,'Cash Flow'!$H$21*1.05+PMT(Assumptions!$C$54/12,Assumptions!$C$56*12,E16)*12,'Cash Flow'!$I$21*1.05+PMT(Assumptions!$C$54/12,Assumptions!$C$56*12,E16)*12)/F16,"-") -> 0.22326872 | H47: =IFERROR(AVERAGE('Cash Flow'!$E$21*1.1-E16*Assumptions!$C$54,'Cash Flow'!$F$21*1.1-E16*Assumptions!$C$54,'Cash Flow'!$G$21*1.1+PMT(Assumptions!$C$54/12,Assumptions!$C$56*12,E16)*12,'Cash Flow'!$H$21*1.1+PMT(Assumptions!$C$54/12,Assumptions!$C$56*12,E16)*12,'Cash Flow'!$I$21*1.1+PMT(Assumptions!$C$54/12,Assumptions!$C$56*12,E16)*12)/F16,"-") -> 0.2413494 | I47: =IFERROR(AVERAGE('Cash Flow'!$E$21*1.15-E16*Assumptions!$C$54,'Cash Flow'!$F$21*1.15-E16*Assumptions!$C$54,'Cash Flow'!$G$21*1.15+PMT(Assumptions!$C$54/12,Assumptions!$C$56*12,E16)*12,'Cash Flow'!$H$21*1.15+PMT(Assumptions!$C$54/12,Assumptions!$C$56*12,E16)*12,'Cash Flow'!$I$21*1.15+PMT(Assumptions!$C$54/12,Assumptions!$C$56*12,E16)*12)/F16,"-") -> 0.25943009
B48: 0.12 | C48: =IFERROR(AVERAGE('Cash Flow'!$E$21*0.85-E17*Assumptions!$C$54,'Cash Flow'!$F$21*0.85-E17*Assumptions!$C$54,'Cash Flow'!$G$21*0.85+PMT(Assumptions!$C$54/12,Assumptions!$C$56*12,E17)*12,'Cash Flow'!$H$21*0.85+PMT(Assumptions!$C$54/12,Assumptions!$C$56*12,E17)*12,'Cash Flow'!$I$21*0.85+PMT(Assumptions!$C$54/12,Assumptions!$C$56*12,E17)*12)/F17,"-") -> 0.17888885 | D48: =IFERROR(AVERAGE('Cash Flow'!$E$21*0.9-E17*Assumptions!$C$54,'Cash Flow'!$F$21*0.9-E17*Assumptions!$C$54,'Cash Flow'!$G$21*0.9+PMT(Assumptions!$C$54/12,Assumptions!$C$56*12,E17)*12,'Cash Flow'!$H$21*0.9+PMT(Assumptions!$C$54/12,Assumptions!$C$56*12,E17)*12,'Cash Flow'!$I$21*0.9+PMT(Assumptions!$C$54/12,Assumptions!$C$56*12,E17)*12)/F17,"-") -> 0.19861323 | E48: =IFERROR(AVERAGE('Cash Flow'!$E$21*0.95-E17*Assumptions!$C$54,'Cash Flow'!$F$21*0.95-E17*Assumptions!$C$54,'Cash Flow'!$G$21*0.95+PMT(Assumptions!$C$54/12,Assumptions!$C$56*12,E17)*12,'Cash Flow'!$H$21*0.95+PMT(Assumptions!$C$54/12,Assumptions!$C$56*12,E17)*12,'Cash Flow'!$I$21*0.95+PMT(Assumptions!$C$54/12,Assumptions!$C$56*12,E17)*12)/F17,"-") -> 0.21833762 | F48: =IFERROR(AVERAGE('Cash Flow'!$E$21*1-E17*Assumptions!$C$54,'Cash Flow'!$F$21*1-E17*Assumptions!$C$54,'Cash Flow'!$G$21*1+PMT(Assumptions!$C$54/12,Assumptions!$C$56*12,E17)*12,'Cash Flow'!$H$21*1+PMT(Assumptions!$C$54/12,Assumptions!$C$56*12,E17)*12,'Cash Flow'!$I$21*1+PMT(Assumptions!$C$54/12,Assumptions!$C$56*12,E17)*12)/F17,"-") -> 0.238062 | G48: =IFERROR(AVERAGE('Cash Flow'!$E$21*1.05-E17*Assumptions!$C$54,'Cash Flow'!$F$21*1.05-E17*Assumptions!$C$54,'Cash Flow'!$G$21*1.05+PMT(Assumptions!$C$54/12,Assumptions!$C$56*12,E17)*12,'Cash Flow'!$H$21*1.05+PMT(Assumptions!$C$54/12,Assumptions!$C$56*12,E17)*12,'Cash Flow'!$I$21*1.05+PMT(Assumptions!$C$54/12,Assumptions!$C$56*12,E17)*12)/F17,"-") -> 0.25778639 | H48: =IFERROR(AVERAGE('Cash Flow'!$E$21*1.1-E17*Assumptions!$C$54,'Cash Flow'!$F$21*1.1-E17*Assumptions!$C$54,'Cash Flow'!$G$21*1.1+PMT(Assumptions!$C$54/12,Assumptions!$C$56*12,E17)*12,'Cash Flow'!$H$21*1.1+PMT(Assumptions!$C$54/12,Assumptions!$C$56*12,E17)*12,'Cash Flow'!$I$21*1.1+PMT(Assumptions!$C$54/12,Assumptions!$C$56*12,E17)*12)/F17,"-") -> 0.27751078 | I48: =IFERROR(AVERAGE('Cash Flow'!$E$21*1.15-E17*Assumptions!$C$54,'Cash Flow'!$F$21*1.15-E17*Assumptions!$C$54,'Cash Flow'!$G$21*1.15+PMT(Assumptions!$C$54/12,Assumptions!$C$56*12,E17)*12,'Cash Flow'!$H$21*1.15+PMT(Assumptions!$C$54/12,Assumptions!$C$56*12,E17)*12,'Cash Flow'!$I$21*1.15+PMT(Assumptions!$C$54/12,Assumptions!$C$56*12,E17)*12)/F17,"-") -> 0.29723516
B49: 0.13 | C49: =IFERROR(AVERAGE('Cash Flow'!$E$21*0.85-E18*Assumptions!$C$54,'Cash Flow'!$F$21*0.85-E18*Assumptions!$C$54,'Cash Flow'!$G$21*0.85+PMT(Assumptions!$C$54/12,Assumptions!$C$56*12,E18)*12,'Cash Flow'!$H$21*0.85+PMT(Assumptions!$C$54/12,Assumptions!$C$56*12,E18)*12,'Cash Flow'!$I$21*0.85+PMT(Assumptions!$C$54/12,Assumptions!$C$56*12,E18)*12)/F18,"-") -> 0.20683173 | D49: =IFERROR(AVERAGE('Cash Flow'!$E$21*0.9-E18*Assumptions!$C$54,'Cash Flow'!$F$21*0.9-E18*Assumptions!$C$54,'Cash Flow'!$G$21*0.9+PMT(Assumptions!$C$54/12,Assumptions!$C$56*12,E18)*12,'Cash Flow'!$H$21*0.9+PMT(Assumptions!$C$54/12,Assumptions!$C$56*12,E18)*12,'Cash Flow'!$I$21*0.9+PMT(Assumptions!$C$54/12,Assumptions!$C$56*12,E18)*12)/F18,"-") -> 0.22819981 | E49: =IFERROR(AVERAGE('Cash Flow'!$E$21*0.95-E18*Assumptions!$C$54,'Cash Flow'!$F$21*0.95-E18*Assumptions!$C$54,'Cash Flow'!$G$21*0.95+PMT(Assumptions!$C$54/12,Assumptions!$C$56*12,E18)*12,'Cash Flow'!$H$21*0.95+PMT(Assumptions!$C$54/12,Assumptions!$C$56*12,E18)*12,'Cash Flow'!$I$21*0.95+PMT(Assumptions!$C$54/12,Assumptions!$C$56*12,E18)*12)/F18,"-") -> 0.2495679 | F49: =IFERROR(AVERAGE('Cash Flow'!$E$21*1-E18*Assumptions!$C$54,'Cash Flow'!$F$21*1-E18*Assumptions!$C$54,'Cash Flow'!$G$21*1+PMT(Assumptions!$C$54/12,Assumptions!$C$56*12,E18)*12,'Cash Flow'!$H$21*1+PMT(Assumptions!$C$54/12,Assumptions!$C$56*12,E18)*12,'Cash Flow'!$I$21*1+PMT(Assumptions!$C$54/12,Assumptions!$C$56*12,E18)*12)/F18,"-") -> 0.27093598 | G49: =IFERROR(AVERAGE('Cash Flow'!$E$21*1.05-E18*Assumptions!$C$54,'Cash Flow'!$F$21*1.05-E18*Assumptions!$C$54,'Cash Flow'!$G$21*1.05+PMT(Assumptions!$C$54/12,Assumptions!$C$56*12,E18)*12,'Cash Flow'!$H$21*1.05+PMT(Assumptions!$C$54/12,Assumptions!$C$56*12,E18)*12,'Cash Flow'!$I$21*1.05+PMT(Assumptions!$C$54/12,Assumptions!$C$56*12,E18)*12)/F18,"-") -> 0.29230407 | H49: =IFERROR(AVERAGE('Cash Flow'!$E$21*1.1-E18*Assumptions!$C$54,'Cash Flow'!$F$21*1.1-E18*Assumptions!$C$54,'Cash Flow'!$G$21*1.1+PMT(Assumptions!$C$54/12,Assumptions!$C$56*12,E18)*12,'Cash Flow'!$H$21*1.1+PMT(Assumptions!$C$54/12,Assumptions!$C$56*12,E18)*12,'Cash Flow'!$I$21*1.1+PMT(Assumptions!$C$54/12,Assumptions!$C$56*12,E18)*12)/F18,"-") -> 0.31367215 | I49: =IFERROR(AVERAGE('Cash Flow'!$E$21*1.15-E18*Assumptions!$C$54,'Cash Flow'!$F$21*1.15-E18*Assumptions!$C$54,'Cash Flow'!$G$21*1.15+PMT(Assumptions!$C$54/12,Assumptions!$C$56*12,E18)*12,'Cash Flow'!$H$21*1.15+PMT(Assumptions!$C$54/12,Assumptions!$C$56*12,E18)*12,'Cash Flow'!$I$21*1.15+PMT(Assumptions!$C$54/12,Assumptions!$C$56*12,E18)*12)/F18,"-") -> 0.33504024
B50: 0.14 | C50: =IFERROR(AVERAGE('Cash Flow'!$E$21*0.85-E19*Assumptions!$C$54,'Cash Flow'!$F$21*0.85-E19*Assumptions!$C$54,'Cash Flow'!$G$21*0.85+PMT(Assumptions!$C$54/12,Assumptions!$C$56*12,E19)*12,'Cash Flow'!$H$21*0.85+PMT(Assumptions!$C$54/12,Assumptions!$C$56*12,E19)*12,'Cash Flow'!$I$21*0.85+PMT(Assumptions!$C$54/12,Assumptions!$C$56*12,E19)*12)/F19,"-") -> 0.23477461 | D50: =IFERROR(AVERAGE('Cash Flow'!$E$21*0.9-E19*Assumptions!$C$54,'Cash Flow'!$F$21*0.9-E19*Assumptions!$C$54,'Cash Flow'!$G$21*0.9+PMT(Assumptions!$C$54/12,Assumptions!$C$56*12,E19)*12,'Cash Flow'!$H$21*0.9+PMT(Assumptions!$C$54/12,Assumptions!$C$56*12,E19)*12,'Cash Flow'!$I$21*0.9+PMT(Assumptions!$C$54/12,Assumptions!$C$56*12,E19)*12)/F19,"-") -> 0.25778639 | E50: =IFERROR(AVERAGE('Cash Flow'!$E$21*0.95-E19*Assumptions!$C$54,'Cash Flow'!$F$21*0.95-E19*Assumptions!$C$54,'Cash Flow'!$G$21*0.95+PMT(Assumptions!$C$54/12,Assumptions!$C$56*12,E19)*12,'Cash Flow'!$H$21*0.95+PMT(Assumptions!$C$54/12,Assumptions!$C$56*12,E19)*12,'Cash Flow'!$I$21*0.95+PMT(Assumptions!$C$54/12,Assumptions!$C$56*12,E19)*12)/F19,"-") -> 0.28079817 | F50: =IFERROR(AVERAGE('Cash Flow'!$E$21*1-E19*Assumptions!$C$54,'Cash Flow'!$F$21*1-E19*Assumptions!$C$54,'Cash Flow'!$G$21*1+PMT(Assumptions!$C$54/12,Assumptions!$C$56*12,E19)*12,'Cash Flow'!$H$21*1+PMT(Assumptions!$C$54/12,Assumptions!$C$56*12,E19)*12,'Cash Flow'!$I$21*1+PMT(Assumptions!$C$54/12,Assumptions!$C$56*12,E19)*12)/F19,"-") -> 0.30380996 | G50: =IFERROR(AVERAGE('Cash Flow'!$E$21*1.05-E19*Assumptions!$C$54,'Cash Flow'!$F$21*1.05-E19*Assumptions!$C$54,'Cash Flow'!$G$21*1.05+PMT(Assumptions!$C$54/12,Assumptions!$C$56*12,E19)*12,'Cash Flow'!$H$21*1.05+PMT(Assumptions!$C$54/12,Assumptions!$C$56*12,E19)*12,'Cash Flow'!$I$21*1.05+PMT(Assumptions!$C$54/12,Assumptions!$C$56*12,E19)*12)/F19,"-") -> 0.32682174 | H50: =IFERROR(AVERAGE('Cash Flow'!$E$21*1.1-E19*Assumptions!$C$54,'Cash Flow'!$F$21*1.1-E19*Assumptions!$C$54,'Cash Flow'!$G$21*1.1+PMT(Assumptions!$C$54/12,Assumptions!$C$56*12,E19)*12,'Cash Flow'!$H$21*1.1+PMT(Assumptions!$C$54/12,Assumptions!$C$56*12,E19)*12,'Cash Flow'!$I$21*1.1+PMT(Assumptions!$C$54/12,Assumptions!$C$56*12,E19)*12)/F19,"-") -> 0.34983353 | I50: =IFERROR(AVERAGE('Cash Flow'!$E$21*1.15-E19*Assumptions!$C$54,'Cash Flow'!$F$21*1.15-E19*Assumptions!$C$54,'Cash Flow'!$G$21*1.15+PMT(Assumptions!$C$54/12,Assumptions!$C$56*12,E19)*12,'Cash Flow'!$H$21*1.15+PMT(Assumptions!$C$54/12,Assumptions!$C$56*12,E19)*12,'Cash Flow'!$I$21*1.15+PMT(Assumptions!$C$54/12,Assumptions!$C$56*12,E19)*12)/F19,"-") -> 0.37284531
B51: 0.15 | C51: =IFERROR(AVERAGE('Cash Flow'!$E$21*0.85-E20*Assumptions!$C$54,'Cash Flow'!$F$21*0.85-E20*Assumptions!$C$54,'Cash Flow'!$G$21*0.85+PMT(Assumptions!$C$54/12,Assumptions!$C$56*12,E20)*12,'Cash Flow'!$H$21*0.85+PMT(Assumptions!$C$54/12,Assumptions!$C$56*12,E20)*12,'Cash Flow'!$I$21*0.85+PMT(Assumptions!$C$54/12,Assumptions!$C$56*12,E20)*12)/F20,"-") -> 0.26271749 | D51: =IFERROR(AVERAGE('Cash Flow'!$E$21*0.9-E20*Assumptions!$C$54,'Cash Flow'!$F$21*0.9-E20*Assumptions!$C$54,'Cash Flow'!$G$21*0.9+PMT(Assumptions!$C$54/12,Assumptions!$C$56*12,E20)*12,'Cash Flow'!$H$21*0.9+PMT(Assumptions!$C$54/12,Assumptions!$C$56*12,E20)*12,'Cash Flow'!$I$21*0.9+PMT(Assumptions!$C$54/12,Assumptions!$C$56*12,E20)*12)/F20,"-") -> 0.28737297 | E51: =IFERROR(AVERAGE('Cash Flow'!$E$21*0.95-E20*Assumptions!$C$54,'Cash Flow'!$F$21*0.95-E20*Assumptions!$C$54,'Cash Flow'!$G$21*0.95+PMT(Assumptions!$C$54/12,Assumptions!$C$56*12,E20)*12,'Cash Flow'!$H$21*0.95+PMT(Assumptions!$C$54/12,Assumptions!$C$56*12,E20)*12,'Cash Flow'!$I$21*0.95+PMT(Assumptions!$C$54/12,Assumptions!$C$56*12,E20)*12)/F20,"-") -> 0.31202845 | F51: =IFERROR(AVERAGE('Cash Flow'!$E$21*1-E20*Assumptions!$C$54,'Cash Flow'!$F$21*1-E20*Assumptions!$C$54,'Cash Flow'!$G$21*1+PMT(Assumptions!$C$54/12,Assumptions!$C$56*12,E20)*12,'Cash Flow'!$H$21*1+PMT(Assumptions!$C$54/12,Assumptions!$C$56*12,E20)*12,'Cash Flow'!$I$21*1+PMT(Assumptions!$C$54/12,Assumptions!$C$56*12,E20)*12)/F20,"-") -> 0.33668393 | G51: =IFERROR(AVERAGE('Cash Flow'!$E$21*1.05-E20*Assumptions!$C$54,'Cash Flow'!$F$21*1.05-E20*Assumptions!$C$54,'Cash Flow'!$G$21*1.05+PMT(Assumptions!$C$54/12,Assumptions!$C$56*12,E20)*12,'Cash Flow'!$H$21*1.05+PMT(Assumptions!$C$54/12,Assumptions!$C$56*12,E20)*12,'Cash Flow'!$I$21*1.05+PMT(Assumptions!$C$54/12,Assumptions!$C$56*12,E20)*12)/F20,"-") -> 0.36133942 | H51: =IFERROR(AVERAGE('Cash Flow'!$E$21*1.1-E20*Assumptions!$C$54,'Cash Flow'!$F$21*1.1-E20*Assumptions!$C$54,'Cash Flow'!$G$21*1.1+PMT(Assumptions!$C$54/12,Assumptions!$C$56*12,E20)*12,'Cash Flow'!$H$21*1.1+PMT(Assumptions!$C$54/12,Assumptions!$C$56*12,E20)*12,'Cash Flow'!$I$21*1.1+PMT(Assumptions!$C$54/12,Assumptions!$C$56*12,E20)*12)/F20,"-") -> 0.3859949 | I51: =IFERROR(AVERAGE('Cash Flow'!$E$21*1.15-E20*Assumptions!$C$54,'Cash Flow'!$F$21*1.15-E20*Assumptions!$C$54,'Cash Flow'!$G$21*1.15+PMT(Assumptions!$C$54/12,Assumptions!$C$56*12,E20)*12,'Cash Flow'!$H$21*1.15+PMT(Assumptions!$C$54/12,Assumptions!$C$56*12,E20)*12,'Cash Flow'!$I$21*1.15+PMT(Assumptions!$C$54/12,Assumptions!$C$56*12,E20)*12)/F20,"-") -> 0.41065038
B53: LEGEND | C53: 🟢 Meets target | D53: 🟡 Within 3% / 2% of target | E53: 🔴 Below target | F53: ★ = Base case (current model price) | G53: Gold col = live exit cap / base rent adj (0%)
B55: MODEL NOTE: | C55: ="Current asking price ($"&TEXT(Assumptions!$C$7,"#,##0")&") implies a "&TEXT('Cash Flow'!$E$21/Assumptions!$C$7,"0.0%")&" entry cap on Yr1 NOI ($"&TEXT('Cash Flow'!$E$21,"#,##0")&"). All scenarios above are at lower implied prices. Use to determine max bid to hit your IRR and CoC targets." -> Current asking price ($12,500,000) implies a 0.1% entry cap on Yr1 NOI ($11,207). All scenarios above are at lower implied prices. Use to determine max bid to hit your IRR and CoC targets.
N300: =N10 -> -71727.552 | O300: =O10 -> 1008.6687 | P300: =P10 -> 1344.8916 | Q300: =Q10 -> -99.716499 | R300: =R10 -> 163.30119 | S300: =V26 -> 151303.39
N301: =N10 -> -71727.552 | O301: =O10 -> 1008.6687 | P301: =P10 -> 1344.8916 | Q301: =Q10 -> -99.716499 | R301: =R10 -> 163.30119 | S301: =W26 -> 117730.72
N302: =N10 -> -71727.552 | O302: =O10 -> 1008.6687 | P302: =P10 -> 1344.8916 | Q302: =Q10 -> -99.716499 | R302: =R10 -> 163.30119 | S302: =X26 -> 90872.592
N303: =N10 -> -71727.552 | O303: =O10 -> 1008.6687 | P303: =P10 -> 1344.8916 | Q303: =Q10 -> -99.716499 | R303: =R10 -> 163.30119 | S303: =Y26 -> 68897.757
N304: =N10 -> -71727.552 | O304: =O10 -> 1008.6687 | P304: =P10 -> 1344.8916 | Q304: =Q10 -> -99.716499 | R304: =R10 -> 163.30119 | S304: =Z26 -> 50585.394
N305: =N10 -> -71727.552 | O305: =O10 -> 1008.6687 | P305: =P10 -> 1344.8916 | Q305: =Q10 -> -99.716499 | R305: =R10 -> 163.30119 | S305: =AA26 -> 35090.318
N306: =N10 -> -71727.552 | O306: =O10 -> 1008.6687 | P306: =P10 -> 1344.8916 | Q306: =Q10 -> -99.716499 | R306: =R10 -> 163.30119 | S306: =AB26 -> 21808.824
N307: =N10 -> -71727.552 | O307: =O10 -> 1008.6687 | P307: =P10 -> 1344.8916 | Q307: =Q10 -> -99.716499 | R307: =R10 -> 163.30119 | S307: =AC26 -> 10298.196
N308: =N10 -> -71727.552 | O308: =O10 -> 1008.6687 | P308: =P10 -> 1344.8916 | Q308: =Q10 -> -99.716499 | R308: =R10 -> 163.30119 | S308: =AD26 -> 226.39704
N309: =N11 -> -59772.96 | O309: =O11 -> 2708.4623 | P309: =P11 -> 3044.6852 | Q309: =Q11 -> 1883.7638 | R309: =R11 -> 2146.7815 | S309: =V27 -> 178500.62
N310: =N11 -> -59772.96 | O310: =O11 -> 2708.4623 | P310: =P11 -> 3044.6852 | Q310: =Q11 -> 1883.7638 | R310: =R11 -> 2146.7815 | S310: =W27 -> 144927.96
N311: =N11 -> -59772.96 | O311: =O11 -> 2708.4623 | P311: =P11 -> 3044.6852 | Q311: =Q11 -> 1883.7638 | R311: =R11 -> 2146.7815 | S311: =X27 -> 118069.83
N312: =N11 -> -59772.96 | O312: =O11 -> 2708.4623 | P312: =P11 -> 3044.6852 | Q312: =Q11 -> 1883.7638 | R312: =R11 -> 2146.7815 | S312: =Y27 -> 96094.992
N313: =N11 -> -59772.96 | O313: =O11 -> 2708.4623 | P313: =P11 -> 3044.6852 | Q313: =Q11 -> 1883.7638 | R313: =R11 -> 2146.7815 | S313: =Z27 -> 77782.629
N314: =N11 -> -59772.96 | O314: =O11 -> 2708.4623 | P314: =P11 -> 3044.6852 | Q314: =Q11 -> 1883.7638 | R314: =R11 -> 2146.7815 | S314: =AA27 -> 62287.553
N315: =N11 -> -59772.96 | O315: =O11 -> 2708.4623 | P315: =P11 -> 3044.6852 | Q315: =Q11 -> 1883.7638 | R315: =R11 -> 2146.7815 | S315: =AB27 -> 49006.059
N316: =N11 -> -59772.96 | O316: =O11 -> 2708.4623 | P316: =P11 -> 3044.6852 | Q316: =Q11 -> 1883.7638 | R316: =R11 -> 2146.7815 | S316: =AC27 -> 37495.432
N317: =N11 -> -59772.96 | O317: =O11 -> 2708.4623 | P317: =P11 -> 3044.6852 | Q317: =Q11 -> 1883.7638 | R317: =R11 -> 2146.7815 | S317: =AD27 -> 27423.632
N318: =N12 -> -51233.966 | O318: =O12 -> 3922.6005 | P318: =P12 -> 4258.8234 | Q318: =Q12 -> 3300.5354 | R318: =R12 -> 3563.5531 | S318: =V28 -> 197927.22
N319: =N12 -> -51233.966 | O319: =O12 -> 3922.6005 | P319: =P12 -> 4258.8234 | Q319: =Q12 -> 3300.5354 | R319: =R12 -> 3563.5531 | S319: =W28 -> 164354.56
N320: =N12 -> -51233.966 | O320: =O12 -> 3922.6005 | P320: =P12 -> 4258.8234 | Q320: =Q12 -> 3300.5354 | R320: =R12 -> 3563.5531 | S320: =X28 -> 137496.42
N321: =N12 -> -51233.966 | O321: =O12 -> 3922.6005 | P321: =P12 -> 4258.8234 | Q321: =Q12 -> 3300.5354 | R321: =R12 -> 3563.5531 | S321: =Y28 -> 115521.59
N322: =N12 -> -51233.966 | O322: =O12 -> 3922.6005 | P322: =P12 -> 4258.8234 | Q322: =Q12 -> 3300.5354 | R322: =R12 -> 3563.5531 | S322: =Z28 -> 97209.226
N323: =N12 -> -51233.966 | O323: =O12 -> 3922.6005 | P323: =P12 -> 4258.8234 | Q323: =Q12 -> 3300.5354 | R323: =R12 -> 3563.5531 | S323: =AA28 -> 81714.15
N324: =N12 -> -51233.966 | O324: =O12 -> 3922.6005 | P324: =P12 -> 4258.8234 | Q324: =Q12 -> 3300.5354 | R324: =R12 -> 3563.5531 | S324: =AB28 -> 68432.656
N325: =N12 -> -51233.966 | O325: =O12 -> 3922.6005 | P325: =P12 -> 4258.8234 | Q325: =Q12 -> 3300.5354 | R325: =R12 -> 3563.5531 | S325: =AC28 -> 56922.028
N326: =N12 -> -51233.966 | O326: =O12 -> 3922.6005 | P326: =P12 -> 4258.8234 | Q326: =Q12 -> 3300.5354 | R326: =R12 -> 3563.5531 | S326: =AD28 -> 46850.229
N327: =N13 -> -44829.72 | O327: =O13 -> 4833.2042 | P327: =P13 -> 5169.4271 | Q327: =Q13 -> 4363.1141 | R327: =R13 -> 4626.1318 | S327: =V29 -> 212497.17
N328: =N13 -> -44829.72 | O328: =O13 -> 4833.2042 | P328: =P13 -> 5169.4271 | Q328: =Q13 -> 4363.1141 | R328: =R13 -> 4626.1318 | S328: =W29 -> 178924.5
N329: =N13 -> -44829.72 | O329: =O13 -> 4833.2042 | P329: =P13 -> 5169.4271 | Q329: =Q13 -> 4363.1141 | R329: =R13 -> 4626.1318 | S329: =X29 -> 152066.37
N330: =N13 -> -44829.72 | O330: =O13 -> 4833.2042 | P330: =P13 -> 5169.4271 | Q330: =Q13 -> 4363.1141 | R330: =R13 -> 4626.1318 | S330: =Y29 -> 130091.54
N331: =N13 -> -44829.72 | O331: =O13 -> 4833.2042 | P331: =P13 -> 5169.4271 | Q331: =Q13 -> 4363.1141 | R331: =R13 -> 4626.1318 | S331: =Z29 -> 111779.17
N332: =N13 -> -44829.72 | O332: =O13 -> 4833.2042 | P332: =P13 -> 5169.4271 | Q332: =Q13 -> 4363.1141 | R332: =R13 -> 4626.1318 | S332: =AA29 -> 96284.097
N333: =N13 -> -44829.72 | O333: =O13 -> 4833.2042 | P333: =P13 -> 5169.4271 | Q333: =Q13 -> 4363.1141 | R333: =R13 -> 4626.1318 | S333: =AB29 -> 83002.603
N334: =N13 -> -44829.72 | O334: =O13 -> 4833.2042 | P334: =P13 -> 5169.4271 | Q334: =Q13 -> 4363.1141 | R334: =R13 -> 4626.1318 | S334: =AC29 -> 71491.975
N335: =N13 -> -44829.72 | O335: =O13 -> 4833.2042 | P335: =P13 -> 5169.4271 | Q335: =Q13 -> 4363.1141 | R335: =R13 -> 4626.1318 | S335: =AD29 -> 61420.176
N336: =N14 -> -39848.64 | O336: =O14 -> 5541.4515 | P336: =P14 -> 5877.6744 | Q336: =Q14 -> 5189.5642 | R336: =R14 -> 5452.5819 | S336: =V30 -> 223829.35
N337: =N14 -> -39848.64 | O337: =O14 -> 5541.4515 | P337: =P14 -> 5877.6744 | Q337: =Q14 -> 5189.5642 | R337: =R14 -> 5452.5819 | S337: =W30 -> 190256.68
N338: =N14 -> -39848.64 | O338: =O14 -> 5541.4515 | P338: =P14 -> 5877.6744 | Q338: =Q14 -> 5189.5642 | R338: =R14 -> 5452.5819 | S338: =X30 -> 163398.55
N339: =N14 -> -39848.64 | O339: =O14 -> 5541.4515 | P339: =P14 -> 5877.6744 | Q339: =Q14 -> 5189.5642 | R339: =R14 -> 5452.5819 | S339: =Y30 -> 141423.72
N340: =N14 -> -39848.64 | O340: =O14 -> 5541.4515 | P340: =P14 -> 5877.6744 | Q340: =Q14 -> 5189.5642 | R340: =R14 -> 5452.5819 | S340: =Z30 -> 123111.35
N341: =N14 -> -39848.64 | O341: =O14 -> 5541.4515 | P341: =P14 -> 5877.6744 | Q341: =Q14 -> 5189.5642 | R341: =R14 -> 5452.5819 | S341: =AA30 -> 107616.28
N342: =N14 -> -39848.64 | O342: =O14 -> 5541.4515 | P342: =P14 -> 5877.6744 | Q342: =Q14 -> 5189.5642 | R342: =R14 -> 5452.5819 | S342: =AB30 -> 94334.784
N343: =N14 -> -39848.64 | O343: =O14 -> 5541.4515 | P343: =P14 -> 5877.6744 | Q343: =Q14 -> 5189.5642 | R343: =R14 -> 5452.5819 | S343: =AC30 -> 82824.157
N344: =N14 -> -39848.64 | O344: =O14 -> 5541.4515 | P344: =P14 -> 5877.6744 | Q344: =Q14 -> 5189.5642 | R344: =R14 -> 5452.5819 | S344: =AD30 -> 72752.357
N345: =N15 -> -35863.776 | O345: =O15 -> 6108.0494 | P345: =P15 -> 6444.2723 | Q345: =Q15 -> 5850.7243 | R345: =R15 -> 6113.742 | S345: =V31 -> 232895.09
N346: =N15 -> -35863.776 | O346: =O15 -> 6108.0494 | P346: =P15 -> 6444.2723 | Q346: =Q15 -> 5850.7243 | R346: =R15 -> 6113.742 | S346: =W31 -> 199322.43
N347: =N15 -> -35863.776 | O347: =O15 -> 6108.0494 | P347: =P15 -> 6444.2723 | Q347: =Q15 -> 5850.7243 | R347: =R15 -> 6113.742 | S347: =X31 -> 172464.3
N348: =N15 -> -35863.776 | O348: =O15 -> 6108.0494 | P348: =P15 -> 6444.2723 | Q348: =Q15 -> 5850.7243 | R348: =R15 -> 6113.742 | S348: =Y31 -> 150489.46
N349: =N15 -> -35863.776 | O349: =O15 -> 6108.0494 | P349: =P15 -> 6444.2723 | Q349: =Q15 -> 5850.7243 | R349: =R15 -> 6113.742 | S349: =Z31 -> 132177.1
N350: =N15 -> -35863.776 | O350: =O15 -> 6108.0494 | P350: =P15 -> 6444.2723 | Q350: =Q15 -> 5850.7243 | R350: =R15 -> 6113.742 | S350: =AA31 -> 116682.02
N351: =N15 -> -35863.776 | O351: =O15 -> 6108.0494 | P351: =P15 -> 6444.2723 | Q351: =Q15 -> 5850.7243 | R351: =R15 -> 6113.742 | S351: =AB31 -> 103400.53
...

Sheet Cash Flow
B2: ANNUAL PRO FORMA CASH FLOW (Year 0–10)
C4: Assumptions | D4: Year 0 | E4: Year 1 | F4: Year 2 | G4: Year 3 | H4: Year 4 | I4: Year 5 | J4: Year 6 | K4: Year 7 | L4: Year 8 | M4: Year 9 | N4: Year 10
B5: REVENUE
B6: Gross Potential Rent | C6: =Assumptions!C24 -> 0 | D6: =$C$6 -> 0 | E6: =D6*(1+E7) -> 0 | F6: =E6*(1+F7) -> 0 | G6: =F6*(1+G7) -> 0 | H6: =G6*(1+H7) -> 0 | I6: =H6*(1+I7) -> 0 | J6: =I6*(1+J7) -> 0 | K6: =J6*(1+K7) -> 0 | L6: =K6*(1+L7) -> 0 | ... N6: =M6*(1+N7) -> 0
B7: Rent Growth Rate | E7: =Assumptions!C72 -> 0.03 | F7: =Assumptions!C73 -> 0.03 | G7: =Assumptions!C74 -> 0.025 | H7: =Assumptions!C75 -> 0.025 | I7: =Assumptions!C76 -> 0.025 | J7: =Assumptions!C77 -> 0.02 | K7: =Assumptions!C78 -> 0.02 | L7: =Assumptions!C79 -> 0.02 | M7: =Assumptions!C80 -> 0.02 | N7: =Assumptions!C81 -> 0.02
B8: Other Income | C8: =Assumptions!C23*Assumptions!C40*12 -> 18000 | D8: =$C$8 -> 18000 | E8: =D8*(1+E7) -> 18540 | F8: =E8*(1+F7) -> 19096.2 | G8: =F8*(1+G7) -> 19573.605 | H8: =G8*(1+H7) -> 20062.945 | I8: =H8*(1+I7) -> 20564.519 | J8: =I8*(1+J7) -> 20975.809 | K8: =J8*(1+K7) -> 21395.325 | L8: =K8*(1+L7) -> 21823.232 | ... N8: =M8*(1+N7) -> 22704.89
B9: Effective Gross Income (EGI) | D9: =D6+D8 -> 18000 | E9: =E6+E8 -> 18540 | F9: =F6+F8 -> 19096.2 | G9: =G6+G8 -> 19573.605 | H9: =H6+H8 -> 20062.945 | I9: =I6+I8 -> 20564.519 | J9: =J6+J8 -> 20975.809 | K9: =K6+K8 -> 21395.325 | ... N9: =N6+N8 -> 22704.89
B10: Less: Vacancy & Credit Loss | C10: =Assumptions!C39 -> 0.07 | D10: =-D9*$C$10 -> -1260 | E10: =-E9*$C$10 -> -1297.8 | F10: =-F9*$C$10 -> -1336.734 | G10: =-G9*$C$10 -> -1370.1524 | H10: =-H9*$C$10 -> -1404.4062 | I10: =-I9*$C$10 -> -1439.5163 | J10: =-J9*$C$10 -> -1468.3066 | K10: =-K9*$C$10 -> -1497.6728 | ... N10: =-N9*$C$10 -> -1589.3423
B11: Net Effective Income | D11: =D9+D10 -> 16740 | E11: =E9+E10 -> 17242.2 | F11: =F9+F10 -> 17759.466 | G11: =G9+G10 -> 18203.453 | H11: =H9+H10 -> 18658.539 | I11: =I9+I10 -> 19125.002 | J11: =J9+J10 -> 19507.502 | K11: =K9+K10 -> 19897.653 | ... N11: =N9+N10 -> 21115.548
B13: OPERATING EXPENSES
B14: Operating Expenses | C14: =Assumptions!C43 -> 0.35 | D14: =D11*$C$14 -> 5859 | E14: =D14*(1+Assumptions!C44) -> 6034.77 | F14: =E14*(1+Assumptions!C44) -> 6215.8131 | G14: =F14*(1+Assumptions!C44) -> 6402.2875 | H14: =G14*(1+Assumptions!C44) -> 6594.3561 | I14: =H14*(1+Assumptions!C44) -> 6792.1868 | J14: =I14*(1+Assumptions!C44) -> 6995.9524 | K14: =J14*(1+Assumptions!C44) -> 7205.831 | L14: =K14*(1+Assumptions!C44) -> 7422.0059 | M14: =L14*(1+Assumptions!C44) -> 7644.6661 | N14: =M14*(1+Assumptions!C44) -> 7874.0061
B19: Total Operating Expenses | D19: =D14 -> 5859 | E19: =E14 -> 6034.77 | F19: =F14 -> 6215.8131 | G19: =G14 -> 6402.2875 | H19: =H14 -> 6594.3561 | I19: =I14 -> 6792.1868 | J19: =J14 -> 6995.9524 | K19: =K14 -> 7205.831 | ... N19: =N14 -> 7874.0061
B21: NET OPERATING INCOME (NOI) | D21: =D11-D19 -> 10881 | E21: =E11-E19 -> 11207.43 | F21: =F11-F19 -> 11543.653 | G21: =G11-G19 -> 11801.165 | H21: =H11-H19 -> 12064.183 | I21: =I11-I19 -> 12332.816 | J21: =J11-J19 -> 12511.55 | K21: =K11-K19 -> 12691.822 | ... N21: =N11-N19 -> 13241.542
B23: DEBT SERVICE
B24: Interest Expense | D24: =Assumptions!C53*Assumptions!C54 -> 568750 | E24: =IF(1*12<=Assumptions!C55,Assumptions!C53*Assumptions!C54,IF((1-1)*12>=Assumptions!C55,-CUMIPMT(Assumptions!C54/12,Assumptions!C56*12,Assumptions!C53,(1-1)*12-Assumptions!C55+1,1*12-Assumptions!C55,0),Assumptions!C53*Assumptions!C54*(Assumptions!C55-(1-1)*12)/12+(-CUMIPMT(Assumptions!C54/12,Assumptions!C56*12,Assumptions!C53,1,1*12-Assumptions!C55,0)))) -> 568750 | F24: =IF(2*12<=Assumptions!C55,Assumptions!C53*Assumptions!C54,IF((2-1)*12>=Assumptions!C55,-CUMIPMT(Assumptions!C54/12,Assumptions!C56*12,Assumptions!C53,(2-1)*12-Assumptions!C55+1,2*12-Assumptions!C55,0),Assumptions!C53*Assumptions!C54*(Assumptions!C55-(2-1)*12)/12+(-CUMIPMT(Assumptions!C54/12,Assumptions!C56*12,Assumptions!C53,1,2*12-Assumptions!C55,0)))) -> 568750 | G24: =IF(3*12<=Assumptions!C55,Assumptions!C53*Assumptions!C54,IF((3-1)*12>=Assumptions!C55,-CUMIPMT(Assumptions!C54/12,Assumptions!C56*12,Assumptions!C53,(3-1)*12-Assumptions!C55+1,3*12-Assumptions!C55,0),Assumptions!C53*Assumptions!C54*(Assumptions!C55-(3-1)*12)/12+(-CUMIPMT(Assumptions!C54/12,Assumptions!C56*12,Assumptions!C53,1,3*12-Assumptions!C55,0)))) -> 565870.45 | H24: =IF(4*12<=Assumptions!C55,Assumptions!C53*Assumptions!C54,IF((4-1)*12>=Assumptions!C55,-CUMIPMT(Assumptions!C54/12,Assumptions!C56*12,Assumptions!C53,(4-1)*12-Assumptions!C55+1,4*12-Assumptions!C55,0),Assumptions!C53*Assumptions!C54*(Assumptions!C55-(4-1)*12)/12+(-CUMIPMT(Assumptions!C54/12,Assumptions!C56*12,Assumptions!C53,1,4*12-Assumptions!C55,0)))) -> 559320.53 | I24: =IF(5*12<=Assumptions!C55,Assumptions!C53*Assumptions!C54,IF((5-1)*12>=Assumptions!C55,-CUMIPMT(Assumptions!C54/12,Assumptions!C56*12,Assumptions!C53,(5-1)*12-Assumptions!C55+1,5*12-Assumptions!C55,0),Assumptions!C53*Assumptions!C54*(Assumptions!C55-(5-1)*12)/12+(-CUMIPMT(Assumptions!C54/12,Assumptions!C56*12,Assumptions!C53,1,5*12-Assumptions!C55,0)))) -> 552331.96 | J24: =IF(6*12<=Assumptions!C55,Assumptions!C53*Assumptions!C54,IF((6-1)*12>=Assumptions!C55,-CUMIPMT(Assumptions!C54/12,Assumptions!C56*12,Assumptions!C53,(6-1)*12-Assumptions!C55+1,6*12-Assumptions!C55,0),Assumptions!C53*Assumptions!C54*(Assumptions!C55-(6-1)*12)/12+(-CUMIPMT(Assumptions!C54/12,Assumptions!C56*12,Assumptions!C53,1,6*12-Assumptions!C55,0)))) -> 544875.35 | K24: =IF(7*12<=Assumptions!C55,Assumptions!C53*Assumptions!C54,IF((7-1)*12>=Assumptions!C55,-CUMIPMT(Assumptions!C54/12,Assumptions!C56*12,Assumptions!C53,(7-1)*12-Assumptions!C55+1,7*12-Assumptions!C55,0),Assumptions!C53*Assumptions!C54*(Assumptions!C55-(7-1)*12)/12+(-CUMIPMT(Assumptions!C54/12,Assumptions!C56*12,Assumptions!C53,1,7*12-Assumptions!C55,0)))) -> 536919.36 | L24: =IF(8*12<=Assumptions!C55,Assumptions!C53*Assumptions!C54,IF((8-1)*12>=Assumptions!C55,-CUMIPMT(Assumptions!C54/12,Assumptions!C56*12,Assumptions!C53,(8-1)*12-Assumptions!C55+1,8*12-Assumptions!C55,0),Assumptions!C53*Assumptions!C54*(Assumptions!C55-(8-1)*12)/12+(-CUMIPMT(Assumptions!C54/12,Assumptions!C56*12,Assumptions!C53,1,8*12-Assumptions!C55,0)))) -> 528430.54 | M24: =IF(9*12<=Assumptions!C55,Assumptions!C53*Assumptions!C54,IF((9-1)*12>=Assumptions!C55,-CUMIPMT(Assumptions!C54/12,Assumptions!C56*12,Assumptions!C53,(9-1)*12-Assumptions!C55+1,9*12-Assumptions!C55,0),Assumptions!C53*Assumptions!C54*(Assumptions!C55-(9-1)*12)/12+(-CUMIPMT(Assumptions!C54/12,Assumptions!C56*12,Assumptions!C53,1,9*12-Assumptions!C55,0)))) -> 519373.2 | N24: =IF(10*12<=Assumptions!C55,Assumptions!C53*Assumptions!C54,IF((10-1)*12>=Assumptions!C55,-CUMIPMT(Assumptions!C54/12,Assumptions!C56*12,Assumptions!C53,(10-1)*12-Assumptions!C55+1,10*12-Assumptions!C55,0),Assumptions!C53*Assumptions!C54*(Assumptions!C55-(10-1)*12)/12+(-CUMIPMT(Assumptions!C54/12,Assumptions!C56*12,Assumptions!C53,1,10*12-Assumptions!C55,0)))) -> 509709.29
B25: Principal Payment | D25: =0 -> 0 | E25: =IF(1*12<=Assumptions!C55,0,IF((1-1)*12>=Assumptions!C55,-CUMPRINC(Assumptions!C54/12,Assumptions!C56*12,Assumptions!C53,(1-1)*12-Assumptions!C55+1,1*12-Assumptions!C55,0),-CUMPRINC(Assumptions!C54/12,Assumptions!C56*12,Assumptions!C53,1,1*12-Assumptions!C55,0))) -> 0 | F25: =IF(2*12<=Assumptions!C55,0,IF((2-1)*12>=Assumptions!C55,-CUMPRINC(Assumptions!C54/12,Assumptions!C56*12,Assumptions!C53,(2-1)*12-Assumptions!C55+1,2*12-Assumptions!C55,0),-CUMPRINC(Assumptions!C54/12,Assumptions!C56*12,Assumptions!C53,1,2*12-Assumptions!C55,0))) -> 0 | G25: =IF(3*12<=Assumptions!C55,0,IF((3-1)*12>=Assumptions!C55,-CUMPRINC(Assumptions!C54/12,Assumptions!C56*12,Assumptions!C53,(3-1)*12-Assumptions!C55+1,3*12-Assumptions!C55,0),-CUMPRINC(Assumptions!C54/12,Assumptions!C56*12,Assumptions!C53,1,3*12-Assumptions!C55,0))) -> 97800.979 | H25: =IF(4*12<=Assumptions!C55,0,IF((4-1)*12>=Assumptions!C55,-CUMPRINC(Assumptions!C54/12,Assumptions!C56*12,Assumptions!C53,(4-1)*12-Assumptions!C55+1,4*12-Assumptions!C55,0),-CUMPRINC(Assumptions!C54/12,Assumptions!C56*12,Assumptions!C53,1,4*12-Assumptions!C55,0))) -> 104350.89 | I25: =IF(5*12<=Assumptions!C55,0,IF((5-1)*12>=Assumptions!C55,-CUMPRINC(Assumptions!C54/12,Assumptions!C56*12,Assumptions!C53,(5-1)*12-Assumptions!C55+1,5*12-Assumptions!C55,0),-CUMPRINC(Assumptions!C54/12,Assumptions!C56*12,Assumptions!C53,1,5*12-Assumptions!C55,0))) -> 111339.46 | J25: =IF(6*12<=Assumptions!C55,0,IF((6-1)*12>=Assumptions!C55,-CUMPRINC(Assumptions!C54/12,Assumptions!C56*12,Assumptions!C53,(6-1)*12-Assumptions!C55+1,6*12-Assumptions!C55,0),-CUMPRINC(Assumptions!C54/12,Assumptions!C56*12,Assumptions!C53,1,6*12-Assumptions!C55,0))) -> 118796.07 | K25: =IF(7*12<=Assumptions!C55,0,IF((7-1)*12>=Assumptions!C55,-CUMPRINC(Assumptions!C54/12,Assumptions!C56*12,Assumptions!C53,(7-1)*12-Assumptions!C55+1,7*12-Assumptions!C55,0),-CUMPRINC(Assumptions!C54/12,Assumptions!C56*12,Assumptions!C53,1,7*12-Assumptions!C55,0))) -> 126752.07 | L25: =IF(8*12<=Assumptions!C55,0,IF((8-1)*12>=Assumptions!C55,-CUMPRINC(Assumptions!C54/12,Assumptions!C56*12,Assumptions!C53,(8-1)*12-Assumptions!C55+1,8*12-Assumptions!C55,0),-CUMPRINC(Assumptions!C54/12,Assumptions!C56*12,Assumptions!C53,1,8*12-Assumptions!C55,0))) -> 135240.89 | M25: =IF(9*12<=Assumptions!C55,0,IF((9-1)*12>=Assumptions!C55,-CUMPRINC(Assumptions!C54/12,Assumptions!C56*12,Assumptions!C53,(9-1)*12-Assumptions!C55+1,9*12-Assumptions!C55,0),-CUMPRINC(Assumptions!C54/12,Assumptions!C56*12,Assumptions!C53,1,9*12-Assumptions!C55,0))) -> 144298.22 | N25: =IF(10*12<=Assumptions!C55,0,IF((10-1)*12>=Assumptions!C55,-CUMPRINC(Assumptions!C54/12,Assumptions!C56*12,Assumptions!C53,(10-1)*12-Assumptions!C55+1,10*12-Assumptions!C55,0),-CUMPRINC(Assumptions!C54/12,Assumptions!C56*12,Assumptions!C53,1,10*12-Assumptions!C55,0))) -> 153962.14
B26: Total Debt Service | D26: =D24+D25 -> 568750 | E26: =E24+E25 -> 568750 | F26: =F24+F25 -> 568750 | G26: =G24+G25 -> 663671.42 | H26: =H24+H25 -> 663671.42 | I26: =I24+I25 -> 663671.42 | J26: =J24+J25 -> 663671.42 | K26: =K24+K25 -> 663671.42 | ... N26: =N24+N25 -> 663671.42
B28: CASH FLOW BEFORE TAX | D28: =D21-D26 -> -557869 | E28: =E21-E26 -> -557542.57 | F28: =F21-F26 -> -557206.35 | G28: =G21-G26 -> -651870.26 | H28: =H21-H26 -> -651607.24 | I28: =I21-I26 -> -651338.61 | J28: =J21-J26 -> -651159.87 | K28: =K21-K26 -> -650979.6 | ... N28: =N21-N26 -> -650429.88
B29: Cumulative Cash Flow | D29: =D28 -> -557869 | E29: =D29+E28 -> -1115411.6 | F29: =E29+F28 -> -1672617.9 | G29: =F29+G28 -> -2324488.2 | H29: =G29+H28 -> -2976095.4 | I29: =H29+I28 -> -3627434 | J29: =I29+J28 -> -4278593.9 | K29: =J29+K28 -> -4929573.5 | L29: =K29+L28 -> -5580371.3 | ... N29: =M29+N28 -> -6881415.8
B31: KEY METRICS
B32: DSCR | D32: =D21/D26 -> 0.019131429 | E32: =E21/E26 -> 0.019705371 | F32: =F21/F26 -> 0.020296533 | G32: =G21/G26 -> 0.017781638 | H32: =H21/H26 -> 0.018177945 | I32: =I21/I26 -> 0.018582713 | J32: =J21/J26 -> 0.018852025 | K32: =K21/K26 -> 0.019123652 | ... N32: =N21/N26 -> 0.019951954
B33: Cash-on-Cash Return | D33: =D28/Assumptions!C84 -> -0.13648171 | E33: =E28/Assumptions!C84 -> -0.13640185 | F33: =F28/Assumptions!C84 -> -0.1363196 | G33: =G28/Assumptions!C84 -> -0.15947896 | H33: =H28/Assumptions!C84 -> -0.15941462 | I33: =I28/Assumptions!C84 -> -0.1593489 | J33: =J28/Assumptions!C84 -> -0.15930517 | K33: =K28/Assumptions!C84 -> -0.15926106 | L33: =L28/Assumptions!C84 -> -0.15921659 | M33: =M28/Assumptions!C84 -> -0.15917176 | N33: =N28/Assumptions!C84 -> -0.15912658
B34: Cap Rate (on Purchase) | D34: =D21/Assumptions!C7 -> 0.00087048 | E34: =E21/Assumptions!C7 -> 0.0008965944 | F34: =F21/Assumptions!C7 -> 0.00092349223 | G34: =G21/Assumptions!C7 -> 0.00094409321 | H34: =H21/Assumptions!C7 -> 0.00096513463 | I34: =I21/Assumptions!C7 -> 0.00098662525 | J34: =J21/Assumptions!C7 -> 0.001000924 | K34: =K21/Assumptions!C7 -> 0.0010153457 | L34: =L21/Assumptions!C7 -> 0.001029888 | M34: =M21/Assumptions!C7 -> 0.0010445481 | N34: =N21/Assumptions!C7 -> 0.0010593234
B35: OpEx Ratio | D35: =D19/D11 -> 0.35 | E35: =E19/E11 -> 0.35 | F35: =F19/F11 -> 0.35 | G35: =G19/G11 -> 0.35170732 | H35: =H19/H11 -> 0.35342296 | I35: =I19/I11 -> 0.35514698 | J35: =J19/J11 -> 0.35862881 | K35: =K19/K11 -> 0.36214478 | ... N35: =N19/N11 -> 0.37290086
B36: All inputs sourced from Assumptions tab — edit blue cells there to update the model.

Sheet Returns
B2: EXIT & RETURNS ANALYSIS
B3: All inputs auto-populated from Assumptions tab | Edit blue cells on Assumptions to update this model
B5: KEY INPUTS
B6: Hold Period (Years) | C6: =Assumptions!C62 -> 5
B7: Exit Cap Rate | C7: =Assumptions!C63 -> 0.06
B8: Selling Costs | C8: =Assumptions!C64 -> 0.02
B9: Total Equity Invested | C9: =Assumptions!C84 -> 4087500
B10: Loan Amount | C10: =Assumptions!C53 -> 8750000
B11: GP Co-Invest | C11: =Assumptions!C67 -> 0.1
B12: LP Preferred Return | C12: =Assumptions!C68 -> 0.08
B13: GP Promote Above Pref | C13: =Assumptions!C69 -> 0.2
B14: Acquisition Price | C14: =Assumptions!C7 -> 12500000
B15: Interest Rate | C15: =Assumptions!C54 -> 0.065
B16: IO Period (Months) | C16: =Assumptions!C55 -> 24
B18: EXIT ANALYSIS
B19: Exit Year NOI | C19: {=INDEX('Cash Flow'!D21:N21,1,C6+2)} -> 12511.55
B20: Gross Sale Price | C20: =C19/C7 -> 208525.83
B21: Less: Selling Costs | C21: =-C20*C8 -> -4170.5167
B22: Net Sale Proceeds | C22: =C20+C21 -> 204355.32
B23: Less: Loan Payoff | C23: =-IF(C6*12<=C16,C10,C10-CUMPRINC(C15/12,360,C10,1,MIN(C6*12-C16,360),0)) -> -9063491.3
B24: Net Equity Proceeds | C24: =C22+C23 -> -8859136
B25: Return of Capital | C25: =C9 -> 4087500
B26: Total Profit on Sale | C26: =C24-C9 -> -12946636
B28: LEVERED IRR CALCULATION
B29: Year | C29: 0 | D29: 1 | E29: 2 | F29: 3 | G29: 4 | H29: 5 | I29: 6 | J29: 7 | K29: 8 | L29: 9 | M29: 10
B30: Levered Cash Flow | C30: =-C9 -> -4087500 | D30: =IF(D29<=$C$6,'Cash Flow'!E28+IF(D29=$C$6,$C$24,0),0) -> -557542.57 | E30: =IF(E29<=$C$6,'Cash Flow'!F28+IF(E29=$C$6,$C$24,0),0) -> -557206.35 | F30: =IF(F29<=$C$6,'Cash Flow'!G28+IF(F29=$C$6,$C$24,0),0) -> -651870.26 | G30: =IF(G29<=$C$6,'Cash Flow'!H28+IF(G29=$C$6,$C$24,0),0) -> -651607.24 | H30: =IF(H29<=$C$6,'Cash Flow'!I28+IF(H29=$C$6,$C$24,0),0) -> -9510474.6 | I30: =IF(I29<=$C$6,'Cash Flow'!J28+IF(I29=$C$6,$C$24,0),0) -> 0 | J30: =IF(J29<=$C$6,'Cash Flow'!K28+IF(J29=$C$6,$C$24,0),0) -> 0 | K30: =IF(K29<=$C$6,'Cash Flow'!L28+IF(K29=$C$6,$C$24,0),0) -> 0 | ... M30: =IF(M29<=$C$6,'Cash Flow'!N28+IF(M29=$C$6,$C$24,0),0) -> 0
B31: Annual CFBT (from Cash Flow) | C31: ='Cash Flow'!D28 -> -557869 | D31: ='Cash Flow'!E28 -> -557542.57 | E31: ='Cash Flow'!F28 -> -557206.35 | F31: ='Cash Flow'!G28 -> -651870.26 | G31: ='Cash Flow'!H28 -> -651607.24 | H31: ='Cash Flow'!I28 -> -651338.61 | I31: ='Cash Flow'!J28 -> -651159.87 | J31: ='Cash Flow'!K28 -> -650979.6 | ... M31: ='Cash Flow'!N28 -> -650429.88
B33: Levered IRR | C33: =IRR(C30:M30) -> #NUM!
B34: Equity Multiple (x) | C34: =SUM(D30:M30)/-C30 -> -2.9183366
B35: Avg Cash-on-Cash Yield | C35: =AVERAGE(D31:INDEX(D31:M31,1,C6))/C9 -> -0.15019278
B36: Total Profit | C36: =C26 -> -12946636
B37: MOIC RECONCILIATION BRIDGE
B38: Equity Invested (Year 0) | C38: =-C30 -> 4087500
B39: + Operating Cash Flows (Yrs 1–4) | C39: =SUM(D30:G30) -> -2418226.4
B40: + Exit Year CFBT (Yr 5) | C40: ='Cash Flow'!I28 -> -651338.61
B41: + Net Equity Proceeds (Exit) | C41: =C24 -> -8859136
B42: Total Equity Distributions | C42: =SUM(D30:M30) -> -11928701
B43: Equity Multiple (MOIC) | C43: =C34 -> -2.9183366
B44: of which: Operating Cash Flow Contribution | C44: =SUM(D30:INDEX(D30:M30,1,C6-1))/(-C30) -> -0.59161503
B45: of which: Exit Proceeds Contribution | C45: {=INDEX(D30:M30,1,C6)/(-C30)} -> -2.3267216
B48: UNLEVERED IRR CALCULATION
B49: Year | C49: 0 | D49: 1 | E49: 2 | F49: 3 | G49: 4 | H49: 5 | I49: 6 | J49: 7 | K49: 8 | L49: 9 | M49: 10
B50: Unlevered Cash Flow | C50: =-(Assumptions!C10+Assumptions!C36) -> -12750000 | D50: =IF(D49<=$C$6,'Cash Flow'!E21+IF(D49=$C$6,$C$22,0),0) -> 11207.43 | E50: =IF(E49<=$C$6,'Cash Flow'!F21+IF(E49=$C$6,$C$22,0),0) -> 11543.653 | F50: =IF(F49<=$C$6,'Cash Flow'!G21+IF(F49=$C$6,$C$22,0),0) -> 11801.165 | G50: =IF(G49<=$C$6,'Cash Flow'!H21+IF(G49=$C$6,$C$22,0),0) -> 12064.183 | H50: =IF(H49<=$C$6,'Cash Flow'!I21+IF(H49=$C$6,$C$22,0),0) -> 216688.13 | I50: =IF(I49<=$C$6,'Cash Flow'!J21+IF(I49=$C$6,$C$22,0),0) -> 0 | J50: =IF(J49<=$C$6,'Cash Flow'!K21+IF(J49=$C$6,$C$22,0),0) -> 0 | K50: =IF(K49<=$C$6,'Cash Flow'!L21+IF(K49=$C$6,$C$22,0),0) -> 0 | ... M50: =IF(M49<=$C$6,'Cash Flow'!N21+IF(M49=$C$6,$C$22,0),0) -> 0
B51: Annual NOI (from Cash Flow) | C51: ='Cash Flow'!D21 -> 10881 | D51: ='Cash Flow'!E21 -> 11207.43 | E51: ='Cash Flow'!F21 -> 11543.653 | F51: ='Cash Flow'!G21 -> 11801.165 | G51: ='Cash Flow'!H21 -> 12064.183 | H51: ='Cash Flow'!I21 -> 12332.816 | I51: ='Cash Flow'!J21 -> 12511.55 | J51: ='Cash Flow'!K21 -> 12691.822 | ... M51: ='Cash Flow'!N21 -> 13241.542
B53: Unlevered IRR | C53: =IRR(C50:M50) -> -0.55364591
B54: Unlevered Equity Multiple (x) | C54: =SUM(D50:M50)/-C50 -> 0.020651338
B56: CASH-ON-CASH RETURN & EQUITY MULTIPLE DECOMPOSITION
B57: Year | C57: 0 | D57: 1 | E57: 2 | F57: 3 | G57: 4 | H57: 5 | I57: 6 | J57: 7 | K57: 8 | L57: 9 | M57: 10 | N57: Avg / Total
B58: CFBT ($) | C58: =C31 -> -557869 | D58: =D31 -> -557542.57 | E58: =E31 -> -557206.35 | F58: =F31 -> -651870.26 | G58: =G31 -> -651607.24 | H58: =H31 -> -651338.61 | I58: =I31 -> -651159.87 | J58: =J31 -> -650979.6 | ... M58: =M31 -> -650429.88 | N58: =AVERAGE(D58:M58) -> -632354.68
B59: Cash-on-Cash Yield (%) | C59: n/a | D59: =D58/$C$9 -> -0.13640185 | E59: =E58/$C$9 -> -0.1363196 | F59: =F58/$C$9 -> -0.15947896 | G59: =G58/$C$9 -> -0.15941462 | H59: =H58/$C$9 -> -0.1593489 | I59: =I58/$C$9 -> -0.15930517 | J59: =J58/$C$9 -> -0.15926106 | K59: =K58/$C$9 -> -0.15921659 | ... M59: =M58/$C$9 -> -0.15912658 | N59: =AVERAGE(D59:INDEX(D59:M59,1,C6)) -> -0.15019278
B60: NOI ($) | C60: =C51 -> 10881 | D60: =D51 -> 11207.43 | E60: =E51 -> 11543.653 | F60: =F51 -> 11801.165 | G60: =G51 -> 12064.183 | H60: =H51 -> 12332.816 | I60: =I51 -> 12511.55 | J60: =J51 -> 12691.822 | ... M60: =M51 -> 13241.542 | N60: =AVERAGE(D60:M60) -> 12332.461
B61: NOI Yield on Cost (%) | C61: n/a | D61: =D60/C14 -> 0.0008965944 | E61: =E60/C14 -> 0.00092349223 | F61: =F60/C14 -> 0.00094409321 | G61: =G60/C14 -> 0.00096513463 | H61: =H60/C14 -> 0.00098662525 | I61: =I60/C14 -> 0.001000924 | J61: =J60/C14 -> 0.0010153457 | K61: =K60/C14 -> 0.001029888 | L61: =L60/C14 -> 0.0010445481 | M61: =M60/C14 -> 0.0010593234 | N61: =AVERAGE(D61:M61) -> 0.00098659689
B62: DSCR | C62: n/a | D62: ='Cash Flow'!E32 -> 0.019705371 | E62: ='Cash Flow'!F32 -> 0.020296533 | F62: ='Cash Flow'!G32 -> 0.017781638 | G62: ='Cash Flow'!H32 -> 0.018177945 | H62: ='Cash Flow'!I32 -> 0.018582713 | I62: ='Cash Flow'!J32 -> 0.018852025 | J62: ='Cash Flow'!K32 -> 0.019123652 | K62: ='Cash Flow'!L32 -> 0.01939755 | ... M62: ='Cash Flow'!N32 -> 0.019951954 | N62: =AVERAGE(D62:M62) -> 0.019154305
B63: Cumulative Equity Multiple | C63: — | D63: =SUM($D30:D30)/$C$9 -> -0.13640185 | E63: =SUM($D30:E30)/$C$9 -> -0.27272145 | F63: =SUM($D30:F30)/$C$9 -> -0.43220041 | G63: =SUM($D30:G30)/$C$9 -> -0.59161503 | H63: =SUM($D30:H30)/$C$9 -> -2.9183366 | N63: =C34 -> -2.9183366
B64: % of Return from Exit Proceeds | H64: =C45/C43 -> 0.79727663
B66: Total Distributions (CF + Exit) | C66: =SUM(D30:M30) -> -11928701
B67: Return of Capital | C67: =-C30 -> 4087500
B68: Total Profit | C68: =C66-C67 -> -16016201
B69: LP Pref Return (cumulative, simple) | C69: =C67*C12*C6 -> 1635000 | D69: ← Simple pref on total equity (see note)
B70: Profit Above Pref | C70: =C68-C69 -> -17651201
B71: GP Promote (20% of profit above pref) | C71: =C70*C13 -> -3530240.2 | D71: ← No catch-up tier (see note)
B72: GP Total (Co-Invest ROC + Promote) | C72: =C67*C11+C71 -> -3121490.2 | D72: ← Excl. GP pro-rata operating CFs (see note)
B73: LP Total (Distributions - GP) | C73: =C66-C72 -> -8807210.8
B74: LP MOIC (LP Total / LP Equity) | C74: =C73/(C67*(1-C11)) -> -2.394077
B75: SENSITIVITY: LEVERED IRR — Exit Cap Rate × Rent Growth
B76: Exit Cap \ Rent Growth | C76: 0.01 | D76: 0.015 | E76: 0.02 | F76: 0.025 | G76: 0.03 | H76: 0.035 | I76: 0.04
B77: 0.04 | C77: =IFERROR(IRR(Q91:V91),0) -> 0 | D77: =IFERROR(IRR(Q92:V92),0) -> 0 | E77: =IFERROR(IRR(Q93:V93),0) -> 0 | F77: =IFERROR(IRR(Q94:V94),0) -> 0 | G77: =IFERROR(IRR(Q95:V95),0) -> 0 | H77: =IFERROR(IRR(Q96:V96),0) -> 0 | I77: =IFERROR(IRR(Q97:V97),0) -> 0
B78: 0.045 | C78: =IFERROR(IRR(Q98:V98),0) -> 0 | D78: =IFERROR(IRR(Q99:V99),0) -> 0 | E78: =IFERROR(IRR(Q100:V100),0) -> 0 | F78: =IFERROR(IRR(Q101:V101),0) -> 0 | G78: =IFERROR(IRR(Q102:V102),0) -> 0 | H78: =IFERROR(IRR(Q103:V103),0) -> 0 | I78: =IFERROR(IRR(Q104:V104),0) -> 0
B79: 0.05 | C79: =IFERROR(IRR(Q105:V105),0) -> 0 | D79: =IFERROR(IRR(Q106:V106),0) -> 0 | E79: =IFERROR(IRR(Q107:V107),0) -> 0 | F79: =IFERROR(IRR(Q108:V108),0) -> 0 | G79: =IFERROR(IRR(Q109:V109),0) -> 0 | H79: =IFERROR(IRR(Q110:V110),0) -> 0 | I79: =IFERROR(IRR(Q111:V111),0) -> 0
B80: 0.055 | C80: =IFERROR(IRR(Q112:V112),0) -> 0 | D80: =IFERROR(IRR(Q113:V113),0) -> 0 | E80: =IFERROR(IRR(Q114:V114),0) -> 0 | F80: =IFERROR(IRR(Q115:V115),0) -> 0 | G80: =IFERROR(IRR(Q116:V116),0) -> 0 | H80: =IFERROR(IRR(Q117:V117),0) -> 0 | I80: =IFERROR(IRR(Q118:V118),0) -> 0
B81: 0.06 | C81: =IFERROR(IRR(Q119:V119),0) -> 0 | D81: =IFERROR(IRR(Q120:V120),0) -> 0 | E81: =IFERROR(IRR(Q121:V121),0) -> 0 | F81: =IFERROR(IRR(Q122:V122),0) -> 0 | G81: =IFERROR(IRR(Q123:V123),0) -> 0 | H81: =IFERROR(IRR(Q124:V124),0) -> 0 | I81: =IFERROR(IRR(Q125:V125),0) -> 0
B82: 0.065 | C82: =IFERROR(IRR(Q126:V126),0) -> 0 | D82: =IFERROR(IRR(Q127:V127),0) -> 0 | E82: =IFERROR(IRR(Q128:V128),0) -> 0 | F82: =IFERROR(IRR(Q129:V129),0) -> 0 | G82: =IFERROR(IRR(Q130:V130),0) -> 0 | H82: =IFERROR(IRR(Q131:V131),0) -> 0 | I82: =IFERROR(IRR(Q132:V132),0) -> 0
B83: 0.07 | C83: =IFERROR(IRR(Q133:V133),0) -> 0 | D83: =IFERROR(IRR(Q134:V134),0) -> 0 | E83: =IFERROR(IRR(Q135:V135),0) -> 0 | F83: =IFERROR(IRR(Q136:V136),0) -> 0 | G83: =IFERROR(IRR(Q137:V137),0) -> 0 | H83: =IFERROR(IRR(Q138:V138),0) -> 0 | I83: =IFERROR(IRR(Q139:V139),0) -> 0
B84: ★ Yellow = base case | Rows = Exit Cap Rate (base: 6.0%) | Columns = Rent Growth Yr1 (base: 3.0%)
B86: [helper] CFBT Yr1-5 | D86: ='Cash Flow'!E28 -> -557542.57 | E86: ='Cash Flow'!F28 -> -557206.35 | F86: ='Cash Flow'!G28 -> -651870.26 | G86: ='Cash Flow'!H28 -> -651607.24 | H86: ='Cash Flow'!I28 -> -651338.61
B87: [helper] Exit NOI Yr5 | D87: ='Cash Flow'!I21 -> 12332.816
B88: SENSITIVITY: LEVERED IRR — Hold Period (Years) × Exit Cap Rate
B89: Exit Cap \ Hold Yr | C89: 3 | D89: 4 | E89: 5 | F89: 6 | G89: 7 | H89: 8 | I89: 10
B90: 0.04 | C90: {=IFERROR(IRR((-C9,IF(D29<=3,'Cash Flow'!E28+IF(D29=3,B18_yr3/0.04-B19_yr3*C8+B22_yr3,0),0),IF(E29<=3,'Cash Flow'!F28+IF(E29=3,B18_yr3/0.04-B19_yr3*C8+B22_yr3,0),0))),"—")} -> — | D90: — | E90: — | F90: — | G90: — | H90: — | I90: —
Q91: =-$C$9 -> -4087500 | R91: =D86*0.98058 -> -546715.09 | S91: =E86*0.96154 -> -535776.19 | T91: =F86*0.94287 -> -614628.91 | U91: =G86*0.92456 -> -602449.99 | V91: =H86*0.98058+$D$87*0.98058/0.04*(1-$C$8)-$C$10 -> -9092403.5
Q92: =-$C$9 -> -4087500 | R92: =D86*0.98544 -> -549424.75 | S92: =E86*0.97109 -> -541097.51 | T92: =F86*0.95694 -> -623800.73 | U92: =G86*0.94301 -> -614472.15 | V92: =H86*0.98544+$D$87*0.98544/0.04*(1-$C$8)-$C$10 -> -9094100.5
Q93: =-$C$9 -> -4087500 | R93: =D86*0.99029 -> -552128.83 | S93: =E86*0.98068 -> -546441.12 | T93: =F86*0.97116 -> -633070.32 | U93: =G86*0.96173 -> -626670.23 | V93: =H86*0.99029+$D$87*0.99029/0.04*(1-$C$8)-$C$10 -> -9095794
Q94: =-$C$9 -> -4087500 | R94: =D86*0.99515 -> -554838.49 | S94: =E86*0.99031 -> -551807.02 | T94: =F86*0.98551 -> -642424.66 | U94: =G86*0.98072 -> -639044.25 | V94: =H86*0.99515+$D$87*0.99515/0.04*(1-$C$8)-$C$10 -> -9097491.1
Q95: =-$C$9 -> -4087500 | R95: =D86*1 -> -557542.57 | S95: =E86*1 -> -557206.35 | T95: =F86*1 -> -651870.26 | U95: =G86*1 -> -651607.24 | V95: =H86*1+$D$87*1/0.04*(1-$C$8)-$C$10 -> -9099184.6
Q96: =-$C$9 -> -4087500 | R96: =D86*1.00485 -> -560246.65 | S96: =E86*1.00973 -> -562627.96 | T96: =F86*1.01463 -> -661407.12 | U96: =G86*1.01956 -> -664352.68 | V96: =H86*1.00485+$D$87*1.00485/0.04*(1-$C$8)-$C$10 -> -9100878.2
Q97: =-$C$9 -> -4087500 | R97: =D86*1.00971 -> -562956.31 | S97: =E86*1.01951 -> -568077.44 | T97: =F86*1.02941 -> -671041.76 | U97: =G86*1.0394 -> -677280.57 | V97: =H86*1.00971+$D$87*1.00971/0.04*(1-$C$8)-$C$10 -> -9102575.2
B98: ★ Yellow = base case | Rows = Exit Cap Rate (base: 6.0%) | Columns = Hold Period (base: 5 years) | Q98: =-$C$9 -> -4087500 | R98: =D86*0.98058 -> -546715.09 | S98: =E86*0.96154 -> -535776.19 | T98: =F86*0.94287 -> -614628.91 | U98: =G86*0.92456 -> -602449.99 | V98: =H86*0.96154+$D$87*0.96154/0.045*(1-$C$8)-$C$10 -> -9118036.4
B99: NOTE: This table requires Data Tables or manual scenario inputs. Values shown as placeholders — link each cell to IRR calc using hold period and exit cap overrides. | Q99: =-$C$9 -> -4087500 | R99: =D86*0.98544 -> -549424.75 | S99: =E86*0.97109 -> -541097.51 | T99: =F86*0.95694 -> -623800.73 | U99: =G86*0.94301 -> -614472.15 | V99: =H86*0.97109+$D$87*0.97109/0.045*(1-$C$8)-$C$10 -> -9121691.8
Q100: =-$C$9 -> -4087500 | R100: =D86*0.99029 -> -552128.83 | S100: =E86*0.98068 -> -546441.12 | T100: =F86*0.97116 -> -633070.32 | U100: =G86*0.96173 -> -626670.23 | V100: =H86*0.98068+$D$87*0.98068/0.045*(1-$C$8)-$C$10 -> -9125362.4
Q101: =-$C$9 -> -4087500 | R101: =D86*0.99515 -> -554838.49 | S101: =E86*0.99031 -> -551807.02 | T101: =F86*0.98551 -> -642424.66 | U101: =G86*0.98072 -> -639044.25 | V101: =H86*0.99031+$D$87*0.99031/0.045*(1-$C$8)-$C$10 -> -9129048.4
Q102: =-$C$9 -> -4087500 | R102: =D86*1 -> -557542.57 | S102: =E86*1 -> -557206.35 | T102: =F86*1 -> -651870.26 | U102: =G86*1 -> -651607.24 | V102: =H86*1+$D$87*1/0.045*(1-$C$8)-$C$10 -> -9132757.3
B103: SENSITIVITY: LEVERED IRR — LTV (%) × Interest Rate [Leverage Sensitivity] | Q103: =-$C$9 -> -4087500 | R103: =D86*1.00485 -> -560246.65 | S103: =E86*1.00973 -> -562627.96 | T103: =F86*1.01463 -> -661407.12 | U103: =G86*1.01956 -> -664352.68 | V103: =H86*1.00973+$D$87*1.00973/0.045*(1-$C$8)-$C$10 -> -9136481.5
B104: LTV \ Int Rate | C104: 0.04 | D104: 0.045 | E104: 0.05 | F104: 0.055 | G104: 0.06 | H104: 0.065 | I104: 0.07 | Q104: =-$C$9 -> -4087500 | R104: =D86*1.00971 -> -562956.31 | S104: =E86*1.01951 -> -568077.44 | T104: =F86*1.02941 -> -671041.76 | U104: =G86*1.0394 -> -677280.57 | V104: =H86*1.01951+$D$87*1.01951/0.045*(1-$C$8)-$C$10 -> -9140224.9
B105: 0.55 | C105: — | D105: — | E105: — | F105: — | G105: — | H105: — | I105: — | Q105: =-$C$9 -> -4087500 | R105: =D86*0.98058 -> -546715.09 | S105: =E86*0.96154 -> -535776.19 | T105: =F86*0.94287 -> -614628.91 | U105: =G86*0.92456 -> -602449.99 | V105: =H86*0.94287+$D$87*0.94287/0.05*(1-$C$8)-$C$10 -> -9136214.1
B106: 0.6 | C106: — | D106: — | E106: — | F106: — | G106: — | H106: — | I106: — | Q106: =-$C$9 -> -4087500 | R106: =D86*0.98544 -> -549424.75 | S106: =E86*0.97109 -> -541097.51 | T106: =F86*0.95694 -> -623800.73 | U106: =G86*0.94301 -> -614472.15 | V106: =H86*0.95694+$D$87*0.95694/0.05*(1-$C$8)-$C$10 -> -9141977.4
B107: 0.65 | C107: — | D107: — | E107: — | F107: — | G107: — | H107: — | I107: — | Q107: =-$C$9 -> -4087500 | R107: =D86*0.99029 -> -552128.83 | S107: =E86*0.98068 -> -546441.12 | T107: =F86*0.97116 -> -633070.32 | U107: =G86*0.96173 -> -626670.23 | V107: =H86*0.97116+$D$87*0.97116/0.05*(1-$C$8)-$C$10 -> -9147802.1
B108: 0.7 | C108: — | D108: — | E108: — | F108: — | G108: — | H108: — | I108: — | Q108: =-$C$9 -> -4087500 | R108: =D86*0.99515 -> -554838.49 | S108: =E86*0.99031 -> -551807.02 | T108: =F86*0.98551 -> -642424.66 | U108: =G86*0.98072 -> -639044.25 | V108: =H86*0.98551+$D$87*0.98551/0.05*(1-$C$8)-$C$10 -> -9153680.1
B109: 0.75 | C109: — | D109: — | E109: — | F109: — | G109: — | H109: — | I109: — | Q109: =-$C$9 -> -4087500 | R109: =D86*1 -> -557542.57 | S109: =E86*1 -> -557206.35 | T109: =F86*1 -> -651870.26 | U109: =G86*1 -> -651607.24 | V109: =H86*1+$D$87*1/0.05*(1-$C$8)-$C$10 -> -9159615.4
B110: 0.8 | C110: — | D110: — | E110: — | F110: — | G110: — | H110: — | I110: — | Q110: =-$C$9 -> -4087500 | R110: =D86*1.00485 -> -560246.65 | S110: =E86*1.00973 -> -562627.96 | T110: =F86*1.01463 -> -661407.12 | U110: =G86*1.01956 -> -664352.68 | V110: =H86*1.01463+$D$87*1.01463/0.05*(1-$C$8)-$C$10 -> -9165608.1
B111: ★ Yellow = base case | Rows = LTV (base: 70%) | Columns = Interest Rate (base: 6.5%) | Q111: =-$C$9 -> -4087500 | R111: =D86*1.00971 -> -562956.31 | S111: =E86*1.01951 -> -568077.44 | T111: =F86*1.02941 -> -671041.76 | U111: =G86*1.0394 -> -677280.57 | V111: =H86*1.02941+$D$87*1.02941/0.05*(1-$C$8)-$C$10 -> -9171662.2
...

Sheet Debt Schedule
B2: DEBT AMORTIZATION SCHEDULE
B4: KEY INPUTS
B5: Loan Amount ($) | C5: =Assumptions!C53 -> 8750000
B6: Annual Interest Rate | C6: =Assumptions!C54 -> 0.065
B7: IO Period (Months) | C7: =Assumptions!C55 -> 24
B8: Amortization (Years) | C8: =Assumptions!C56 -> 30
B9: Monthly Rate | C9: =C6/12 -> 0.0054166667
B10: Monthly Payment (Amort) | C10: =-PMT(C6/12,C8*12,C5) -> 55305.952
B12: Month | C12: Year | D12: IO/Amort | E12: Beg Balance | F12: Payment | G12: Interest | H12: Principal | I12: End Balance
B13: 1 | C13: =CEILING(B13/12,1) -> 1 | D13: =IF(B13<=$C$7,"IO","Amort") -> IO | E13: =$C$5 -> 8750000 | F13: =IF(D13="IO",E13*$C$9,$C$10) -> 47395.833 | G13: =E13*$C$9 -> 47395.833 | H13: =F13-G13 -> 0 | I13: =E13-H13 -> 8750000
B14: =B13+1 -> 2 | C14: =CEILING(B14/12,1) -> 1 | D14: =IF(B14<=$C$7,"IO","Amort") -> IO | E14: =I13 -> 8750000 | F14: =IF(D14="IO",E14*$C$9,$C$10) -> 47395.833 | G14: =E14*$C$9 -> 47395.833 | H14: =F14-G14 -> 0 | I14: =E14-H14 -> 8750000
B15: =B14+1 -> 3 | C15: =CEILING(B15/12,1) -> 1 | D15: =IF(B15<=$C$7,"IO","Amort") -> IO | E15: =I14 -> 8750000 | F15: =IF(D15="IO",E15*$C$9,$C$10) -> 47395.833 | G15: =E15*$C$9 -> 47395.833 | H15: =F15-G15 -> 0 | I15: =E15-H15 -> 8750000
B16: =B15+1 -> 4 | C16: =CEILING(B16/12,1) -> 1 | D16: =IF(B16<=$C$7,"IO","Amort") -> IO | E16: =I15 -> 8750000 | F16: =IF(D16="IO",E16*$C$9,$C$10) -> 47395.833 | G16: =E16*$C$9 -> 47395.833 | H16: =F16-G16 -> 0 | I16: =E16-H16 -> 8750000
B17: =B16+1 -> 5 | C17: =CEILING(B17/12,1) -> 1 | D17: =IF(B17<=$C$7,"IO","Amort") -> IO | E17: =I16 -> 8750000 | F17: =IF(D17="IO",E17*$C$9,$C$10) -> 47395.833 | G17: =E17*$C$9 -> 47395.833 | H17: =F17-G17 -> 0 | I17: =E17-H17 -> 8750000
B18: =B17+1 -> 6 | C18: =CEILING(B18/12,1) -> 1 | D18: =IF(B18<=$C$7,"IO","Amort") -> IO | E18: =I17 -> 8750000 | F18: =IF(D18="IO",E18*$C$9,$C$10) -> 47395.833 | G18: =E18*$C$9 -> 47395.833 | H18: =F18-G18 -> 0 | I18: =E18-H18 -> 8750000
B19: =B18+1 -> 7 | C19: =CEILING(B19/12,1) -> 1 | D19: =IF(B19<=$C$7,"IO","Amort") -> IO | E19: =I18 -> 8750000 | F19: =IF(D19="IO",E19*$C$9,$C$10) -> 47395.833 | G19: =E19*$C$9 -> 47395.833 | H19: =F19-G19 -> 0 | I19: =E19-H19 -> 8750000
B20: =B19+1 -> 8 | C20: =CEILING(B20/12,1) -> 1 | D20: =IF(B20<=$C$7,"IO","Amort") -> IO | E20: =I19 -> 8750000 | F20: =IF(D20="IO",E20*$C$9,$C$10) -> 47395.833 | G20: =E20*$C$9 -> 47395.833 | H20: =F20-G20 -> 0 | I20: =E20-H20 -> 8750000
B21: =B20+1 -> 9 | C21: =CEILING(B21/12,1) -> 1 | D21: =IF(B21<=$C$7,"IO","Amort") -> IO | E21: =I20 -> 8750000 | F21: =IF(D21="IO",E21*$C$9,$C$10) -> 47395.833 | G21: =E21*$C$9 -> 47395.833 | H21: =F21-G21 -> 0 | I21: =E21-H21 -> 8750000
B22: =B21+1 -> 10 | C22: =CEILING(B22/12,1) -> 1 | D22: =IF(B22<=$C$7,"IO","Amort") -> IO | E22: =I21 -> 8750000 | F22: =IF(D22="IO",E22*$C$9,$C$10) -> 47395.833 | G22: =E22*$C$9 -> 47395.833 | H22: =F22-G22 -> 0 | I22: =E22-H22 -> 8750000
B23: =B22+1 -> 11 | C23: =CEILING(B23/12,1) -> 1 | D23: =IF(B23<=$C$7,"IO","Amort") -> IO | E23: =I22 -> 8750000 | F23: =IF(D23="IO",E23*$C$9,$C$10) -> 47395.833 | G23: =E23*$C$9 -> 47395.833 | H23: =F23-G23 -> 0 | I23: =E23-H23 -> 8750000
B24: =B23+1 -> 12 | C24: =CEILING(B24/12,1) -> 1 | D24: =IF(B24<=$C$7,"IO","Amort") -> IO | E24: =I23 -> 8750000 | F24: =IF(D24="IO",E24*$C$9,$C$10) -> 47395.833 | G24: =E24*$C$9 -> 47395.833 | H24: =F24-G24 -> 0 | I24: =E24-H24 -> 8750000
B25: =B24+1 -> 13 | C25: =CEILING(B25/12,1) -> 2 | D25: =IF(B25<=$C$7,"IO","Amort") -> IO | E25: =I24 -> 8750000 | F25: =IF(D25="IO",E25*$C$9,$C$10) -> 47395.833 | G25: =E25*$C$9 -> 47395.833 | H25: =F25-G25 -> 0 | I25: =E25-H25 -> 8750000
... B132: =B131+1 -> 120 | C132: =CEILING(B132/12,1) -> 10 | D132: =IF(B132<=$C$7,"IO","Amort") -> Amort | E132: =I131 -> 7770674.1 | F132: =IF(D132="IO",E132*$C$9,$C$10) -> 55305.952 | G132: =E132*$C$9 -> 42091.151 | H132: =F132-G132 -> 13214.801 | I132: =E132-H132 -> 7757459.3

Sheet Inputs
A1: MULTIFAMILY ACQUISITION — INPUTS
A2: All inputs below drive the model. Blue = hardcoded input. Black = formula output.
A4: ACQUISITION & PROPERTY
A5: Property Name | B5: Sample Multifamily
A6: Acquisition Price ($) | B6: 12500000
A7: Closing Costs (%) | B7: 0.02
A8: Closing Costs ($) | B8: =B6*B7 -> 250000
A9: Total Acquisition Cost ($) | B9: =B6+B8 -> 12750000
A11: UNIT MIX & RENT SCHEDULE
A12: Unit Type | B12: Beds | C12: Baths | D12: # Units | E12: Avg SF | F12: Avg Rent / Mo ($) | G12: Mo Revenue ($) | H12: Ann Revenue ($)
A13: Studio | B13: 0 | C13: 1 | D13: 10 | E13: 550 | F13: 1800 | G13: =D13*F13 -> 18000 | H13: =G13*12 -> 216000
A14: 1BR / 1BA | B14: 1 | C14: 1 | D14: 35 | E14: 700 | F14: 2150 | G14: =D14*F14 -> 75250 | H14: =G14*12 -> 903000
A15: 2BR / 1BA | B15: 2 | C15: 1 | D15: 20 | E15: 900 | F15: 2500 | G15: =D15*F15 -> 50000 | H15: =G15*12 -> 600000
A16: 2BR / 2BA | B16: 2 | C16: 2 | D16: 15 | E16: 950 | F16: 2650 | G16: =D16*F16 -> 39750 | H16: =G16*12 -> 477000
A17: 3BR / 2BA | B17: 3 | C17: 2 | D17: 10 | E17: 1100 | F17: 3100 | G17: =D17*F17 -> 31000 | H17: =G17*12 -> 372000
A18: 4BR / 2BA | B18: 4 | C18: 2 | D18: 7 | E18: 1300 | F18: 3600 | G18: =D18*F18 -> 25200 | H18: =G18*12 -> 302400
A19: 5BR / 3BA | B19: 5 | C19: 3 | D19: 3 | E19: 1500 | F19: 4200 | G19: =D19*F19 -> 12600 | H19: =G19*12 -> 151200
A20: TOTALS | D20: =SUM(D13:D19) -> 100 | E20: =SUMPRODUCT(D13:D19,E13:E19)/SUM(D13:D19) -> 868.5 | F20: =SUMPRODUCT(D13:D19,F13:F19)/SUM(D13:D19) -> 2518 | G20: =SUM(G13:G19) -> 251800 | H20: =SUM(H13:H19) -> 3021600
A22: Total Units (auto) | B22: =D20 -> 100
A23: Gross Potential Rent / Yr ($) | B23: =H20 -> 3021600
A25: RENOVATION
A26: Renovation Cost / Unit ($) | B26: 15000
A27: Total Renovation Budget ($) | B27: =B26*B22 -> 1500000
A29: REVENUE ASSUMPTIONS
A30: Vacancy & Credit Loss (%) | B30: 0.07
A31: Other Income / Unit / Month ($) | B31: 75
A33: OPERATING EXPENSES
A34: Real Estate Taxes / Unit / Yr ($) | B34: 2400
A35: Insurance / Unit / Yr ($) | B35: 900
A36: Management Fee (% of EGI) | B36: 0.05
A37: Repairs & Maintenance / Unit / Yr ($) | B37: 1200
A38: CapEx Reserve / Unit / Yr ($) | B38: 300
A39: OpEx Growth Rate (%) | B39: 0.03
A41: DEBT ASSUMPTIONS
A42: Loan Type | B42: Agency/Perm
A43: LTV (%) | B43: 0.7
A44: Loan Amount ($) | B44: =B6*B43 -> 8750000
A45: Interest Rate (%) | B45: 0.065
A46: IO Period (Months) | B46: 24
A47: Amortization (Years) | B47: 30
A48: Loan Term (Years) | B48: 10
A49: Origination Fee (%) | B49: 0.01
A50: Origination Fee ($) | B50: =B44*B49 -> 87500
A52: HOLD PERIOD & EXIT
A53: Hold Period (Years) | B53: 5
A54: Exit Cap Rate (%) | B54: 0.06
A55: Selling Costs (%) | B55: 0.02
A57: GP/LP STRUCTURE
A58: GP Co-Invest (%) | B58: 0.1
A59: LP Pref Return (%) | B59: 0.08
A60: GP Promote Above Pref (%) | B60: 0.2
A62: RENT GROWTH BY YEAR
A63: Year 1 | B63: 0.03
A64: Year 2 | B64: 0.03
A65: Year 3 | B65: 0.025
A66: Year 4 | B66: 0.025
A67: Year 5 | B67: 0.025
A68: Year 6 | B68: 0.02
A69: Year 7 | B69: 0.02
A70: Year 8 | B70: 0.02
A71: Year 9 | B71: 0.02
A72: Year 10 | B72: 0.02
A74: EQUITY SUMMARY
A75: Total Equity Required ($) | B75: =B9+B27-B44+B50 -> 5587500
A76: GP Equity ($) | B76: =B75*B58 -> 558750
A77: LP Equity ($) | B77: =B75-B76 -> 5028750

Sheet ZZZOLD
